Workbook

Sheet Contents
B2: October 2026 Economic and fiscal outlook – detailed forecast tables: economy
B3: Table 1.1: GDP Expenditure Components (Chain-Linked Volumes)
B4: Table 1.2: GDP Expenditure Components (Current Prices)
B5: Table 1.3: GDP Income Components
B6: Table 1.4: Nominal GDP (non-seasonally adjusted)
B7: Table 1.5: Per capita (age +16)
B8: Table 1.6: Labour Market
B9: Table 1.7: Inflation
B10: Table 1.8: Balance of Payments
B11: Table 1.9: Market-derived assumptions
B12: Table 1.10: Financial Balances by Sector
B13: Table 1.11: Balance Sheets and Lending
... B24: Table 1.20 Electricity price forecast

Sheet 1.1
A1: Back to contents
B2: 1.1 GDP expenditure components (£ billion chain-linked volumes, seasonally adjusted)
C3: Private consumption | D3: Government consumption | E3: Fixed investment | J3: Net acquisition of valuables | K3: Final domestic demand | L3: Change in inventories | M3: Total domestic demand | N3: Exports | O3: Total final expenditure | P3: Imports | Q3: Statistical discrepancy | R3: Real GDP | S3: Non-oil GVA
E4: of which: | F4: Business investment | G4: Private dwellings | H4: General government | I4: Public corps dwellings
B5: 2008Q1 | C5: 366.795 | D5: 115.993 | E5: 101.666 | F5: 52.099 | G5: 31.883 | H5: 16.775 | I5: 1.784 | J5: 0.505 | K5: 584.959 | L5: -4.672 | M5: 580.287 | N5: 168.251 | O5: 756.225 | P5: 169.186 | Q5: 0 | R5: 586.69 | S5: 513.251
B6: 2008Q2 | C6: 362.064 | D6: 115.307 | E6: 103.272 | F6: 57.108 | G6: 30.069 | H6: 15.255 | I6: 1.66 | J6: -0.216 | K6: 580.427 | L6: -0.281 | M6: 580.146 | N6: 168.428 | O6: 752.599 | P6: 168.738 | Q6: 0 | R6: 583.541 | S6: 511.331
B7: 2008Q3 | C7: 356.567 | D7: 117.362 | E7: 98.198 | F7: 54.942 | G7: 24.559 | H7: 15.861 | I7: 3.419 | J7: -1.304 | K7: 570.823 | L7: -0.858 | M7: 569.965 | N7: 169.106 | O7: 738.868 | P7: 164.573 | Q7: 0 | R7: 573.961 | S7: 503.224
B8: 2008Q4 | C8: 347.875 | D8: 118.565 | E8: 96.036 | F8: 52.434 | G8: 23.384 | H8: 17.411 | I8: 3.329 | J8: 0.241 | K8: 562.717 | L8: -2.768 | M8: 559.949 | N8: 161.069 | O8: 717.793 | P8: 155.485 | Q8: 0 | R8: 561.816 | S8: 492.727
B9: 2009Q1 | C9: 346.435 | D9: 117.859 | E9: 90.795 | F9: 48.456 | G9: 21.958 | H9: 17.521 | I9: 3.285 | J9: 1.402 | K9: 556.491 | L9: -7.604 | M9: 548.887 | N9: 152.669 | O9: 700.234 | P9: 149.466 | Q9: 0 | R9: 550.451 | S9: 483.023
B10: 2009Q2 | C10: 345.972 | D10: 117.61 | E10: 87.418 | F10: 46.751 | G10: 21.178 | H10: 16.507 | I10: 3.256 | J10: 0.533 | K10: 551.533 | L10: -7.752 | M10: 543.781 | N10: 151.805 | O10: 698.826 | P10: 149.706 | Q10: 0 | R10: 548.859 | S10: 480.942
B11: 2009Q3 | C11: 347.113 | D11: 118.717 | E11: 87.976 | F11: 45.581 | G11: 21.321 | H11: 18.129 | I11: 3.289 | J11: 0.773 | K11: 554.579 | L11: -8.53 | M11: 546.049 | N11: 151.597 | O11: 703.47 | P11: 153.651 | Q11: 0 | R11: 549.54 | S11: 482.029
B12: 2009Q4 | C12: 349.909 | D12: 119.548 | E12: 86.66 | F12: 45.414 | G12: 20.128 | H12: 17.924 | I12: 3.378 | J12: -0.322 | K12: 555.795 | L12: -5.121 | M12: 550.674 | N12: 157.882 | O12: 709.156 | P12: 157.472 | Q12: 0 | R12: 551.372 | S12: 484.18
B13: 2010Q1 | C13: 349.45 | D13: 117.946 | E13: 90.007 | F13: 47.159 | G13: 20.935 | H13: 18.677 | I13: 3.422 | J13: -0.48 | K13: 556.923 | L13: -2.406 | M13: 554.517 | N13: 157.938 | O13: 715.447 | P13: 159.135 | Q13: 0 | R13: 556.002 | S13: 488.699
B14: 2010Q2 | C14: 358.968 | D14: 118.254 | E14: 87.938 | F14: 46.055 | G14: 21.505 | H14: 17.329 | I14: 3.4 | J14: -0.745 | K14: 564.415 | L14: -1.128 | M14: 563.287 | N14: 162.473 | O14: 726.669 | P14: 163.978 | Q14: 0 | R14: 562.353 | S14: 494.936
B15: 2010Q3 | C15: 359.801 | D15: 118.609 | E15: 90.701 | F15: 47.527 | G15: 22.204 | H15: 17.948 | I15: 3.383 | J15: 0.346 | K15: 569.457 | L15: -0.989 | M15: 568.468 | N15: 164.197 | O15: 735.142 | P15: 169.102 | Q15: 0 | R15: 565.659 | S15: 498.167
B16: 2010Q4 | C16: 358.905 | D16: 118.817 | E16: 92.57 | F16: 50.337 | G16: 21.612 | H16: 17.522 | I16: 3.262 | J16: 0.364 | K16: 570.656 | L16: -2.502 | M16: 568.154 | N16: 167.102 | O16: 737.228 | P16: 170.871 | Q16: 0 | R16: 565.945 | S16: 498.906
... B101: 2032Q1 | C101: 473.59318 | D101: 164.04245 | E101: 151.74559 | F101: 81.741768 | G101: 40.515358 | H101: 26.961891 | I101: 2.5265711 | J101: 4.162 | K101: 793.54321 | L101: 1.4223616 | M101: 794.96557 | N101: 244.1829 | O101: 1039.1485 | P101: 261.05619 | Q101: -0.692 | R101: 777.40028 | S101: 703.06406
B102: 2008 | C102: 1433.301 | D102: 467.227 | E102: 399.172 | F102: 216.583 | G102: 109.895 | H102: 65.302 | I102: 10.192 | J102: -0.774 | K102: 2298.926 | L102: -8.579 | M102: 2290.347 | N102: 666.854 | O102: 2965.485 | P102: 657.982 | Q102: 0 | R102: 2306.008 | S102: 2020.533
B103: 2009 | C103: 1389.429 | D103: 473.734 | E103: 352.849 | F103: 186.202 | G103: 84.585 | H103: 70.081 | I103: 13.208 | J103: 2.386 | K103: 2218.398 | L103: -29.007 | M103: 2189.391 | N103: 613.953 | O103: 2811.686 | P103: 610.295 | Q103: 0 | R103: 2200.222 | S103: 1930.174
B104: 2010 | C104: 1427.124 | D104: 473.626 | E104: 361.216 | F104: 191.078 | G104: 86.256 | H104: 71.476 | I104: 13.467 | J104: -0.515 | K104: 2261.451 | L104: -7.025 | M104: 2254.426 | N104: 651.71 | O104: 2914.486 | P104: 663.086 | Q104: 0 | R104: 2249.959 | S104: 1980.708
B105: 2011 | C105: 1418.187 | D105: 472.11 | E105: 360.603 | F105: 199.419 | G105: 82.73 | H105: 66.506 | I105: 12.301 | J105: -0.775 | K105: 2250.125 | L105: 0.43 | M105: 2250.555 | N105: 695.989 | O105: 2952.109 | P105: 681.262 | Q105: 0 | R105: 2269.116 | S105: 2007.666
B106: 2012 | C106: 1446.168 | D106: 479.021 | E106: 367.983 | F106: 211.73 | G106: 82.477 | H106: 61.929 | I106: 11.296 | J106: -1.609 | K106: 2291.563 | L106: 4.545 | M106: 2296.108 | N106: 699.711 | O106: 3002.459 | P106: 696.649 | Q106: 0 | R106: 2303.794 | S106: 2049.074
B107: 2013 | C107: 1477.994 | D107: 479.189 | E107: 383.415 | F107: 221.254 | G107: 92.359 | H107: 58.295 | I107: 10.777 | J107: 6.577 | K107: 2347.175 | L107: 0.648 | M107: 2347.823 | N107: 702.7 | O107: 3064.553 | P107: 718.796 | Q107: 0 | R107: 2343.384 | S107: 2087.782
B108: 2014 | C108: 1518.913 | D108: 490.334 | E108: 411.507 | F108: 235.726 | G108: 97.12 | H108: 65.43 | I108: 12.568 | J108: 4.943 | K108: 2425.697 | L108: 20.925 | M108: 2446.622 | N108: 712.184 | O108: 3175.387 | P108: 755.205 | Q108: 0 | R108: 2417.439 | S108: 2155.831
B109: 2015 | C109: 1563.941 | D109: 495.189 | E109: 439.379 | F109: 256.423 | G109: 103.508 | H109: 66.528 | I109: 12.047 | J109: -0.831 | K109: 2497.678 | L109: 8.939 | M109: 2506.617 | N109: 738.202 | O109: 3263.96 | P109: 792.45 | Q109: 0 | R109: 2469.182 | S109: 2195.071
B110: 2016 | C110: 1619.767 | D110: 499.524 | E110: 466.345 | F110: 276.239 | G110: 111.832 | H110: 65.012 | I110: 12.218 | J110: -0.412 | K110: 2585.224 | L110: -15.807 | M110: 2569.417 | N110: 765.88 | O110: 3352.776 | P110: 827.957 | Q110: 0 | R110: 2523.665 | S110: 2244.315
B111: 2017 | C111: 1653.27 | D111: 504.596 | E111: 484.361 | F111: 278.862 | G111: 121.82 | H111: 71.075 | I111: 12.088 | J111: -0.766 | K111: 2641.461 | L111: -6.229 | M111: 2635.232 | N111: 815.172 | O111: 3454.44 | P111: 853.305 | Q111: 0 | R111: 2599.961 | S111: 2315.596
B112: 2018 | C112: 1687.414 | D112: 507.841 | E112: 483.363 | F112: 276.188 | G112: 130.036 | H112: 70.542 | I112: 6.334 | J112: 1.699 | K112: 2680.317 | L112: -1.5 | M112: 2678.817 | N112: 846.41 | O112: 3523.695 | P112: 882.424 | Q112: 0 | R112: 2640.295 | S112: 2348.685
B113: 2019 | C113: 1706.496 | D113: 522.794 | E113: 492.227 | F113: 280.224 | G113: 132.696 | H113: 72.89 | I113: 6.0812308 | J113: 1.436 | K113: 2722.953 | L113: -1.02 | M113: 2721.933 | N113: 862.521 | O113: 3583.95 | P113: 909.625 | Q113: 0 | R113: 2673.465 | S113: 2381.148
... B125: 2031 | C125: 1876.2601 | D125: 650.72528 | E125: 602.49594 | F125: 324.32765 | G125: 159.73015 | H125: 108.50606 | I125: 9.93208 | J125: 16.648 | K125: 3146.1293 | L125: 4.969321 | M125: 3151.0987 | N125: 969.55014 | O125: 4120.6488 | P125: 1036.9715 | Q125: -2.768 | R125: 3080.9093 | S125: 2785.3842
B126: 2008-09 | C126: 1412.941 | D126: 469.093 | E126: 388.301 | F126: 212.94 | G126: 99.97 | H126: 66.048 | I126: 11.693 | J126: 0.123 | K126: 2270.458 | L126: -11.511 | M126: 2258.947 | N126: 651.272 | O126: 2909.494 | P126: 638.262 | Q126: 0 | R126: 2269.769 | S126: 1990.305
B127: 2009-10 | C127: 1392.444 | D127: 473.821 | E127: 352.061 | F127: 184.905 | G127: 83.562 | H127: 71.237 | I127: 13.345 | J127: 0.504 | K127: 2218.83 | L127: -23.809 | M127: 2195.021 | N127: 619.222 | O127: 2826.899 | P127: 619.964 | Q127: 0 | R127: 2205.773 | S127: 1935.85
B128: 2010-11 | C128: 1432.915 | D128: 474.904 | E128: 360.567 | F128: 190.979 | G128: 86.298 | H128: 71.25 | I128: 13.206 | J128: -2.813 | K128: 2265.573 | L128: -4.686 | M128: 2260.887 | N128: 669.16 | O128: 2933.663 | P128: 671.346 | Q128: 0 | R128: 2260.83 | S128: 1992.087
B129: 2011-12 | C129: 1417.864 | D129: 474.358 | E129: 364.452 | F129: 206.141 | G129: 81.576 | H129: 64.597 | I129: 11.977 | J129: -0.13 | K129: 2256.544 | L129: -5.038 | M129: 2251.506 | N129: 701.65 | O129: 2964.894 | P129: 687.367 | Q129: 0 | R129: 2275.659 | S129: 2016.794
B130: 2012-13 | C130: 1456.88 | D130: 476.464 | E130: 367.582 | F130: 211.68 | G130: 84.167 | H130: 59.997 | I130: 11.248 | J130: 1.278 | K130: 2302.204 | L130: 9.344 | M130: 2311.548 | N130: 694.342 | O130: 3008.674 | P130: 696.599 | Q130: 0 | R130: 2310.127 | S130: 2056.462
B131: 2013-14 | C131: 1485.969 | D131: 482.447 | E131: 391.595 | F131: 224.303 | G131: 95.087 | H131: 60.709 | I131: 10.787 | J131: 6.848 | K131: 2366.859 | L131: 1.477 | M131: 2368.336 | N131: 702.864 | O131: 3091.332 | P131: 728.399 | Q131: 0 | R131: 2360.331 | S131: 2102.784
B132: 2014-15 | C132: 1532.817 | D132: 490.519 | E132: 420.537 | F132: 242.948 | G132: 97.726 | H132: 66.023 | I132: 13.09 | J132: 6.385 | K132: 2450.258 | L132: 25.945 | M132: 2476.203 | N132: 717.582 | O132: 3207.738 | P132: 771.184 | Q132: 0 | R132: 2433.819 | S132: 2170.395
B133: 2015-16 | C133: 1577.102 | D133: 497.553 | E133: 442.761 | F133: 261.559 | G133: 105.417 | H133: 63.153 | I133: 11.724 | J133: -2.874 | K133: 2514.542 | L133: -1.845 | M133: 2512.697 | N133: 745.131 | O133: 3280.497 | P133: 797.216 | Q133: 0 | R133: 2481.205 | S133: 2204.23
B134: 2016-17 | C134: 1630.199 | D134: 500.049 | E134: 471.326 | F134: 276.504 | G134: 114.953 | H134: 66.582 | I134: 12.315 | J134: -1.797 | K134: 2599.777 | L134: -12.356 | M134: 2587.421 | N134: 776.567 | O134: 3375.12 | P134: 832.926 | Q134: 0 | R134: 2541.029 | S134: 2261.286
B135: 2017-18 | C135: 1661.473 | D135: 505.834 | E135: 488.823 | F135: 280.546 | G135: 123.854 | H135: 73.337 | I135: 10.667 | J135: 0.262 | K135: 2656.392 | L135: -6.743 | M135: 2649.649 | N135: 825.668 | O135: 3476.53 | P135: 860.204 | Q135: 0 | R135: 2615.239 | S135: 2328.357
B136: 2018-19 | C136: 1694.832 | D136: 510.194 | E136: 484.947 | F136: 274.929 | G136: 132.073 | H136: 71.535 | I136: 6.1691512 | J136: 13.868 | K136: 2703.841 | L136: 10.005 | M136: 2713.846 | N136: 847.958 | O136: 3561.413 | P136: 912.718 | Q136: 0 | R136: 2648.01 | S136: 2355.839
B137: 2019-20 | C137: 1693.402 | D137: 523.336 | E137: 484.933 | F137: 278.852 | G137: 129.036 | H137: 70.716 | I137: 6.0650272 | J137: -10.111 | K137: 2691.56 | L137: -13.14 | M137: 2678.42 | N137: 858.752 | O137: 3536.522 | P137: 874.999 | Q137: 0 | R137: 2660.189 | S137: 2371.79
... B149: 2031-32 | C149: 1883.4913 | D149: 653.00483 | E149: 604.36277 | F149: 325.38336 | G149: 160.69762 | H149: 108.27828 | I149: 10.003519 | J149: 16.648 | K149: 3157.5069 | L149: 5.2117891 | M149: 3162.7186 | N149: 972.44082 | O149: 4135.1595 | P149: 1039.8654 | Q149: -2.768 | R149: 3092.5261 | S149: 2796.2643
B150: Definitions:
B151: Household and non-profit institutions serving households final consumption expenditure (ONS Economic Accounts Table 1.1.2, identifier: ABJR + HAYO)
B152: General government final consumption (ONS Economic Accounts Table 1.1.2, identifier: NMRY)
B153: Total gross fixed capital formation (ONS Economic Accounts Table 1.1.2, identifier: NPQT)
B154: Business investment (ONS Economic Accounts Table 1.1.8, identifier: NPEL)
B155: Private sector investment in dwellings, including transfer costs (ONS Economic Accounts Table 1.1.8, identifier: L636 + L637)
B156: General government gross fixed capital formation (ONS Economic Accounts Table 1.1.8, identifier: DLWF)
B157: Public corporations investment in dwellings, including transfer costs (ONS Economic Accounts Table 1.1.8, identifier: L634 + L635)
B158: Net acquisitions of valuables (ONS Economic Accounts Table 1.1.2, identifier: NPJR)
B159: Final domestic demand is the sum of private consumption, government consumption, fixed investment and net acquisition of valuables
B160: Change in inventories (ONS Economic Accounts Table 1.1.2, identifier: CAFU)
B161: Total domestic demand is the sum of final domestic demand and change in inventories
... B166: Gross domestic product at market prices (ONS Economic Accounts Table 1.1.2, identifier: ABMI)

Sheet 1.2
A1: Back to contents
B2: 1.2 GDP expenditure components (£ billion current prices, seasonally adjusted)
C3: Private consumption | D3: Government consumption | E3: Fixed investment | G3: Net acquisition of valuables | H3: Final domestic demand | I3: Change in inventories | J3: Total domestic demand | K3: Exports | L3: Total final expenditure | M3: Imports | N3: Statistical discrepancy | O3: GDP at market prices | P3: Gross national income
E4: of which: | F4: General government
B5: 2008Q1 | C5: 254.939 | D5: 79.563 | E5: 74.277 | F5: 12.181 | G5: 0.314 | H5: 409.093 | I5: 0.18 | J5: 409.273 | K5: 105.083 | L5: 514.356 | M5: 114.64 | N5: 0 | O5: 399.716 | P5: 399.097
B6: 2008Q2 | C6: 255.557 | D6: 79.825 | E6: 76.1 | F6: 11.29 | G6: -0.157 | H6: 411.325 | I6: -0.41 | J6: 410.915 | K6: 110.79 | L6: 521.705 | M6: 119.018 | N6: 0 | O6: 402.687 | P6: 397.924
B7: 2008Q3 | C7: 255.126 | D7: 80.711 | E7: 72.954 | F7: 11.788 | G7: -0.657 | H7: 408.134 | I7: 0.503 | J7: 408.637 | K7: 113.068 | L7: 521.705 | M7: 119.568 | N7: 0 | O7: 402.137 | P7: 397.712
B8: 2008Q4 | C8: 247.459 | D8: 82.893 | E8: 71.679 | F8: 12.839 | G8: 0.281 | H8: 402.312 | I8: -2.04 | J8: 400.272 | K8: 109.737 | L8: 510.009 | M8: 112.332 | N8: 0 | O8: 397.677 | P8: 386.453
B9: 2009Q1 | C9: 247.016 | D9: 83.663 | E9: 68.481 | F9: 13.247 | G9: 1.249 | H9: 400.409 | I9: -5.806 | J9: 394.603 | K9: 103.777 | L9: 498.38 | M9: 108.605 | N9: 0 | O9: 389.775 | P9: 382.791
B10: 2009Q2 | C10: 247.047 | D10: 83.757 | E10: 65.661 | F10: 12.177 | G10: 0.525 | H10: 396.99 | I10: -3.24 | J10: 393.75 | K10: 101.784 | L10: 495.534 | M10: 106.383 | N10: 0 | O10: 389.151 | P10: 383.333
B11: 2009Q3 | C11: 248.1 | D11: 85.714 | E11: 66.14 | F11: 13.441 | G11: 0.567 | H11: 400.521 | I11: -3.5 | J11: 397.021 | K11: 102.676 | L11: 499.697 | M11: 108.518 | N11: 0 | O11: 391.179 | P11: 392.017
B12: 2009Q4 | C12: 248.74 | D12: 85.393 | E12: 64.643 | F12: 13.095 | G12: -0.012 | H12: 398.764 | I12: -5.412 | J12: 393.352 | K12: 108.239 | L12: 501.591 | M12: 112.291 | N12: 0 | O12: 389.3 | P12: 388.252
B13: 2010Q1 | C13: 248.576 | D13: 86.36 | E13: 66.662 | F13: 13.45 | G13: -0.258 | H13: 401.34 | I13: 2.097 | J13: 403.437 | K13: 110.63 | L13: 514.067 | M13: 115.941 | N13: 0 | O13: 398.126 | P13: 398.272
B14: 2010Q2 | C14: 257.23 | D14: 86.009 | E14: 65.37 | F14: 12.504 | G14: -0.362 | H14: 408.247 | I14: -0.069 | J14: 408.178 | K14: 116.022 | L14: 524.2 | M14: 121.263 | N14: 0 | O14: 402.937 | P14: 403.384
B15: 2010Q3 | C15: 259.625 | D15: 86.02 | E15: 67.39 | F15: 12.903 | G15: 0.443 | H15: 413.478 | I15: 0.516 | J15: 413.994 | K15: 116.673 | L15: 530.667 | M15: 124.49 | N15: 0 | O15: 406.177 | P15: 405.649
B16: 2010Q4 | C16: 261.581 | D16: 87.098 | E16: 68.691 | F16: 12.449 | G16: 0.574 | H16: 417.944 | I16: -2.532 | J16: 415.412 | K16: 121.17 | L16: 536.582 | M16: 127.983 | N16: 0 | O16: 408.599 | P16: 409.241
... B101: 2032Q1 | C101: 587.65387 | D101: 198.96622 | E101: 178.58878 | F101: 32.528326 | G101: 4.7625579 | H101: 969.97143 | I101: 1.3916884 | J101: 971.36312 | K101: 280.47456 | L101: 1251.8377 | M101: 288.78165 | N101: -0.85648292 | O101: 962.19955 | P101: 952.31909
B102: 2008 | C102: 1013.081 | D102: 322.992 | E102: 295.01 | F102: 48.098 | G102: -0.219 | H102: 1630.864 | I102: -1.767 | J102: 1629.097 | K102: 438.678 | L102: 2067.775 | M102: 465.558 | N102: 0 | O102: 1602.217 | P102: 1581.186
B103: 2009 | C103: 990.903 | D103: 338.527 | E103: 264.925 | F103: 51.96 | G103: 2.329 | H103: 1596.684 | I103: -17.958 | J103: 1578.726 | K103: 416.476 | L103: 1995.202 | M103: 435.797 | N103: 0 | O103: 1559.405 | P103: 1546.393
B104: 2010 | C104: 1027.012 | D104: 345.487 | E104: 268.113 | F104: 51.306 | G104: 0.397 | H104: 1641.009 | I104: 0.012 | J104: 1641.021 | K104: 464.495 | L104: 2105.516 | M104: 489.677 | N104: 0 | O104: 1615.839 | P104: 1616.546
B105: 2011 | C105: 1060.307 | D105: 347.499 | E105: 270.216 | F105: 47.833 | G105: 1.049 | H105: 1679.071 | I105: 4.137 | J105: 1683.208 | K105: 522.107 | L105: 2205.315 | M105: 535.37 | N105: 0 | O105: 1669.945 | P105: 1676.89
B106: 2012 | C106: 1099.217 | D106: 354.855 | E106: 280.159 | F106: 45.52 | G106: 0.217 | H106: 1734.448 | I106: 3.957 | J106: 1738.405 | K106: 525.113 | L106: 2263.518 | M106: 541.81 | N106: 0 | O106: 1721.708 | P106: 1705.748
B107: 2013 | C107: 1148.293 | D107: 356.935 | E107: 296.889 | F107: 43.729 | G107: 7.139 | H107: 1809.256 | I107: 3.151 | J107: 1812.407 | K107: 540.436 | L107: 2352.843 | M107: 563.771 | N107: 0 | O107: 1789.072 | P107: 1757.503
B108: 2014 | C108: 1194.143 | D108: 368.248 | E108: 322.1 | F108: 50.207 | G108: 6.017 | H108: 1890.508 | I108: 17.503 | J108: 1908.011 | K108: 534.994 | L108: 2443.005 | M108: 567.939 | N108: 0 | O108: 1875.066 | P108: 1841.794
B109: 2015 | C109: 1225.459 | D109: 372.7 | E109: 346.078 | F109: 51.638 | G109: 0.81 | H109: 1945.047 | I109: 9.323 | J109: 1954.37 | K109: 537.513 | L109: 2491.883 | M109: 563.867 | N109: 0 | O109: 1928.016 | P109: 1886.247
B110: 2016 | C110: 1285.036 | D110: 381.332 | E110: 372.262 | F110: 51.356 | G110: 1.341 | H110: 2039.971 | I110: -0.806 | J110: 2039.165 | K110: 582.613 | L110: 2621.778 | M110: 617.023 | N110: 0 | O110: 2004.755 | P110: 1958.022
B111: 2017 | C111: 1334.709 | D111: 387.331 | E111: 397.794 | F111: 57.575 | G111: 0.664 | H111: 2120.498 | I111: 2.777 | J111: 2123.275 | K111: 649.59 | L111: 2772.865 | M111: 675.643 | N111: 0 | O111: 2097.222 | P111: 2074.819
B112: 2018 | C112: 1389.908 | D112: 397.819 | E112: 405.867 | F112: 58.385 | G112: 2.564 | H112: 2196.158 | I112: 1.475 | J112: 2197.633 | K112: 691.74 | L112: 2889.373 | M112: 717.814 | N112: 0 | O112: 2171.559 | P112: 2142.305
B113: 2019 | C113: 1425.544 | D113: 425.699 | E113: 424.262 | F113: 62.246 | G113: 2.582 | H113: 2278.087 | I113: 1.861 | J113: 2279.948 | K113: 718.759 | L113: 2998.707 | M113: 745.746 | N113: 0 | O113: 2252.961 | P113: 2250.702
... B125: 2031 | C125: 2299.5554 | D125: 782.74731 | E125: 701.93424 | F125: 128.96568 | G125: 19.347404 | H125: 3803.5843 | I125: 4.8071886 | J125: 3808.3915 | K125: 1101.5655 | L125: 4909.957 | M125: 1136.4648 | N125: -3.3871141 | O125: 3770.1051 | P125: 3731.3875
B126: 2008-09 | C126: 1005.158 | D126: 327.092 | E126: 289.214 | F126: 49.164 | G126: 0.716 | H126: 1622.18 | I126: -7.753 | J126: 1614.427 | K126: 437.372 | L126: 2051.799 | M126: 459.523 | N126: 0 | O126: 1592.276 | P126: 1564.88
B127: 2009-10 | C127: 992.463 | D127: 341.224 | E127: 263.106 | F127: 52.163 | G127: 0.822 | H127: 1597.615 | I127: -10.055 | J127: 1587.56 | K127: 423.329 | L127: 2010.889 | M127: 443.133 | N127: 0 | O127: 1567.756 | P127: 1561.874
B128: 2010-11 | C128: 1041.899 | D128: 348.11 | E128: 267.9 | F128: 51.138 | G128: -1.04 | H128: 1656.869 | I128: -3.154 | J128: 1653.715 | K128: 482.822 | L128: 2136.537 | M128: 502.303 | N128: 0 | O128: 1634.234 | P128: 1636.499
B129: 2011-12 | C129: 1065.828 | D129: 349.131 | E129: 274.396 | F129: 46.127 | G129: 1.557 | H129: 1690.912 | I129: 2.817 | J129: 1693.729 | K129: 529.283 | L129: 2223.012 | M129: 542.935 | N129: 0 | O129: 1680.077 | P129: 1682.844
B130: 2012-13 | C130: 1112.428 | D130: 353.227 | E130: 280.71 | F130: 44.755 | G130: 2.297 | H130: 1748.662 | I130: 5.174 | J130: 1753.836 | K130: 524.54 | L130: 2278.376 | M130: 543.283 | N130: 0 | O130: 1735.093 | P130: 1710.732
B131: 2013-14 | C131: 1159.003 | D131: 360.299 | E131: 304.383 | F131: 45.922 | G131: 7.604 | H131: 1831.289 | I131: 6.23 | J131: 1837.519 | K131: 538.348 | L131: 2375.867 | M131: 566.151 | N131: 0 | O131: 1809.716 | P131: 1783.162
B132: 2014-15 | C132: 1203.786 | D132: 368.998 | E132: 329.509 | F132: 50.694 | G132: 7.102 | H132: 1909.395 | I132: 19.405 | J132: 1928.8 | K132: 535.152 | L132: 2463.952 | M132: 571.552 | N132: 0 | O132: 1892.4 | P132: 1854.969
B133: 2015-16 | C133: 1238.243 | D133: 374.606 | E133: 349.576 | F133: 49.42 | G133: -0.851 | H133: 1961.574 | I133: 4.835 | J133: 1966.409 | K133: 541.98 | L133: 2508.389 | M133: 565.745 | N133: 0 | O133: 1942.644 | P133: 1896.09
B134: 2016-17 | C134: 1299.243 | D134: 383.073 | E134: 378.293 | F134: 52.926 | G134: -0.204 | H134: 2060.405 | I134: 1.992 | J134: 2062.397 | K134: 603.394 | L134: 2665.791 | M134: 636.374 | N134: 0 | O134: 2029.417 | P134: 1992.981
B135: 2017-18 | C135: 1348.299 | D135: 389.044 | E135: 403.7 | F135: 59.458 | G135: 1.619 | H135: 2142.662 | I135: -0.969 | J135: 2141.693 | K135: 658.297 | L135: 2799.99 | M135: 684.911 | N135: 0 | O135: 2115.079 | P135: 2088.597
B136: 2018-19 | C136: 1400.539 | D136: 401.905 | E136: 410.625 | F136: 59.839 | G136: 13.702 | H136: 2226.771 | I136: 8.568 | J136: 2235.339 | K136: 698.174 | L136: 2933.513 | M136: 743.133 | N136: 0 | O136: 2190.38 | P136: 2169.141
B137: 2019-20 | C137: 1417.254 | D137: 432.042 | E137: 420.715 | F137: 60.875 | G137: -7.958 | H137: 2262.053 | I137: -4.51 | J137: 2257.543 | K137: 718.387 | L137: 2975.93 | M137: 717.588 | N137: 0 | O137: 2258.342 | P137: 2247.882
... B149: 2031-32 | C149: 2319.8873 | D149: 788.22905 | E149: 706.90316 | F149: 129.46649 | G149: 19.336763 | H149: 3834.3563 | I149: 5.065561 | J149: 3839.4218 | K149: 1109.6931 | L149: 4949.115 | M149: 1143.9149 | N149: -3.4027418 | O149: 3801.7973 | P149: 3762.8682
B150: Definitions:
B151: Household and non-profit institutions serving households final consumption expenditure (ONS Economic Accounts Table 1.1.2, identifier: ABJQ + HAYE)
B152: General government final consumption (ONS Economic Accounts Table 1.1.2, identifier: NMRP)
B153: Total gross fixed capital formation (ONS Economic Accounts Table 1.1.2, identifier: NPQS)
B154: General government investment (ONS Economic Accounts Table 1.1.8, identifier: RPZG)
B155: Net acquisitions of valuables (ONS Economic Accounts Table 1.1.2, identifier: NPJQ)
B156: Final domestic demand is the sum of private consumption, government consumption, fixed investment and net acquisition of valuables
B157: Change in inventories (ONS Economic Accounts Table 1.1.2, identifier: CAEX)
B158: Total domestic demand is the sum of final domestic demand and change in inventories
B159: Total exports (ONS Economic Accounts Table 1.1.2, identifier: IKBH)
B160: Total final expenditure (ONS Economic Accounts Table 1.1.2, identifier: ABMF)
B161: Total imports (ONS Economic Accounts Table 1.1.2, identifier: IKBI)
... B164: Gross national income at market prices (ONS Economic Accounts Table 1.1.1, identifier: ABMZ)

Sheet 1.3
A1: Back to contents
B2: 1.3 GDP income components (£ billion current prices, seasonally adjusted)
C3: Labour income | D3: Non-oil PNFC profits | E3: Other income | F3: Gross value added at factor cost | G3: Taxes on products and production less subsidies | H3: Statistical discrepancy (income) | I3: GDP at market prices
B4: 2008Q1 | C4: 191.746 | D4: 61.086 | E4: =F4-C4-D4-H4 -> 103.531 | F4: 356.363 | G4: 43.353 | H4: 0 | I4: 399.716
B5: 2008Q2 | C5: 190.831 | D5: 67.079 | E5: =F5-C5-D5-H5 -> 100.416 | F5: 358.326 | G5: 44.361 | H5: 0 | I5: 402.687
B6: 2008Q3 | C6: 189.702 | D6: 68.516 | E6: =F6-C6-D6-H6 -> 102.043 | F6: 360.261 | G6: 41.876 | H6: 0 | I6: 402.137
B7: 2008Q4 | C7: 188.656 | D7: 63.414 | E7: =F7-C7-D7-H7 -> 105.777 | F7: 357.847 | G7: 39.83 | H7: 0 | I7: 397.677
B8: 2009Q1 | C8: 186.006 | D8: 59.159 | E8: =F8-C8-D8-H8 -> 106.994 | F8: 352.159 | G8: 37.616 | H8: 0 | I8: 389.775
B9: 2009Q2 | C9: 188.824 | D9: 56.745 | E9: =F9-C9-D9-H9 -> 104.852 | F9: 350.421 | G9: 38.73 | H9: 0 | I9: 389.151
B10: 2009Q3 | C10: 188.143 | D10: 64.034 | E10: =F10-C10-D10-H10 -> 98.625 | F10: 350.802 | G10: 40.377 | H10: 0 | I10: 391.179
B11: 2009Q4 | C11: 188.557 | D11: 52.774 | E11: =F11-C11-D11-H11 -> 107.016 | F11: 348.347 | G11: 40.953 | H11: 0 | I11: 389.3
B12: 2010Q1 | C12: 188.728 | D12: 57.754 | E12: =F12-C12-D12-H12 -> 107.253 | F12: 353.735 | G12: 44.391 | H12: 0 | I12: 398.126
B13: 2010Q2 | C13: 189.62 | D13: 59.339 | E13: =F13-C13-D13-H13 -> 105.209 | F13: 354.168 | G13: 48.769 | H13: 0 | I13: 402.937
B14: 2010Q3 | C14: 191.153 | D14: 62.308 | E14: =F14-C14-D14-H14 -> 107.581 | F14: 361.042 | G14: 45.135 | H14: 0 | I14: 406.177
B15: 2010Q4 | C15: 192.214 | D15: 65.584 | E15: =F15-C15-D15-H15 -> 105.386 | F15: 363.184 | G15: 45.415 | H15: 0 | I15: 408.599
... B100: 2032Q1 | C100: 434.11094 | D100: 166.34066 | E100: =F100-C100-D100-H100 -> 262.65025 | F100: 860.60784 | G100: 101.5917 | H100: -2.494 | I100: 962.19955
B101: 2008 | C101: 760.935 | D101: 260.095 | E101: =F101-C101-D101-H101 -> 411.767 | F101: 1432.797 | G101: 169.42 | H101: 0 | I101: 1602.217
B102: 2009 | C102: 751.53 | D102: 232.712 | E102: =F102-C102-D102-H102 -> 417.487 | F102: 1401.729 | G102: 157.676 | H102: 0 | I102: 1559.405
B103: 2010 | C103: 761.715 | D103: 244.985 | E103: =F103-C103-D103-H103 -> 425.429 | F103: 1432.129 | G103: 183.71 | H103: 0 | I103: 1615.839
B104: 2011 | C104: 777.882 | D104: 254.295 | E104: =F104-C104-D104-H104 -> 437.161 | F104: 1469.338 | G104: 200.607 | H104: 0 | I104: 1669.945
B105: 2012 | C105: 789.833 | D105: 268.518 | E105: =F105-C105-D105-H105 -> 456.754 | F105: 1515.105 | G105: 206.603 | H105: 0 | I105: 1721.708
B106: 2013 | C106: 826.706 | D106: 281.556 | E106: =F106-C106-D106-H106 -> 463.186 | F106: 1571.448 | G106: 217.624 | H106: 0 | I106: 1789.072
B107: 2014 | C107: 861.13 | D107: 315.1 | E107: =F107-C107-D107-H107 -> 470.646 | F107: 1646.876 | G107: 228.19 | H107: 0 | I107: 1875.066
B108: 2015 | C108: 892.489 | D108: 325.7 | E108: =F108-C108-D108-H108 -> 476.157 | F108: 1694.346 | G108: 233.67 | H108: 0 | I108: 1928.016
B109: 2016 | C109: 923.663 | D109: 337.323 | E109: =F109-C109-D109-H109 -> 501.763 | F109: 1762.749 | G109: 242.006 | H109: 0 | I109: 2004.755
B110: 2017 | C110: 967.03 | D110: 354.319 | E110: =F110-C110-D110-H110 -> 523.4 | F110: 1844.749 | G110: 252.473 | H110: 0 | I110: 2097.222
B111: 2018 | C111: 1005.821 | D111: 367.031 | E111: =F111-C111-D111-H111 -> 539.527 | F111: 1912.379 | G111: 259.18 | H111: 0 | I111: 2171.559
B112: 2019 | C112: 1046.611 | D112: 377.657 | E112: =F112-C112-D112-H112 -> 563.195 | F112: 1987.463 | G112: 265.498 | H112: 0 | I112: 2252.961
... B124: 2031 | C124: 1704.1682 | D124: 650.13631 | E124: =F124-C124-D124-H124 -> 1026.8688 | F124: 3371.1974 | G124: 398.90772 | H124: -9.976 | I124: 3770.1051
B125: 2008-09 | C125: 755.195 | D125: 258.168 | E125: =F125-C125-D125-H125 -> 415.23 | F125: 1428.593 | G125: 163.683 | H125: 0 | I125: 1592.276
B126: 2009-10 | C126: 754.252 | D126: 231.307 | E126: =F126-C126-D126-H126 -> 417.746 | F126: 1403.305 | G126: 164.451 | H126: 0 | I126: 1567.756
B127: 2010-11 | C127: 769.119 | D127: 251.331 | E127: =F127-C127-D127-H127 -> 424.608 | F127: 1445.058 | G127: 189.176 | H127: 0 | I127: 1634.234
B128: 2011-12 | C128: 777.862 | D128: 255.264 | E128: =F128-C128-D128-H128 -> 444.423 | F128: 1477.549 | G128: 202.528 | H128: 0 | I128: 1680.077
B129: 2012-13 | C129: 793.358 | D129: 276.714 | E129: =F129-C129-D129-H129 -> 456.878 | F129: 1526.95 | G129: 208.143 | H129: 0 | I129: 1735.093
B130: 2013-14 | C130: 842.425 | D130: 281.338 | E130: =F130-C130-D130-H130 -> 464.487 | F130: 1588.25 | G130: 221.466 | H130: 0 | I130: 1809.716
B131: 2014-15 | C131: 865.081 | D131: 324.665 | E131: =F131-C131-D131-H131 -> 473.755 | F131: 1663.501 | G131: 228.899 | H131: 0 | I131: 1892.4
B132: 2015-16 | C132: 901.425 | D132: 325.931 | E132: =F132-C132-D132-H132 -> 479.148 | F132: 1706.504 | G132: 236.14 | H132: 0 | I132: 1942.644
B133: 2016-17 | C133: 931.849 | D133: 341.806 | E133: =F133-C133-D133-H133 -> 511.805 | F133: 1785.46 | G133: 243.957 | H133: 0 | I133: 2029.417
B134: 2017-18 | C134: 979.732 | D134: 356.425 | E134: =F134-C134-D134-H134 -> 525.608 | F134: 1861.765 | G134: 253.314 | H134: 0 | I134: 2115.079
B135: 2018-19 | C135: 1014.142 | D135: 367.389 | E135: =F135-C135-D135-H135 -> 546.638 | F135: 1928.169 | G135: 262.211 | H135: 0 | I135: 2190.38
B136: 2019-20 | C136: 1051.179 | D136: 379.446 | E136: =F136-C136-D136-H136 -> 565.738 | F136: 1996.363 | G136: 261.979 | H136: 0 | I136: 2258.342
... B148: 2031-32 | C148: 1717.1244 | D148: 656.25978 | E148: =F148-C148-D148-H148 -> 1036.5053 | F148: 3399.9135 | G148: 401.88383 | H148: -9.976 | I148: 3801.7973
B149: Definitions:
B150: Labour income = Wages & Salaries + Mixed Income (ONS Economic Accounts, identifier: DTWM-ROYK+RNKX)
B151: Gross trading profits of non-oil private sector non-financial corporations (ONS Economic Accounts, identifier: CAED)
B152: Other income = employer social contribution + operating surplus of households + operating surplus of general government + operating surplus of public corporations - non-oil PNFC profits (ONS Economic Accounts, identifier: ABNG-CAED+ROYK)
B153: Gross value added at factor cost (ONS Economic Accounts, identifier: CGCB)
B154: Taxes on products and production less subsidies (ONS Economic Accounts, identifier: CMVL)
B155: Statistical discrepancy (ONS Economic Accounts, identifier: GIXQ)
B156: GDP at market prices (ONS Economic Accounts, identifier: YBHA)

Sheet 1.4
A1: Back to contents
B2: 1.4 Nominal GDP (£ billion, non-seasonally adjusted)
B3: 2008Q1 | C3: 397.265
B4: 2008Q2 | C4: 397.113
B5: 2008Q3 | C5: 404.265
B6: 2008Q4 | C6: 403.574
B7: 2009Q1 | C7: 388.315
B8: 2009Q2 | C8: 380.351
B9: 2009Q3 | C9: 394.53
B10: 2009Q4 | C10: 396.209
B11: 2010Q1 | C11: 395.98
B12: 2010Q2 | C12: 394.997
B13: 2010Q3 | C13: 409.292
B14: 2010Q4 | C14: 415.57
... B99: 2032Q1 | C99: 964.54755
B100: Calendar Year
B101: 2008 | C101: 1602.217
B102: 2009 | C102: 1559.405
B103: 2010 | C103: 1615.839
B104: 2011 | C104: 1669.945
B105: 2012 | C105: 1721.708
B106: 2013 | C106: 1789.072
B107: 2014 | C107: 1875.066
B108: 2015 | C108: 1928.016
B109: 2016 | C109: 2004.755
B110: 2017 | C110: 2097.222
B111: 2018 | C111: 2171.559
B112: 2019 | C112: 2252.961
... B124: 2031 | C124: 3770.1051
B125: Centred end-March
B126: 2008-09 | C126: =SUM(OFFSET(C$6,4*(ROW()-ROW(C$126)),0, 4, 1)) -> 1566.77
B127: 2009-10 | C127: =SUM(OFFSET(C$6,4*(ROW()-ROW(C$126)),0, 4, 1)) -> 1596.478
B128: 2010-11 | C128: =SUM(OFFSET(C$6,4*(ROW()-ROW(C$126)),0, 4, 1)) -> 1654.846
B129: 2011-12 | C129: =SUM(OFFSET(C$6,4*(ROW()-ROW(C$126)),0, 4, 1)) -> 1706.949
B130: 2012-13 | C130: =SUM(OFFSET(C$6,4*(ROW()-ROW(C$126)),0, 4, 1)) -> 1770.435
B131: 2013-14 | C131: =SUM(OFFSET(C$6,4*(ROW()-ROW(C$126)),0, 4, 1)) -> 1855.01
B132: 2014-15 | C132: =SUM(OFFSET(C$6,4*(ROW()-ROW(C$126)),0, 4, 1)) -> 1914.717
B133: 2015-16 | C133: =SUM(OFFSET(C$6,4*(ROW()-ROW(C$126)),0, 4, 1)) -> 1979.243
B134: 2016-17 | C134: =SUM(OFFSET(C$6,4*(ROW()-ROW(C$126)),0, 4, 1)) -> 2072.938
B135: 2017-18 | C135: =SUM(OFFSET(C$6,4*(ROW()-ROW(C$126)),0, 4, 1)) -> 2153.988
B136: 2018-19 | C136: =SUM(OFFSET(C$6,4*(ROW()-ROW(C$126)),0, 4, 1)) -> 2229.923
B137: 2019-20 | C137: =SUM(OFFSET(C$6,4*(ROW()-ROW(C$126)),0, 4, 1)) -> 2148.881
... B148: 2030-31 | C148: =SUM(OFFSET(C$6,4*(ROW()-ROW(C$126)),0, 4, 1)) -> 3737.6708
B149: 2031-32 | C149: 3864.1606
B150: Definitions:
B151: Nominal GDP NSA, billions (ONS identifier: BKTL)

Sheet 1.5
A1: Back to contents
B2: 1.5 Per person
C3: By total population | H3: Ages 16+
C4: Index: 2008Q1=100 | G4: £ thousands (2023 prices) | H4: Index: 2008Q1=100 | L4: £ thousands (2023 prices)
C5: LFS employment | D5: Real household disposable income | E5: Real consumption | F5: Real GDP | G5: Real household disposable income | H5: LFS employment | I5: Real household disposable income | J5: Real consumption | K5: Real GDP | L5: Real household disposable income
B6: 2008Q1 | C6: 100 | D6: 100 | E6: 100 | F6: 100 | G6: 5.8449545 | H6: 100 | I6: 100 | J6: 100 | K6: 100 | L6: 7.3301624
B7: 2008Q2 | C7: 99.92395 | D7: 100.80489 | E7: 98.509003 | F7: 99.26055 | G7: 5.8919999 | H7: 99.888431 | I7: 100.76906 | J7: 98.473987 | K7: 99.225266 | L7: 7.3865355
B8: 2008Q3 | C8: 99.27153 | D8: 98.999832 | E8: 96.84266 | F8: 97.459161 | G8: 5.7864951 | H8: 99.201997 | I8: 98.930489 | J8: 96.774828 | K8: 97.390897 | L8: 7.2517655
B9: 2008Q4 | C9: 98.922915 | D9: 100.68398 | E9: 94.315943 | F9: 95.229327 | G9: 5.8849328 | H9: 98.831618 | I9: 100.59106 | J9: 94.228897 | K9: 95.141438 | L9: 7.3734879
B10: 2009Q1 | C10: 98.207654 | D10: 99.384544 | E10: 93.760803 | F10: 93.139295 | G10: 5.8089814 | H10: 98.095254 | I10: 99.270797 | J10: 93.653493 | K10: 93.032695 | L10: 7.2767107
B11: 2009Q2 | C11: 97.102744 | D11: 101.79117 | E11: 93.470064 | F11: 92.705841 | G11: 5.9496475 | H11: 96.973684 | I11: 101.65588 | J11: 93.345832 | K11: 92.582625 | L11: 7.4515409
B12: 2009Q3 | C12: 96.849766 | D12: 100.9674 | E12: 93.591925 | F12: 92.63637 | G12: 5.9014988 | H12: 96.703583 | I12: 100.81501 | J12: 93.450659 | K12: 92.496547 | L12: 7.3899037
B13: 2009Q4 | C13: 96.765824 | D13: 101.84332 | E13: 94.157148 | F13: 92.759331 | G13: 5.9526956 | H13: 96.596207 | I13: 101.6648 | J13: 93.992103 | K13: 92.596737 | L13: 7.452195
B14: 2010Q1 | C14: 96.27737 | D14: 101.59637 | E14: 93.845973 | F14: 93.35158 | G14: 5.9382614 | H14: 96.087191 | I14: 101.39568 | J14: 93.660597 | K14: 93.16718 | L14: 7.4324681
B15: 2010Q2 | C15: 96.678428 | D15: 101.90924 | E15: 96.210059 | F15: 94.229846 | G15: 5.9565488 | H15: 96.464121 | I15: 101.68334 | J15: 95.996791 | K15: 94.020968 | L15: 7.453554
B16: 2010Q3 | C16: 97.114898 | D16: 101.15969 | E16: 96.232451 | F16: 94.586379 | G16: 5.9127379 | H16: 96.883604 | I16: 100.91876 | J16: 96.003258 | K16: 94.361108 | L16: 7.3975093
B17: 2010Q4 | C17: 96.71185 | D17: 100.07147 | E17: 95.793272 | F17: 94.437492 | G17: 5.849132 | H17: 96.461805 | I17: 99.812742 | J17: 95.545601 | K17: 94.193327 | L17: 7.3164361
... B102: 2032Q1 | C102: 104.72812 | D102: 115.11885 | E102: 113.07774 | F102: 116.04624 | G102: 6.7286443 | H102: 100.43781 | I102: 110.40288 | J102: 108.44538 | K102: 111.29228 | L102: 8.0927101
C103: Index: 2008=100 | H103: Index: 2008=100
B104: 2008 | C104: 100 | D104: 100 | E104: 100 | F104: 100 | G104: 23.408397 | H104: 100 | I104: 100 | J104: 100 | K104: 100 | L104: 29.341943
B105: 2009 | C105: 97.690817 | D105: 100.87484 | E105: 96.235304 | F105: 94.719884 | G105: 23.613184 | H105: 97.599044 | I105: 100.78008 | J105: 96.144898 | K105: 94.630902 | L105: 29.570834
B106: 2010 | C106: 97.153956 | D106: 101.05928 | E106: 98.059106 | F106: 96.089829 | G106: 23.656358 | H106: 96.979497 | I106: 100.87781 | J106: 97.883022 | K106: 95.917281 | L106: 29.59951
B107: 2011 | C107: 96.882124 | D107: 97.842659 | E107: 96.668024 | F107: 96.135244 | G107: 22.903398 | H107: 96.642956 | I107: 97.60112 | J107: 96.429384 | K107: 95.89792 | L107: 28.638065
B108: 2012 | C108: 97.345834 | D108: 99.558625 | E108: 97.90745 | F108: 96.943172 | G108: 23.305078 | H108: 97.092182 | I108: 99.299207 | J108: 97.652334 | K108: 96.690569 | L108: 29.136317
B109: 2013 | C109: 97.898582 | D109: 100.67303 | E109: 99.380627 | F109: 97.937523 | G109: 23.565943 | H109: 97.617333 | I109: 100.38381 | J109: 99.09512 | K109: 97.656162 | L109: 29.454561
B110: 2014 | C110: 99.508474 | D110: 102.28292 | E110: 101.38116 | F110: 100.28973 | G110: 23.942792 | H110: 99.201392 | I110: 101.96728 | J110: 101.0683 | K110: 99.980239 | L110: 29.919181
B111: 2015 | C111: 100.4688 | D111: 107.65991 | E111: 103.62038 | F111: 101.68444 | G111: 25.201458 | H111: 100.14429 | I111: 107.31217 | J111: 103.28569 | K111: 101.356 | L111: 31.487475
B112: 2016 | C112: 101.20349 | D112: 107.64316 | E112: 106.52541 | F112: 103.15944 | G112: 25.197538 | H112: 100.87723 | I112: 107.29614 | J112: 106.182 | K112: 102.82688 | L112: 31.482774
B113: 2017 | C113: 101.653 | D113: 108.05918 | E113: 108.13243 | F113: 105.69528 | G113: 25.294921 | H113: 101.32238 | I113: 107.70772 | J113: 107.78073 | K113: 105.35151 | L113: 31.603538
B114: 2018 | C114: 102.34357 | D114: 109.62905 | E114: 109.81987 | F114: 106.8042 | G114: 25.662403 | H114: 101.97954 | I114: 109.2391 | J114: 109.42924 | K114: 106.4243 | L114: 32.052875
B115: 2019 | C115: 103.19203 | D115: 111.75276 | E115: 110.56669 | F115: 107.6639 | G115: 26.159529 | H115: 102.72059 | I115: 111.2422 | J115: 110.06155 | K115: 107.17203 | L115: 32.640623
... B127: 2031 | C127: 105.0503 | D127: 114.58088 | E127: 115.13368 | F127: 117.5073 | G127: 26.821547 | H127: 101.00357 | I127: 110.16701 | J127: 110.69851 | K127: 112.98069 | L127: 32.325141
C128: Index: 2008/2009 =100 | H128: Index: 2008/2009 =100
B129: 2008-09 | C129: 100 | D129: 100 | E129: 100 | F129: 100 | G129: 23.372277 | H129: 100 | I129: 100 | J129: 100 | K129: 100 | L129: 29.288286
B130: 2009-10 | C130: 97.646337 | D130: 101.5824 | E130: 97.823013 | F130: 96.46427 | G130: 23.74212 | H130: 97.562218 | I130: 101.49489 | J130: 97.738742 | K130: 96.38117 | L130: 29.726115
B131: 2010-11 | C131: 97.749046 | D131: 100.10333 | E131: 99.852334 | F131: 98.072686 | G131: 23.396427 | H131: 97.582431 | I131: 99.932701 | J131: 99.682134 | K131: 97.905519 | L131: 29.268575
B132: 2011-12 | C132: 97.171986 | D132: 98.518021 | E132: 98.043925 | F132: 97.957043 | G132: 23.025905 | H132: 96.952145 | I132: 98.295135 | J132: 97.822112 | K132: 97.735426 | L132: 28.78896
B133: 2012-13 | C133: 97.962895 | D133: 99.499075 | E133: 100.06953 | F133: 98.777107 | G133: 23.255199 | H133: 97.730593 | I133: 99.26313 | J133: 99.832233 | K133: 98.542874 | L133: 29.072469
B134: 2013-14 | C134: 98.742494 | D134: 101.76004 | E134: 101.35744 | F134: 100.22156 | G134: 23.783638 | H134: 98.481942 | I134: 101.49153 | J134: 101.08999 | K134: 99.957103 | L134: 29.725129
B135: 2014-15 | C135: 100.28142 | D135: 103.21772 | E135: 103.78444 | F135: 102.58234 | G135: 24.124332 | H135: 99.994255 | I135: 102.92215 | J135: 103.48724 | K135: 102.28858 | L135: 30.144133
B136: 2015-16 | C136: 101.06373 | D136: 108.61598 | E136: 105.9863 | F136: 103.79943 | G136: 25.386028 | H136: 100.76804 | I136: 108.2982 | J136: 105.67622 | K136: 103.49575 | L136: 31.718688
B137: 2016-17 | C137: 101.8112 | D137: 107.25934 | E137: 108.7901 | F137: 105.56033 | G137: 25.068949 | H137: 101.51026 | I137: 106.9423 | J137: 108.46853 | K137: 105.24831 | L137: 31.321566
B138: 2017-18 | C138: 102.29707 | D138: 109.14979 | E138: 110.29831 | F138: 108.07601 | G138: 25.510791 | H138: 101.98964 | I138: 108.82177 | J138: 109.96683 | K138: 107.75122 | L138: 31.872031
B139: 2018-19 | C139: 102.96573 | D139: 109.94841 | E139: 111.95509 | F139: 108.88779 | G139: 25.697446 | H139: 102.61197 | I139: 109.57065 | J139: 111.57044 | K139: 108.51368 | L139: 32.091365
B140: 2019-20 | C140: 103.75423 | D140: 112.04991 | E140: 111.43194 | F140: 108.96938 | G140: 26.188616 | H140: 103.2722 | I140: 111.52934 | J140: 110.91424 | K140: 108.46313 | L140: 32.665033
... B152: 2031-32 | C152: 105.59935 | D152: 114.91324 | E152: 117.39048 | F152: 119.98446 | G152: 26.857841 | H152: 101.4777 | I152: 110.42806 | J152: 112.80861 | K152: 115.30134 | L152: 32.342485
B153: Definitions: | H153: Definitions:
B154: Per person LFS employment = LFS employment, all aged 16 and over (ONS identifier: MGRZ) divided by total population (ONS identifier: EBAQ) | H154: Per person LFS employment = LFS employment, all aged 16 and over (ONS identifier: MGRZ) divided by LFS population, all aged 16 and over (ONS identifier: MGSL)
B155: Per person real household disposable income = Real household disposable income (chained volume measure, identifier: NRJR) divided by total population (ONS identifier: EBAQ) | H155: Per person real household disposable income = Real household disposable income (chained volume measure, identifier: NRJR) divided by LFS population, all aged 16 and over (ONS identifier: MGSL)
B156: Per person real consumption = Household and non-profit institutions serving households final consumption expenditure (chained volume measure, identifier: ABJR+HAYO) divided by total population (ONS identifier: EBAQ) | H156: Per person real consumption = Household and non-profit institutions serving households final consumption expenditure (chained volume measure, identifier: ABJR+HAYO) divided by LFS population, all aged 16 and over (ONS identifier: MGSL)
B157: Per person real GDP = Gross domestic product at market prices (chained volume measure, identifier: ABMI) divided by total population (ONS identifier: EBAQ) | H157: Per person real GDP = Gross domestic product at market prices (chained volume measure, identifier: ABMI) divided by LFS population, all aged 16 and over (ONS identifier: MGSL)

Sheet 1.6
A1: Back to contents
B2: 1.6 Labour market
C3: Employment (16+, millions) | D3: Employment rate (16+, per cent) | E3: Employees (16+, millions) | F3: ILO unemployment (16+, millions) | G3: ILO unemployment rate (16+, per cent) | H3: Participation rate (16+, per cent) | I3: Average hours worked | J3: Total hours worked (millions) | K3: Labour income share (per cent) | L3: Labour compensation share (per cent) | M3: Compensation of employees (£ billion) (a) | N3: Wages and salaries (£ billion) (a-b) | O3: Employers social contributions (£ billion) (b) | P3: Mixed income (£ billion) | Q3: Average weekly earnings growth (per cent) | R3: Average weekly earnings index (2008Q1=100) | S3: Average hourly earnings index (2008Q1=100) | T3: Productivity per hour index (2008Q1 =100) | U3: Productivity per worker index (2008Q1 =100) | V3: Real product wage (2008Q1 =100) | W3: Real consumption wage (2008Q1 =100) | X3: Real weekly earnings index (2008Q1=100) | Y3: Real hourly earnings index (2008Q1=100)
B4: 2008Q1 | C4: 29.684 | D4: 60.337012 | E4: 25.806 | F4: 1.622 | G4: 5.1811154 | H4: 63.633961 | I4: 32.2 | J4: 955.8248 | K4: 47.970559 | L4: 56.230424 | M4: 202.225 | N4: 169.209 | O4: 33.016 | P4: 22.537 | Q4: 2.5663719 | R4: 100 | S4: 100 | T4: 100 | U4: 100 | V4: 100 | W4: 100 | X4: 100 | Y4: 100
B5: 2008Q2 | C5: 29.722 | D5: 60.269695 | E5: 25.863 | F5: 1.68 | G5: 5.3499777 | H5: 63.676366 | I5: 31.8 | J5: 945.1596 | K5: 47.389412 | L5: 55.448276 | M5: 200.18 | N5: 167.728 | O5: 32.452 | P5: 23.103 | Q5: 2.5181341 | R5: 98.906288 | S5: 100.15039 | T5: 100.58561 | U5: 99.336095 | V5: 97.770016 | W5: 97.260852 | X5: 96.950314 | Y5: 98.169814
B6: 2008Q3 | C6: 29.58 | D6: 59.855521 | E6: 25.762 | F6: 1.84 | G6: 5.8561426 | H6: 63.578786 | I6: 32 | J6: 946.56 | K6: 47.173476 | L6: 55.173734 | M6: 199.128 | N6: 166.956 | O6: 32.172 | P6: 22.746 | Q6: 0.3669952 | R6: 98.837031 | S6: 99.454762 | T6: 98.787921 | U6: 98.174331 | V6: 95.56305 | W6: 95.81597 | X6: 95.687985 | Y6: 96.286035
B7: 2008Q4 | C7: 29.528 | D7: 59.632046 | E7: 25.7 | F7: 2.003 | G7: 6.3524785 | H7: 63.677121 | I7: 31.9 | J7: 941.9432 | K7: 47.439505 | L7: 55.674832 | M7: 198.142 | N7: 165.392 | O7: 32.75 | P7: 23.264 | Q7: -0.37208675 | R7: 98.147357 | S7: 99.070373 | T7: 97.17152 | U7: 96.266195 | V7: 93.987986 | W7: 96.130699 | X7: 94.903576 | Y7: 95.796086
B8: 2009Q1 | C8: 29.366 | D8: 59.187746 | E8: 25.522 | F8: 2.235 | G8: 7.072561 | H8: 63.692432 | I8: 31.5 | J8: 925.029 | K8: 47.721378 | L8: 56.205247 | M8: 195.359 | N8: 162.291 | O8: 33.068 | P8: 23.715 | Q8: -3.0211642 | R8: 96.978836 | S8: 99.133921 | T8: 96.946676 | U8: 94.83914 | V8: 92.92483 | W8: 95.216917 | X8: 94.149135 | Y8: 96.241338
B9: 2009Q2 | C9: 29.087 | D9: 58.511024 | E9: 25.244 | F9: 2.448 | G9: 7.7628032 | H9: 63.435388 | I9: 31.7 | J9: 922.0579 | K9: 48.522039 | L9: 57.008719 | M9: 198.045 | N9: 165.019 | O9: 33.026 | P9: 23.805 | Q9: 0.79734916 | R9: 99.694916 | S9: 101.26739 | T9: 96.977773 | U9: 95.471907 | V9: 95.239864 | W9: 97.4464 | X9: 95.723943 | Y9: 97.233784
B10: 2009Q3 | C10: 29.069 | D10: 58.348053 | E10: 25.188 | F10: 2.475 | G10: 7.8461831 | H10: 63.315937 | I10: 31.5 | J10: 915.6735 | K10: 48.096396 | L10: 56.369335 | M10: 197.252 | N10: 164.89 | O10: 32.362 | P10: 23.253 | Q10: 1.0132113 | R10: 99.838459 | S10: 102.05709 | T10: 97.775101 | U10: 95.649555 | V10: 95.069408 | W10: 97.178584 | X10: 95.238711 | Y10: 97.355126
B11: 2009Q4 | C11: 29.102 | D11: 58.283265 | E11: 25.19 | F11: 2.453 | G11: 7.7737284 | H11: 63.195946 | I11: 31.5 | J11: 916.713 | K11: 48.434883 | L11: 57.398407 | M11: 199.924 | N11: 165.029 | O11: 34.895 | P11: 23.528 | Q11: 1.8006908 | R11: 99.914688 | S11: 102.13501 | T11: 97.989812 | U11: 95.859599 | V11: 97.433682 | W11: 99.025026 | X11: 94.622408 | Y11: 96.725128
B12: 2010Q1 | C12: 29.013 | D12: 57.97614 | E12: 25.059 | F12: 2.526 | G12: 8.0091315 | H12: 63.0238 | I12: 31.6 | J12: 916.8108 | K12: 47.404088 | L12: 56.58485 | M12: 201.034 | N12: 164.483 | O12: 36.551 | P12: 24.245 | Q12: 3.2232551 | R12: 100.10471 | S12: 102.00543 | T12: 98.802115 | U12: 96.961082 | V12: 97.935847 | W12: 100.03002 | X12: 94.102385 | Y12: 95.889139
B13: 2010Q2 | C13: 29.192 | D13: 58.203569 | E13: 25.243 | F13: 2.488 | G13: 7.8535353 | H13: 63.164191 | I13: 31.6 | J13: 922.4672 | K13: 47.059466 | L13: 56.250481 | M13: 201.716 | N13: 164.682 | O13: 37.034 | P13: 24.938 | Q13: -0.2002655 | R13: 99.495262 | S13: 101.38441 | T13: 99.317937 | U13: 97.467293 | V13: 97.5518 | W13: 98.908182 | X13: 92.340336 | Y13: 94.093634
B14: 2010Q3 | C14: 29.385 | D14: 58.456672 | E14: 25.339 | F14: 2.47 | G14: 7.7538848 | H14: 63.370335 | I14: 31.6 | J14: 928.566 | K14: 47.061503 | L14: 56.163446 | M14: 203.533 | N14: 166.563 | O14: 36.97 | P14: 24.59 | Q14: 0.41265018 | R14: 100.25044 | S14: 102.15393 | T14: 99.245662 | U14: 97.396364 | V14: 97.647891 | W14: 98.732456 | X14: 92.769528 | Y14: 94.530975
B15: 2010Q4 | C15: 29.324 | D15: 58.202171 | E15: 25.315 | F15: 2.503 | G15: 7.8643919 | H15: 63.170117 | I15: 31.8 | J15: 932.5032 | K15: 47.04221 | L15: 56.036114 | M15: 203.636 | N15: 166.887 | O15: 36.749 | P15: 25.327 | Q15: 0.62652507 | R15: 100.54068 | S15: 101.80534 | T15: 98.876596 | U15: 97.648315 | V15: 97.248156 | W15: 97.892329 | X15: 92.105518 | Y15: 93.264078
... B100: 2032Q1 | C100: 35.496917 | D100: 60.601175 | E100: 30.607421 | F100: 1.5330402 | G100: 4.14 | H100: 63.218417 | I100: 31.674836 | J100: 1124.359 | K100: 45.116519 | L100: 54.554351 | M100: 467.92386 | N100: 377.11308 | O100: 90.810777 | P100: 56.99786 | Q100: 2.5624905 | R100: 187.90663 | S100: 191.02209 | T100: 112.64432 | U100: 110.80715 | V100: 108.18038 | W100: 109.27756 | X100: 96.525121 | Y100: 98.125494
B101: 2008 | C101: 29.6285 | D101: 60.023569 | E101: 25.78275 | F101: 1.78625 | G101: 5.6849286 | H101: 63.641559 | I101: 31.975 | J101: 947.3719 | K101: 47.492631 | L101: 55.630729 | M101: 799.675 | N101: 669.285 | O101: 130.39 | P101: 91.65 | Q101: 1.2583379 | R101: 100 | S101: 100 | T101: 100 | U101: 100 | V101: 100 | W101: 100 | X101: 100 | Y101: 100
B102: 2009 | C102: 29.156 | D102: 58.582522 | E102: 25.286 | F102: 2.40275 | G102: 7.6138189 | H102: 63.409926 | I102: 31.55 | J102: 919.86835 | K102: 48.193381 | L102: 56.744784 | M102: 790.58 | N102: 657.229 | O102: 133.351 | P102: 94.301 | Q102: 0.12781303 | R102: 100.12781 | S102: 101.4766 | T102: 98.271146 | U102: 96.958841 | V102: 98.282234 | W102: 99.91249 | X102: 98.005676 | Y102: 99.325879
B103: 2010 | C103: 29.2285 | D103: 58.209638 | E103: 25.239 | F103: 2.49675 | G103: 7.8702359 | H103: 63.182111 | I103: 31.65 | J103: 925.0868 | K103: 47.140526 | L103: 56.256781 | M103: 809.919 | N103: 662.615 | O103: 147.304 | P103: 99.1 | Q103: 1.0072471 | R103: 101.13635 | S103: 102.17487 | T103: 99.923657 | U103: 98.9047 | V103: 100.79072 | W103: 101.63292 | X103: 95.832127 | Y103: 96.816186
B104: 2011 | C104: 29.381 | D104: 58.008367 | E104: 25.3235 | F104: 2.593 | G104: 8.1095071 | H104: 63.12749 | I104: 31.575 | J104: 927.6992 | K104: 46.581295 | L104: 55.488893 | M104: 826.366 | N104: 677.614 | O104: 148.752 | P104: 100.268 | Q104: 1.9223717 | R104: 103.08056 | S104: 104.38641 | T104: 100.49275 | U104: 99.229084 | V104: 100.91352 | W104: 99.469423 | X104: 93.500789 | Y104: 94.68528
B105: 2012 | C105: 29.723 | D105: 58.27711 | E105: 25.4985 | F105: 2.56975 | G105: 7.958284 | H105: 63.315747 | I105: 31.825 | J105: 945.95045 | K105: 45.874968 | L105: 54.878237 | M105: 841.692 | N105: 686.682 | O105: 155.01 | P105: 103.151 | Q105: 0.64272569 | R105: 103.74309 | S105: 104.23206 | T105: 100.06254 | U105: 99.58636 | V105: 100.63054 | W105: 98.971603 | X105: 91.513518 | Y105: 91.944847
B106: 2013 | C106: 30.09675 | D106: 58.592287 | E106: 25.8345 | F106: 2.474 | G106: 7.5965131 | H106: 63.408987 | I106: 32.05 | J106: 964.60415 | K106: 46.208649 | L106: 54.914727 | M106: 873.956 | N106: 718.198 | O106: 155.758 | P106: 108.508 | Q106: 3.229328 | R106: 107.09329 | S106: 106.84269 | T106: 99.809087 | U106: 100.03978 | V106: 101.06831 | W106: 99.221517 | X106: 92.106445 | Y106: 91.890907
B107: 2014 | C107: 30.81825 | D107: 59.543186 | E107: 26.2605 | F107: 2.02625 | G107: 6.1695433 | H107: 63.458608 | I107: 32.175 | J107: 991.58278 | K107: 45.925317 | L107: 53.983966 | M107: 896.603 | N107: 745.498 | O107: 151.105 | P107: 115.632 | Q107: 2.1173089 | R107: 109.36079 | S107: 108.681 | T107: 100.16047 | U107: 100.78512 | V107: 100.52331 | W107: 98.972477 | X107: 92.702215 | Y107: 92.125977
B108: 2015 | C108: 31.34575 | D108: 60.109137 | E108: 26.771 | F108: 1.7805 | G108: 5.3755561 | H108: 63.523722 | I108: 32.1 | J108: 1006.209 | K108: 46.290539 | L108: 54.402557 | M108: 926.308 | N108: 769.907 | O108: 156.401 | P108: 122.582 | Q108: 1.304837 | R108: 110.78777 | S108: 110.35635 | T108: 100.82232 | U108: 101.20997 | V108: 100.93797 | W108: 100.62943 | X108: 93.874184 | Y108: 93.508631
B109: 2016 | C109: 31.81025 | D109: 60.549274 | E109: 27.038 | F109: 1.63475 | G109: 4.8881177 | H109: 63.661086 | I109: 32.05 | J109: 1019.5168 | K109: 46.07361 | L109: 54.382406 | M109: 963.779 | N109: 797.208 | O109: 166.571 | P109: 126.455 | Q109: 2.5234968 | R109: 113.5835 | S109: 113.3177 | T109: 101.69742 | U109: 101.93269 | V109: 102.45778 | W109: 102.39133 | X109: 95.612374 | Y109: 95.388632
B110: 2017 | C110: 32.12775 | D110: 60.816565 | E110: 27.33 | F110: 1.47925 | G110: 4.4016679 | H110: 63.616811 | I110: 32.1 | J110: 1031.2937 | K110: 46.110045 | L110: 54.335116 | M110: 1001.409 | N110: 828.911 | O110: 172.498 | P110: 138.119 | Q110: 2.8658423 | R110: 116.83862 | S110: 116.38364 | T110: 103.57985 | U110: 103.97654 | V110: 103.70142 | W110: 103.4296 | X110: 95.782503 | Y110: 95.409519
B111: 2018 | C111: 32.50675 | D111: 61.210944 | E111: 27.72625 | F111: 1.385 | G111: 4.0866365 | H111: 63.818989 | I111: 32 | J111: 1040.2193 | K111: 46.317922 | L111: 54.592898 | M111: 1042.411 | N111: 862.715 | O111: 179.696 | P111: 143.106 | Q111: 2.5906882 | R111: 119.86554 | S111: 119.7719 | T111: 104.28259 | U111: 104.35848 | V111: 104.21243 | W111: 104.01652 | X111: 95.887776 | Y111: 95.812864
B112: 2019 | C112: 32.923 | D112: 61.655758 | E112: 27.9615 | F112: 1.311 | G112: 3.8295746 | H112: 64.110922 | I112: 32.066248 | J112: 1055.7 | K112: 46.45491 | L112: 55.122437 | M112: 1091.121 | N112: 895.845 | O112: 195.276 | P112: 150.766 | Q112: 2.9665578 | R112: 123.42142 | S112: 123.07021 | T112: 104.0446 | U112: 104.33354 | V112: 105.50453 | W112: 106.44828 | X112: 96.99514 | Y112: 96.719129
... B124: 2031 | C124: 35.388344 | D124: 60.625273 | E124: 30.543582 | F124: 1.5307532 | G124: 4.146248 | H124: 63.247679 | I124: 31.695053 | J124: 1121.635 | K124: 45.202141 | L124: 54.656403 | M124: 1838.2228 | N124: 1481.7872 | O124: 356.43563 | P124: 222.38105 | Q124: 2.6014041 | R124: 186.88912 | S124: 188.53982 | T124: 112.85036 | U124: 111.85812 | V124: 111.2249 | W124: 111.90463 | X124: 98.939975 | Y124: 99.813864
B125: 2008-09 | C125: 29.549 | D125: 59.736252 | E125: 25.71175 | F125: 1.9395 | G125: 6.1577899 | H125: 63.656176 | I125: 31.8 | J125: 939.67295 | K125: 47.428649 | L125: 55.620822 | M125: 792.809 | N125: 662.367 | O125: 130.442 | P125: 92.828 | Q125: -0.15306947 | R125: 100 | S125: 100 | T125: 100 | U125: 100 | V125: 100 | W125: 100 | X125: 100 | Y125: 100
B126: 2009-10 | C126: 29.06775 | D126: 58.279621 | E126: 25.17025 | F126: 2.4755 | G126: 7.8479616 | H126: 63.242768 | I126: 31.575 | J126: 917.8138 | K126: 48.110293 | L126: 56.838309 | M126: 796.255 | N126: 659.421 | O126: 136.834 | P126: 94.831 | Q126: 1.6970123 | R126: 101.69701 | S126: 99.446784 | T126: 99.505219 | U126: 98.789441 | V126: 101.42879 | W126: 102.40765 | X126: 99.470127 | Y126: 97.269172
B127: 2010-11 | C127: 29.3355 | D127: 58.291221 | E127: 25.33875 | F127: 2.486 | G127: 7.8124148 | H127: 63.23106 | I127: 31.675 | J127: 929.20403 | K127: 47.062967 | L127: 56.108122 | M127: 817.066 | N127: 669.247 | O127: 147.819 | P127: 99.872 | Q127: 0.81519673 | R127: 102.52604 | S127: 100.79425 | T127: 100.73821 | U127: 100.33109 | V127: 102.65957 | W127: 102.3162 | X127: 96.87934 | Y127: 95.242924
B128: 2011-12 | C128: 29.38825 | D128: 57.914891 | E128: 25.28 | F128: 2.6305 | G128: 8.2154767 | H128: 63.098641 | I128: 31.575 | J128: 927.92903 | K128: 46.299187 | L128: 55.227052 | M128: 827.149 | N128: 677.154 | O128: 149.995 | P128: 100.708 | Q128: 1.41662 | R128: 103.97845 | S128: 101.00828 | T128: 101.53777 | U128: 100.8079 | V128: 102.85347 | W128: 100.42783 | X128: 94.200613 | Y128: 91.509749
B129: 2012-13 | C129: 29.8265 | D129: 58.379644 | E129: 25.60225 | F129: 2.5465 | G129: 7.8662785 | H129: 63.364002 | I129: 31.9 | J129: 951.4727 | K129: 45.724235 | L129: 54.680009 | M129: 845.182 | N129: 689.791 | O129: 155.391 | P129: 103.567 | Q129: 0.58402511 | R129: 104.58571 | S129: 100.54703 | T129: 100.52615 | U129: 100.83114 | V129: 101.99388 | W129: 99.755971 | X129: 92.301257 | Y129: 88.736953
B130: 2013-14 | C130: 30.2745 | D130: 58.827899 | E130: 25.91375 | F130: 2.392 | G130: 7.3237031 | H130: 63.476467 | I130: 32.075 | J130: 971.05703 | K130: 46.550122 | L130: 55.136331 | M130: 885.826 | N130: 730.44 | O130: 155.386 | P130: 111.985 | Q130: 4.6200428 | R130: 109.41761 | S130: 103.65118 | T130: 100.63832 | U130: 101.4979 | V130: 103.65555 | W130: 101.11802 | X130: 94.39055 | Y130: 89.416063
B131: 2014-15 | C131: 30.974 | D131: 59.731553 | E131: 26.42975 | F131: 1.92975 | G131: 5.8654188 | H131: 63.453362 | I131: 32.175 | J131: 996.58235 | K131: 45.713433 | L131: 53.703445 | M131: 900.902 | N131: 749.699 | O131: 151.203 | P131: 115.382 | Q131: 0.63280848 | R131: 110.11002 | S131: 104.89953 | T131: 101.11242 | U131: 102.29446 | V131: 101.88479 | W131: 100.13908 | X131: 94.000156 | Y131: 89.551997
B132: 2015-16 | C132: 31.45025 | D132: 60.193707 | E132: 26.82825 | F132: 1.746 | G132: 5.2604193 | H132: 63.535735 | I132: 32.1 | J132: 1009.5635 | K132: 46.401966 | L132: 54.513179 | M132: 934.25 | N132: 776.678 | O132: 157.572 | P132: 124.747 | Q132: 2.0598164 | R132: 112.37808 | S132: 107.42124 | T132: 101.76016 | U132: 102.70691 | V132: 103.24211 | W132: 102.33138 | X132: 95.839255 | Y132: 91.611923
B133: 2016-17 | C133: 31.9055 | D133: 60.637467 | E133: 27.11225 | F133: 1.59525 | G133: 4.7619545 | H133: 63.669427 | I133: 32.075 | J133: 1023.3747 | K133: 45.917079 | L133: 54.290222 | M133: 973.756 | N133: 803.83 | O133: 169.926 | P133: 128.019 | Q133: 2.4117981 | R133: 115.08841 | S133: 110.65792 | T133: 102.80241 | U133: 103.68244 | V133: 104.62426 | W133: 103.97557 | X133: 97.07563 | Y133: 93.338562
B134: 2017-18 | C134: 32.226 | D134: 60.923749 | E134: 27.44 | F134: 1.45225 | G134: 4.3122568 | H134: 63.669312 | I134: 32.025 | J134: 1032.0266 | K134: 46.321296 | L134: 54.554889 | M134: 1013.306 | N134: 839.159 | O134: 174.147 | P134: 140.573 | Q134: 3.1481634 | R134: 118.71158 | S134: 114.12303 | T134: 104.92226 | U134: 105.64917 | V134: 106.05575 | W134: 104.99001 | X134: 97.380803 | Y134: 93.616745
B135: 2018-19 | C135: 32.59825 | D135: 61.295413 | E135: 27.77825 | F135: 1.3555 | G135: 3.9924289 | H135: 63.844286 | I135: 32.10332 | J135: 1046.5246 | K135: 46.29982 | L135: 54.633123 | M135: 1051.824 | N135: 869.293 | O135: 182.531 | P135: 144.849 | Q135: 2.3295703 | R135: 121.47705 | S135: 116.50017 | T135: 104.76613 | U135: 105.75148 | V135: 106.34942 | W135: 105.71707 | X135: 97.439826 | Y135: 93.447744
B136: 2019-20 | C136: 32.97425 | D136: 61.690051 | E136: 28.00975 | F136: 1.3375 | G136: 3.8979793 | H136: 64.192287 | I136: 31.768924 | J136: 1047.55 | K136: 46.546493 | L136: 55.278651 | M136: 1096.685 | N136: 899.483 | O136: 197.202 | P136: 151.696 | Q136: 2.6177355 | R136: 124.657 | S136: 125.02908 | T136: 105.14264 | U136: 105.02645 | V136: 107.06621 | W136: 107.93924 | X136: 98.281145 | Y136: 98.574494
... B148: 2031-32 | C148: 35.433228 | D148: 60.618103 | E148: 30.570403 | F148: 1.5302889 | G148: 4.139998 | H148: 63.236075 | I148: 31.686719 | J148: 1122.7623 | K148: 45.166121 | L148: 54.613018 | M148: 1851.6499 | N148: 1492.498 | O148: 359.1519 | P148: 224.62634 | Q148: 2.5891927 | R148: 189.51586 | S148: 187.19926 | T148: 114.04025 | U148: 113.62235 | V148: 113.49187 | W148: 113.46077 | X148: 100.57115 | Y148: 99.341795
B149: Definitions:
B150: LFS employment, all aged 16 and over (ONS identifier: MGRZ)
B151: LFS employment rate, all aged 16 and over (ONS identifier: MGSR)
B152: LFS employees equal to total employment less self-employed, all aged 16 and over (ONS identifier: MGRZ less MGRQ)
B153: ILO unemployment, all aged 16 and over (ONS identifier: MGSC)
B154: ILO unemployment rate, all aged 16 and over (ONS identifier: MGSX)
B155: LFS participation rate, all aged 16 and over (ONS identifier: MGWG)
B156: LFS average (mean) actual weekly hours worked, all workers (ONS identifier: YBUV)
B157: LFS total weekly hours worked, millions (ONS identifier: YBUS). Estimates before 2019Q1 calculated from LFS average actual weekly hours worked (ONS identifier: YBUV) multiplied by LFS employment (ONS identifier: MGRZ)
B158: Labour income share: wages and salaries (ONS identifier: DTWM) and mixed income (ONS identifier: ROYH) as a share of nominal Gross Domestic Product (ONS identifier: YBHA).
B159: Labour compensation share: wages and salaries (ONS identifier: DTWM), employers social contributions (ONS identifier: ROYK) and mixed income (ONS identifier: ROYH) as a share of nominal Gross Domestic Product (ONS identifier: YBHA).
B160: Compensation of employees, £ billion (ONS identifier: DTWM)
... B171: Note: Historical data from the ONS Labour Force Survey include the latest reweighted estimates published on 3 December 2024. This creates a discontinuity in the series between Q4 2018 and Q1 2019, with the exception of UK total employment, unemployment, inactivity, and participation.

Sheet 1.7
A1: Back to contents
B2: 1.7 Inflation
C3: Year-on-year growth | M3: Jan 1987=100 | N3: Jan 1987=100 | O3: 2015=100 | P3: 2015=100 | Q3: 2015=100 | R3: Jan 1987=100 | S3: 2015 = 100 | T3: 2016 = 100 | U3: 2023=100 | V3: 2023=100
C4: RPI | D4: RPIX | E4: CPI | F4: CPIH | G4: OOH | H4: Mortgage interest payments | I4: Actual rents for housing | J4: Private rentals for housing | K4: Consumer expenditure deflator | L4: GDP deflator | M4: RPI | N4: RPIX | O4: CPI | P4: CPIH | Q4: OOH | R4: Mortgage interest payments | S4: Actual rents for housing | T4: Private rentals for housing | U4: Consumer expenditure deflator | V4: GDP deflator
B5: 2008Q1 | C5: 3.9901478 | D5: 3.4989858 | E5: 2.3757202 | F5: 2.5889967 | G5: 2.7248973 | H5: 11.74954 | I5: 3.2925822 | J5: 2.2163408 | K5: 3.7081837 | L5: 2.2522523 | M5: 211.1 | N5: 204.1 | O5: 82.924333 | P5: 84.533333 | Q5: 91.733333 | R5: 404.53333 | S5: 83.364 | T5: 93.591667 | U5: 69.504492 | V5: 68.1
B6: 2008Q2 | C6: 4.3625788 | D6: 4.3833333 | E6: 3.4197229 | F6: 3.3613445 | G6: 2.7839644 | H6: 4.1721797 | I6: 3.4293759 | J6: 2.0361434 | K6: 3.8404405 | L6: 2.0710059 | M6: 215.3 | N6: 208.76667 | O6: 84.597333 | P6: 86.1 | Q6: 92.3 | R6: 393.66667 | S6: 84.729 | T6: 93.877333 | U6: 70.583377 | V6: 69
B7: 2008Q3 | C7: 4.9573477 | D7: 5.3473263 | E7: 4.8388413 | F7: 4.5218088 | G7: 2.6179941 | H7: -1.689441 | I7: 3.0344883 | J7: 2.1955058 | K7: 4.8777088 | L7: 4.0059347 | M7: 217.36667 | N7: 210.8 | O7: 85.653333 | P7: 87.066667 | Q7: 92.766667 | R7: 395.7 | S7: 85.044667 | T7: 94.383 | U7: 71.550648 | V7: 70.1
B8: 2008Q4 | C8: 2.7327612 | D8: 3.7860082 | E8: 3.8240517 | F8: 3.7257233 | G8: 2.5978778 | H8: -13.529838 | I8: 3.5605924 | J8: 1.766431 | K8: 3.8912418 | L8: 5.0445104 | M8: 215.53333 | N8: 210.16667 | O8: 85.758667 | P8: 87.233333 | Q8: 93.466667 | R8: 357.9 | S8: 85.898333 | T8: 94.617 | U8: 71.134459 | V8: 70.8
B9: 2009Q1 | C9: -0.078951682 | D9: 2.3844521 | E9: 3.0055512 | F9: 2.9574133 | G9: 2.2165698 | H9: -38.900791 | I9: 2.9169266 | J9: 0.6328911 | K9: 2.5865564 | L9: 3.9647577 | M9: 210.93333 | N9: 208.96667 | O9: 85.416667 | P9: 87.033333 | Q9: 93.766667 | R9: 247.16667 | S9: 85.795667 | T9: 94.184 | U9: 71.302265 | V9: 70.8
B10: 2009Q2 | C10: -1.2695462 | D10: 1.437011 | E10: 2.0887183 | F10: 2.013163 | G10: 1.5529072 | H10: -45.791702 | I10: 1.5846601 | J10: -0.30181229 | K10: 1.1663767 | L10: 2.7536232 | M10: 212.56667 | N10: 211.76667 | O10: 86.364333 | P10: 87.833333 | Q10: 93.733333 | R10: 213.4 | S10: 86.071667 | T10: 93.594 | U10: 71.406646 | V10: 70.9
B11: 2009Q3 | C11: -1.3801564 | D11: 1.3124605 | E11: 1.489726 | F11: 1.3016845 | G11: 0.64678405 | H11: -45.53955 | I11: 1.9170318 | J11: -1.2936652 | K11: -0.10533098 | L11: 1.5691869 | M11: 214.36667 | N11: 213.56667 | O11: 86.929333 | P11: 88.2 | Q11: 93.366667 | R11: 215.5 | S11: 86.675 | T11: 93.162 | U11: 71.475283 | V11: 71.2
B12: 2009Q4 | C12: 0.61862079 | D12: 2.7914354 | E12: 2.1031888 | F12: 1.6048911 | G12: -0.78459344 | H12: -39.051877 | I12: 0.9930344 | J12: -1.7445773 | K12: -0.066641541 | L12: -0.28248588 | M12: 216.86667 | N12: 216.03333 | O12: 87.562333 | P12: 88.633333 | Q12: 92.733333 | R12: 218.13333 | S12: 86.751333 | T12: 92.966333 | U12: 71.087054 | V12: 70.6
B13: 2010Q1 | C13: 3.9506956 | D13: 4.5461796 | E13: 3.2745366 | F13: 2.3362697 | G13: -1.6352648 | H13: -10.923803 | I13: 1.1329244 | J13: -1.2935672 | K13: -0.23669515 | L13: 1.1299435 | M13: 219.26667 | N13: 218.46667 | O13: 88.213667 | P13: 89.066667 | Q13: 92.233333 | R13: 220.16667 | S13: 86.767667 | T13: 92.965667 | U13: 71.133495 | V13: 71.6
B14: 2010Q2 | C14: 5.1434842 | D14: 5.1629152 | E14: 3.4566739 | F14: 2.5426946 | G14: -1.6002845 | H14: 4.6391753 | I14: 1.6443661 | J14: -0.55238584 | K14: 0.35228136 | L14: 1.1283498 | M14: 223.5 | N14: 222.7 | O14: 89.349667 | P14: 90.066667 | Q14: 92.233333 | R14: 223.3 | S14: 87.487 | T14: 93.077 | U14: 71.658198 | V14: 71.7
B15: 2010Q3 | C15: 4.7115534 | D15: 4.6823786 | E15: 3.0852647 | F15: 2.3431595 | G15: -0.92823991 | H15: 5.2436195 | I15: 1.1952697 | J15: 0.15671626 | K15: 0.95509884 | L15: 0.84269663 | M15: 224.46667 | N15: 223.56667 | O15: 89.611333 | P15: 90.266667 | Q15: 92.5 | R15: 226.8 | S15: 87.711 | T15: 93.308 | U15: 72.157943 | V15: 71.8
B16: 2010Q4 | C16: 4.6726097 | D16: 4.6597747 | E16: 3.3762615 | F16: 2.7453931 | G16: 0.071890726 | H16: 4.7677262 | I16: 1.517748 | J16: 0.94693778 | K16: 2.526509 | L16: 2.266289 | M16: 227 | N16: 226.1 | O16: 90.518667 | P16: 91.066667 | Q16: 92.8 | R16: 228.53333 | S16: 88.068 | T16: 93.846667 | U16: 72.883075 | V16: 72.2
... B92: 2029Q4 | C92: 3.0372 | D92: 2.9270383 | E92: 2.1300339 | F92: 2.2044852 | G92: 2.1867986 | H92: 5.4314418 | I92: 2.6517263 | J92: 2.1867986 | K92: 2.0964792 | L92: 1.933554 | M92: 466.27376 | N92: 455.71903 | O92: 155.01771 | P92: 154.87354 | Q92: 149.90629 | R92: 728.39513 | S92: 150.90414 | T92: 151.79367 | U92: 118.68725 | V92: 118.57285
B93: 2030Q1 | C93: 2.7928306 | E93: 2.1135571 | F93: 2.203348 | G93: 2.2522656 | H93: 5.5403475 | I93: 2.4591424 | J93: 2.2522656 | K93: 2.0641801 | L93: 1.9313442 | M93: 467.02175 | O93: 155.16135 | P93: 155.12199 | Q93: 150.68026 | S93: 151.41052 | T93: 152.5774 | U93: 119.27354 | V93: 119.15128
B94: 2030Q2 | C94: 2.3182819 | E94: 1.9971864 | F94: 2.1221404 | G94: 2.31 | I94: 2.5213494 | J94: 2.31 | K94: 2.0284806 | L94: 1.9463531 | M94: 471.86711 | O94: 156.92831 | P94: 156.73138 | Q94: 151.02582 | S94: 152.2823 | T94: 152.9273 | U94: 119.85793 | V94: 119.74046
B95: 2030Q3 | C95: 1.9371314 | E95: 1.9679683 | F95: 2.1117614 | G95: 2.38 | I95: 2.5696463 | J95: 2.38 | K95: 1.9989428 | L95: 1.9722726 | M95: 474.06776 | O95: 157.51219 | P95: 157.46233 | Q95: 152.19326 | S95: 153.7549 | T95: 154.10944 | U95: 120.44792 | V95: 120.33518
B96: 2030Q4 | C96: 2.1210072 | E96: 1.9635954 | F96: 2.1210072 | G96: 2.45 | I96: 2.6181198 | J96: 2.45 | K96: 1.9874005 | L96: 1.9847047 | M96: 476.16346 | O96: 158.06163 | P96: 158.15842 | Q96: 153.57899 | S96: 154.85499 | T96: 155.51262 | U96: 121.04604 | V96: 120.92617
B97: 2031Q1 | C97: 2.1625143 | E97: 2.0000638 | F97: 2.1625142 | G97: 2.52 | I97: 2.7063029 | J97: 2.52 | K97: 1.991092 | L97: 1.9803405 | M97: 477.12117 | O97: 158.26468 | P97: 158.47652 | Q97: 154.47741 | S97: 155.50815 | T97: 156.42235 | U97: 121.64839 | V97: 121.51088
B98: 2031Q2 | C98: 2.1716155 | E98: 1.999796 | F98: 2.1716156 | G98: 2.57 | I98: 2.7295145 | J98: 2.57 | K98: 1.9983476 | L98: 1.9623428 | M98: 482.11424 | O98: 160.06656 | P98: 160.13498 | Q98: 154.90718 | S98: 156.43887 | T98: 156.85753 | U98: 122.25311 | V98: 122.09018
B99: 2031Q3 | C99: 2.1806016 | E99: 1.9996873 | F99: 2.1806015 | G99: 2.62 | I99: 2.7640021 | J99: 2.62 | K99: 2.0022023 | L99: 1.9262406 | M99: 484.40529 | O99: 160.66194 | P99: 160.89596 | Q99: 156.18072 | S99: 158.00469 | T99: 158.14711 | U99: 122.85953 | V99: 122.65313
B100: 2031Q4 | C100: 2.1901945 | E100: 2.0003474 | F100: 2.1901945 | G100: 2.67 | I100: 2.7986178 | J100: 2.67 | K100: 2.0022059 | L100: 1.8912421 | M100: 486.59237 | O100: 161.22341 | P100: 161.6224 | Q100: 157.67955 | S100: 159.18879 | T100: 159.66481 | U100: 123.46963 | V100: 123.21317
B101: 2032Q1 | C101: 2.1989098 | E101: 1.9998958 | F101: 2.1989099 | G101: 2.72 | I101: 2.8133413 | J101: 2.72 | K101: 2.0022608 | L101: 1.8585415 | M101: 487.61263 | O101: 161.42981 | P101: 161.96128 | Q101: 158.67919 | S101: 159.88312 | T101: 160.67703 | U101: 124.08411 | V101: 123.76921
B102: 2008 | C102: 4.0062939 | D102: 4.2552305 | E102: 3.617752 | F102: 3.5524867 | G102: 2.6807173 | H102: -0.28914734 | I102: 3.3295609 | J102: 2.0527899 | K102: 4.081087 | L102: 3.3457249 | M102: 214.825 | N102: 208.45833 | O102: 84.733417 | P102: 86.233333 | Q102: 92.566667 | R102: 387.95 | S102: 84.759 | T102: 94.11725 | U102: 70.693244 | V102: 69.5
B103: 2009 | C103: -0.53144024 | D103: 1.9788127 | E103: 2.1653205 | F103: 1.9617317 | G103: 0.90025207 | H103: -42.376595 | I103: 1.8457234 | J103: -0.68071121 | K103: 0.88348997 | L103: 1.9784173 | M103: 213.68333 | N103: 212.58333 | O103: 86.568167 | P103: 87.925 | Q103: 93.4 | R103: 223.55 | S103: 86.323417 | T103: 93.476583 | U103: 71.317812 | V103: 70.875
B104: 2010 | C104: 4.6213244 | D104: 4.7628381 | E104: 3.2981716 | F104: 2.4926548 | G104: -1.0260528 | H104: 0.5144263 | I104: 1.3727446 | J104: -0.18961968 | K104: 0.89790462 | L104: 1.340388 | M104: 223.55833 | N104: 222.70833 | O104: 89.423333 | P104: 90.116667 | Q104: 92.441667 | R104: 224.7 | S104: 87.508417 | T104: 93.299333 | U104: 71.958178 | V104: 71.825
B105: 2011 | C105: 5.1999849 | D105: 5.2871843 | E105: 4.4636933 | F105: 3.8561124 | G105: 1.5144686 | H105: 3.0559265 | I105: 2.5092824 | J105: 1.2935962 | K105: 3.9007024 | L105: 2.5060912 | M105: 235.18333 | N105: 234.48333 | O105: 93.414917 | P105: 93.591667 | Q105: 93.841667 | R105: 231.56667 | S105: 89.70425 | T105: 94.50625 | U105: 74.765052 | V105: 73.625
B106: 2012 | C106: 3.2067183 | D106: 3.2162911 | E106: 2.8282421 | F106: 2.5732348 | G106: 1.6605985 | H106: 2.3499352 | I106: 3.3419078 | J106: 1.3813019 | K106: 1.6609013 | L106: 1.4940577 | M106: 242.725 | N106: 242.025 | O106: 96.056917 | P106: 96 | Q106: 95.4 | R106: 237.00833 | S106: 92.702083 | T106: 95.811667 | U106: 76.006826 | V106: 74.725
B107: 2013 | C107: 3.0418513 | D107: 3.0540922 | E107: 2.5647988 | F107: 2.2916667 | G107: 1.4063592 | H107: 2.7952605 | I107: 2.4712677 | J107: 1.2623724 | K107: 2.2151078 | L107: 2.1411843 | M107: 250.10833 | N107: 249.41667 | O107: 98.520583 | P107: 98.2 | Q107: 96.741667 | R107: 243.63333 | S107: 94.993 | T107: 97.021167 | U107: 77.690459 | V107: 76.325
B108: 2014 | C108: 2.3689734 | D108: 2.4423655 | E108: 1.4610314 | F108: 1.4511202 | G108: 1.4643811 | H108: -0.044465796 | I108: 2.3398215 | J108: 1.0477095 | K108: 1.1942222 | L108: 1.6049787 | M108: 256.03333 | N108: 255.50833 | O108: 99.96 | P108: 99.625 | Q108: 98.158333 | R108: 243.525 | S108: 97.215667 | T108: 98.037667 | U108: 78.618256 | V108: 77.55
B109: 2015 | C109: 0.97969011 | D109: 1.0273638 | E109: 0.040099373 | F109: 0.36804675 | G109: 1.8762204 | H109: -0.42432338 | I109: 2.8640788 | J109: 2.0016966 | K109: -0.33376507 | L109: 0.67698259 | M109: 258.54167 | N109: 258.13333 | O109: 100.00008 | P109: 99.991667 | Q109: 100 | R109: 242.49167 | S109: 100 | T109: 100.00008 | U109: 78.355855 | V109: 78.075
B110: 2016 | C110: 1.743755 | D110: 1.8724174 | E110: 0.65966612 | F110: 1.0084175 | G110: 2.35 | H110: -3.0928896 | I110: 1.7561667 | J110: 2.4230813 | K110: 1.2447631 | L110: 1.6970861 | M110: 263.05 | N110: 262.96667 | O110: 100.65975 | P110: 101 | Q110: 102.35 | R110: 234.99167 | S110: 101.75617 | T110: 102.42317 | U110: 79.3312 | V110: 79.4
B111: 2017 | C111: 3.5829689 | D111: 3.8059323 | E111: 2.6831314 | F111: 2.5577557 | G111: 1.9866471 | H111: -4.3760418 | I111: 0.95088422 | J111: 1.7266601 | K111: 1.7624913 | L111: 1.5743073 | M111: 272.475 | N111: 272.975 | O111: 103.36058 | P111: 103.58333 | Q111: 104.38333 | R111: 224.70833 | S111: 102.72375 | T111: 104.19167 | U111: 80.729406 | V111: 80.65
B112: 2018 | C112: 3.3428144 | D112: 3.3397442 | E112: 2.4780562 | F112: 2.2928399 | G112: 1.1416254 | H112: 3.5972557 | I112: 0.45348163 | J112: 0.99872031 | K112: 2.0277156 | L112: 1.9528828 | M112: 281.58333 | N112: 282.09167 | O112: 105.92192 | P112: 105.95833 | Q112: 105.575 | R112: 232.79167 | S112: 103.18958 | T112: 105.23225 | U112: 82.366368 | V112: 82.225
B113: 2019 | C113: 2.5628885 | D113: 2.5464536 | E113: 1.7910206 | F113: 1.7381044 | G113: 1.1524193 | H113: 3.1072131 | I113: 0.73416648 | J113: 1.2616538 | K113: 1.4207788 | L113: 2.4627546 | M113: 288.8 | N113: 289.275 | O113: 107.819 | P113: 107.8 | Q113: 106.79167 | R113: 240.025 | S113: 103.94717 | T113: 106.55992 | U113: 83.536612 | V113: 84.25
... B123: 2029 | C123: 2.9821719 | D123: 2.9010406 | E123: 2.1046173 | F123: 2.1660857 | G123: 2.0846402 | H123: 4.7541211 | I123: 2.614385 | J123: 2.0846402 | K123: 2.0739592 | L123: 1.9777822 | M123: 461.71037 | N123: 451.48297 | O123: 153.82382 | P123: 153.58291 | Q123: 148.38468 | R123: 713.6686 | S123: 149.28018 | T123: 150.25291 | U123: 117.77774 | V123: 117.73216
B124: 2030 | C124: 2.2892386 | E124: 2.0101264 | F124: 2.1393127 | G124: 2.3485568 | I124: 2.5425347 | J124: 2.3485568 | K124: 2.0195828 | L124: 1.958779 | M124: 472.28002 | O124: 156.91587 | P124: 156.86853 | Q124: 151.86958 | S124: 153.07568 | T124: 153.78169 | U124: 120.15636 | V124: 120.03827
B125: 2031 | C125: 2.1763035 | E125: 1.9999738 | F125: 2.1763035 | G125: 2.5954059 | I125: 2.7499115 | J125: 2.5954059 | K125: 1.9984848 | L125: 1.9398544 | M125: 482.55827 | O125: 160.05415 | P125: 160.28246 | Q125: 155.81121 | S125: 157.28512 | T125: 157.77295 | U125: 122.55766 | V125: 122.36684
B126: 2008-09 | C126: 2.9765472 | D126: 3.9667782 | E126: 3.7692248 | F126: 3.6392562 | G126: 2.5525663 | H126: -12.784322 | I126: 3.2345869 | J126: 1.6541499 | K126: 3.793365 | L126: 3.7707948 | M126: 214.78333 | N126: 209.675 | O126: 85.3565 | P126: 86.858333 | Q126: 93.075 | R126: 348.60833 | S126: 85.366917 | T126: 94.265333 | U126: 71.142687 | V126: 70.175
B127: 2009-10 | C127: 0.45782591 | D127: 2.5197727 | E127: 2.2387477 | F127: 1.8132975 | G127: -0.062673471 | H127: -37.809863 | I127: 1.4051111 | J127: -1.1598467 | K127: 0.18685301 | L127: 1.282508 | M127: 215.76667 | N127: 214.95833 | O127: 87.267417 | P127: 88.433333 | Q127: 93.016667 | R127: 216.8 | S127: 86.566417 | T127: 93.172 | U127: 71.27562 | V127: 71.075
B128: 2010-11 | C128: 4.9629227 | D128: 4.962202 | E128: 3.511238 | F128: 2.7987185 | G128: -0.34939975 | H128: 4.8124231 | I128: 1.5559344 | J128: 0.41974341 | K128: 2.0207886 | L128: 1.7235315 | M128: 226.475 | N128: 225.625 | O128: 90.331583 | P128: 90.908333 | Q128: 92.691667 | R128: 227.23333 | S128: 87.913333 | T128: 93.563083 | U128: 72.715949 | V128: 72.3
B129: 2011-12 | C129: 4.7981749 | D129: 4.9012004 | E129: 4.3005446 | F129: 3.7400311 | G129: 1.6722107 | H129: 2.1197008 | I129: 2.7878782 | J129: 1.3770567 | K129: 3.3759709 | L129: 2.1438451 | M129: 237.34167 | N129: 236.68333 | O129: 94.216333 | P129: 94.308333 | Q129: 94.241667 | R129: 232.05 | S129: 90.36425 | T129: 94.8515 | U129: 75.170819 | V129: 73.85
B130: 2012-13 | C130: 3.0897792 | D130: 3.0737272 | E130: 2.6538215 | F130: 2.4123001 | G130: 1.5916527 | H130: 3.2320621 | I130: 3.3981912 | J130: 1.3520257 | K130: 1.5753672 | L130: 1.6926202 | M130: 244.675 | N130: 243.95833 | O130: 96.716667 | P130: 96.583333 | Q130: 95.741667 | R130: 239.55 | S130: 93.435 | T130: 96.133917 | U130: 76.355035 | V130: 75.1
B131: 2013-14 | C131: 2.8847792 | D131: 2.9137489 | E131: 2.3043253 | F131: 2.0880069 | G131: 1.3752285 | H131: 1.7985112 | I131: 2.1783414 | J131: 1.1748368 | K131: 2.1481425 | L131: 2.0639148 | M131: 251.73333 | N131: 251.06667 | O131: 98.945333 | P131: 98.6 | Q131: 97.058333 | R131: 243.85833 | S131: 95.470333 | T131: 97.263333 | U131: 77.99525 | V131: 76.65
B132: 2014-15 | C132: 1.9597457 | D132: 2.0280138 | E132: 1.0507486 | F132: 1.1409736 | G132: 1.6141496 | H132: -0.051259372 | I132: 2.5326367 | J132: 1.1559683 | K132: 0.69474305 | L132: 1.4350946 | M132: 256.66667 | N132: 256.15833 | O132: 99.985 | P132: 99.725 | Q132: 98.625 | R132: 243.73333 | S132: 97.88825 | T132: 98.387667 | U132: 78.537116 | V132: 77.75
B133: 2015-16 | C133: 1.0779221 | D133: 1.1386187 | E133: 0.10134854 | F133: 0.44288443 | G133: 1.9011407 | H133: -0.93681616 | I133: 2.8951381 | J133: 2.2821289 | K133: -0.031500615 | L133: 0.67524116 | M133: 259.43333 | N133: 259.075 | O133: 100.08633 | P133: 100.16667 | Q133: 100.5 | R133: 241.45 | S133: 100.72225 | T133: 100.633 | U133: 78.512377 | V133: 78.275
B134: 2016-17 | C134: 2.1424899 | D134: 2.3191483 | E134: 1.1074606 | F134: 1.3727124 | G134: 2.4792703 | H134: -4.224477 | I134: 1.3311359 | J134: 2.30963 | K134: 1.5074151 | L134: 1.980198 | M134: 264.99167 | N134: 265.08333 | O134: 101.19475 | P134: 101.54167 | Q134: 102.99167 | R134: 231.25 | S134: 102.063 | T134: 102.95725 | U134: 79.695884 | V134: 79.825
B135: 2017-18 | C135: 3.7422561 | D135: 3.9075762 | E135: 2.824916 | F135: 2.6343863 | G135: 1.6425277 | H135: -2.2882883 | I135: 0.72634876 | J135: 1.4718083 | K135: 1.8216025 | L135: 1.3153774 | M135: 274.90833 | N135: 275.44167 | O135: 104.05342 | P135: 104.21667 | Q135: 104.68333 | R135: 225.95833 | S135: 102.80433 | T135: 104.47258 | U135: 81.147626 | V135: 80.875
B136: 2018-19 | C136: 3.055564 | D136: 3.0314949 | E136: 2.2675853 | F136: 2.1269791 | G136: 1.1383538 | H136: 4.097363 | I136: 0.5437514 | J136: 1.009276 | K136: 1.8311465 | L136: 2.2256569 | M136: 283.30833 | N136: 283.79167 | O136: 106.41292 | P136: 106.43333 | Q136: 105.875 | R136: 235.21667 | S136: 103.36333 | T136: 105.527 | U136: 82.633558 | V136: 82.675
B137: 2019-20 | C137: 2.5884637 | D137: 2.6016738 | E137: 1.7392939 | F137: 1.699029 | G137: 1.1806375 | H137: 1.842273 | I137: 0.75518398 | J137: 1.3313338 | K137: 1.2804629 | L137: 2.691261 | M137: 290.64167 | N137: 291.175 | O137: 108.26375 | P137: 108.24167 | Q137: 107.125 | R137: 239.55 | S137: 104.14392 | T137: 106.93192 | U137: 83.69165 | V137: 84.9
... B146: 2028-29 | C146: 2.9154566 | D146: 2.8037592 | E146: 2.0135763 | F146: 2.0689886 | G146: 1.9425549 | H146: 5.408803 | I146: 2.6428378 | J146: 1.9425549 | K146: 2.070026 | L146: 1.9597 | M146: 451.51322 | N146: 441.79777 | O146: 151.40549 | P146: 151.10034 | Q146: 146.06984 | R146: 688.20521 | S146: 146.42822 | T146: 147.90892 | U146: 115.96579 | V146: 116.02508
B147: 2029-30 | C147: 2.9610065 | E147: 2.1275392 | F147: 2.1962996 | G147: 2.152796 | H147: 5.1083488 | I147: 2.5681283 | J147: 2.152796 | K147: 2.0825187 | L147: 1.9577478 | M147: 464.88256 | O147: 154.6267 | P147: 154.41896 | Q147: 149.21443 | S147: 150.18868 | T147: 151.0931 | U147: 118.3808 | V147: 118.29656
B148: 2030-31 | C148: 2.1343707 | E148: 1.982192 | F148: 2.1294045 | G148: 2.4156124 | I148: 2.604323 | J148: 2.4156124 | K148: 2.0014002 | L148: 1.9709857 | M148: 474.80487 | O148: 157.6917 | P148: 157.70716 | Q148: 152.81887 | S148: 154.10008 | T148: 154.74293 | U148: 120.75007 | V148: 120.62817
B149: 2031-32 | C149: 2.1853734 | E149: 1.9999321 | F149: 2.1853735 | G149: 2.6454802 | I149: 2.7766258 | J149: 2.6454802 | K149: 2.0012614 | L149: 1.9093799 | M149: 485.18113 | O149: 160.84543 | P149: 161.15365 | Q149: 156.86166 | S149: 158.37887 | T149: 158.83662 | U149: 123.16659 | V149: 122.93142
B150: Notes:
B151: RPI, RPIX, CPI and CPIH inflation are based on outturn data up to and including July 2026.
B152: Consumer expenditure deflator and GDP deflator are based on the Quarterly National Accounts released by the ONS on 13 August 2026.
B153: Actual rents for housing’ component of CPI. This series is constructed using forecasts of social housing rents and private rents.
B154: Definitions:
B155: All items Retail Prices Index (RPI), all items Retail Prices Index excluding mortgage interest payments (RPIX) (percentage change over 12 months) (ONS Consumer Prices Index Bulletin, identifier: CZBH and CDKQ respectively). Due to a change in methodology we will not forecast RPIX after 2029 Q4.
B156: All items Consumer Prices Index (CPI), All items Consumer Prices Index including owner occupiers' housing costs (CPIH), Owner occupiers' housing costs (OOH) (percentage change over 12 months) (ONS Consumer Prices Index Bulletin, identifier: D7G7, L55O, and L5P7 respectively)
B157: Mortgage Interest Payments (ONS Consumer Prices Index Statistical Bulletin, identifier: CZCR). Due to the announced change in RPI methodology by the ONS from February 2030 we do not forecast RPI Mortgage Interest Payments and RPIX after 2029 Q4.
B158: Actual rents for housing (ONS Consumer Prices Index Bulletin, identifier: D7GQ)
B159: Private rentals for housing (ONS Consumer Prices Index Bulletin, identifier: KYHJ)
B160: Consumer expenditure deflator: Households final consumption expenditure at current market prices (ABJQ) plus non-profit institutions (HAYE) divided by Households final consumption expenditure, chained volume measure (ABJR) plus non-profit institutions (HAYO)

Sheet 1.8
A1: Back to contents
B2: 1.8 Balance of payments (£ billion, current prices)
C3: Trade balance | D3: Trade balance (% GDP) | E3: Investment income balance | F3: Employee income balance | G3: Transfers balance | H3: Current account balance | I3: Current account balance (% GDP)
B4: 2008Q1 | C4: -9.557 | D4: -2.3909476 | E4: -0.484 | F4: -0.135 | G4: -4.019 | H4: -14.195 | I4: -3.5512714
B5: 2008Q2 | C5: -8.228 | D5: -2.0432743 | E5: -4.564 | F5: -0.199 | G5: -3.656 | H5: -16.647 | I5: -4.13398
B6: 2008Q3 | C6: -6.5 | D6: -1.6163646 | E6: -4.26 | F6: -0.165 | G6: -3.542 | H6: -14.467 | I6: -3.5975302
B7: 2008Q4 | C7: -2.595 | D7: -0.65253962 | E7: -11.008 | F7: -0.216 | G7: -2.417 | H7: -16.236 | I7: -4.0827103
B8: 2009Q1 | C8: -4.828 | D8: -1.2386633 | E8: -6.959 | F8: -0.025 | G8: -3.75 | H8: -15.562 | I8: -3.9925598
B9: 2009Q2 | C9: -4.599 | D9: -1.1818035 | E9: -5.777 | F9: -0.041 | G9: -4.411 | H9: -14.828 | I9: -3.8103461
B10: 2009Q3 | C10: -5.842 | D10: -1.493434 | E10: 0.933 | F10: -0.095 | G10: -3.798 | H10: -8.802 | I10: -2.2501208
B11: 2009Q4 | C11: -4.052 | D11: -1.0408425 | E11: -0.95 | F11: -0.098 | G11: -3.323 | H11: -8.423 | I11: -2.163627
B12: 2010Q1 | C12: -5.311 | D12: -1.3339998 | E12: 0.186 | F12: -0.04 | G12: -4.556 | H12: -9.721 | I12: -2.4416893
B13: 2010Q2 | C13: -5.241 | D13: -1.3006996 | E13: 0.542 | F13: -0.096 | G13: -4.305 | H13: -9.1 | I13: -2.2584176
B14: 2010Q3 | C14: -7.817 | D14: -1.9245304 | E14: -0.439 | F14: -0.089 | G14: -4.923 | H14: -13.268 | I14: -3.2665562
B15: 2010Q4 | C15: -6.813 | D15: -1.667405 | E15: 0.807 | F15: -0.164 | G15: -6.246 | H15: -12.416 | I15: -3.0386761
... B100: 2032Q1 | C100: -8.3070857 | D100: -0.86334333 | E100: -9.9330839 | F100: 0.05262447 | G100: -4.5850333 | H100: -22.772578 | I100: -2.366721
B101: 2008 | C101: -26.88 | D101: -1.6776754 | E101: -20.316 | F101: -0.715 | G101: -13.634 | H101: -61.545 | I101: -3.84124
B102: 2009 | C102: -19.321 | D102: -1.2389982 | E102: -12.753 | F102: -0.259 | G102: -15.282 | H102: -47.615 | I102: -3.0534082
B103: 2010 | C103: -25.182 | D103: -1.5584473 | E103: 1.096 | F103: -0.389 | G103: -20.03 | H103: -44.505 | I103: -2.7542967
B104: 2011 | C104: -13.263 | D104: -0.79421777 | E104: 7.114 | F104: -0.173 | G104: -20.908 | H104: -27.23 | I104: -1.6305926
B105: 2012 | C105: -16.697 | D105: -0.96979279 | E105: -15.812 | F105: -0.148 | G105: -21 | H105: -53.657 | I105: -3.1164983
B106: 2013 | C106: -23.335 | D106: -1.3043075 | E106: -31.243 | F106: -0.326 | G106: -25.863 | H106: -80.767 | I106: -4.5144634
B107: 2014 | C107: -32.945 | D107: -1.7570048 | E107: -32.803 | F107: -0.469 | G107: -24.081 | H107: -90.298 | I107: -4.8157238
B108: 2015 | C108: -26.354 | D108: -1.3668974 | E108: -41.679 | F108: -0.09 | G108: -24.083 | H108: -92.206 | I108: -4.7824292
B109: 2016 | C109: -34.41 | D109: -1.7164192 | E109: -46.373 | F109: -0.36 | G109: -24.008 | H109: -105.151 | I109: -5.2450798
B110: 2017 | C110: -26.053 | D110: -1.2422624 | E110: -22.093 | F110: -0.31 | G110: -22.419 | H110: -70.875 | I110: -3.3794706
B111: 2018 | C111: -26.074 | D111: -1.2007042 | E111: -28.868 | F111: -0.386 | G111: -25.514 | H111: -80.842 | I111: -3.7227632
B112: 2019 | C112: -26.987 | D112: -1.1978459 | E112: -1.802 | F112: -0.457 | G112: -26.616 | H112: -55.862 | I112: -2.4794925
... B124: 2031 | C124: -34.899308 | D124: -0.92568527 | E124: -38.908549 | F124: 0.19092151 | G124: -18.034658 | H124: -91.651593 | I124: -2.431009
B125: 2008-09 | C125: -22.151 | D125: -1.3911533 | E125: -26.791 | F125: -0.605 | G125: -13.365 | H125: -62.912 | I125: -3.9510738
B126: 2009-10 | C126: -19.804 | D126: -1.2632068 | E126: -5.608 | F126: -0.274 | G126: -16.088 | H126: -41.774 | I126: -2.6645728
B127: 2010-11 | C127: -19.481 | D127: -1.192057 | E127: 2.66 | F127: -0.397 | G127: -20.868 | H127: -38.086 | I127: -2.3305108
B128: 2011-12 | C128: -13.652 | D128: -0.8125818 | E128: 2.903 | F128: -0.138 | G128: -20.702 | H128: -31.589 | I128: -1.8802114
B129: 2012-13 | C129: -18.743 | D129: -1.0802303 | E129: -24.132 | F129: -0.229 | G129: -22.218 | H129: -65.322 | I129: -3.764755
B130: 2013-14 | C130: -27.803 | D130: -1.5363184 | E130: -26.247 | F130: -0.307 | G130: -25.284 | H130: -79.641 | I130: -4.4007458
B131: 2014-15 | C131: -36.4 | D131: -1.9234834 | E131: -36.967 | F131: -0.464 | G131: -24.043 | H131: -97.874 | I131: -5.171951
B132: 2015-16 | C132: -23.765 | D132: -1.2233327 | E132: -46.549 | F132: -0.005 | G132: -24.081 | H132: -94.4 | I132: -4.8593566
B133: 2016-17 | C133: -32.98 | D133: -1.6250973 | E133: -36.096 | F133: -0.34 | G133: -23.21 | H133: -92.626 | I133: -4.5641679
B134: 2017-18 | C134: -26.614 | D134: -1.2582982 | E134: -26.025 | F134: -0.457 | G134: -23.283 | H134: -76.379 | I134: -3.6111654
B135: 2018-19 | C135: -44.959 | D135: -2.0525662 | E135: -20.851 | F135: -0.388 | G135: -26.651 | H135: -92.849 | I135: -4.2389448
B136: 2019-20 | C136: 0.799 | D136: 0.035379938 | E136: -10.082 | F136: -0.371 | G136: -25.857 | H136: -35.511 | I136: -1.5724368
... B148: 2031-32 | C148: -34.221755 | D148: -0.90014674 | E148: -39.127702 | F148: 0.19861041 | G148: -18.162945 | H148: -91.313791 | I148: -2.4018585
B149: Definitions:
B150: Balance of trade in goods & services (ONS UK Trade release, identifier: IKBJ)
B151: Investment income balance (ONS identifier: HBOM+MT5X)
B152: Employee income balance (ONS identifiers: IJAH-IJAI)
B153: Transfers balance (ONS identifier: IKBP)
B154: Current balance (ONS Balance of Payments identifier: HBOP)
B155: Current balance (% of GDP) (ONS identifier: AA6H)

Sheet 1.9
A1: Back to contents
B2: 1.9 Market-derived assumptions
C3: Bank Rate | D3: Long-term interest rates (20-year gilts) | E3: Average mortgage rate | F3: Deposit rate | G3: Trade-weighted sterling effective exchange rate | H3: US$/£ exchange rate | I3: €/£ exchange rate | J3: Oil prices ($) | K3: Gas prices (£) | L3: Equity prices
B4: 2008Q1 | C4: 5.3548 | D4: 4.5371 | E4: 5.8566667 | F4: 3.7931043 | G4: 95.8724 | H4: 1.978 | I4: 1.3212 | J4: 96.7 | K4: 0.52762943 | L4: 2927.05
B5: 2008Q2 | C5: 5.0278 | D5: 4.8686 | E5: 5.7633333 | F5: 3.6347041 | G5: 93.0504 | H5: 1.9708 | I5: 1.2615 | J5: 122.2 | K5: 0.63075505 | L5: 2855.6899
B6: 2008Q3 | C6: 5 | D6: 4.7852 | E6: 5.7966667 | F6: 3.7349071 | G6: 91.6517 | H6: 1.8934 | I6: 1.2586 | J6: 115.6 | K6: 0.66140476 | L6: 2483.6699
B7: 2008Q4 | C7: 3.3672 | D7: 4.5359 | E7: 5.3866667 | F7: 3.1819631 | G7: 83.9687 | H7: 1.5742 | I7: 1.1957 | J7: 55.8 | K7: 0.65293928 | L7: 2209.29
B8: 2009Q1 | C8: 1.0714 | D8: 4.2021 | E8: 4.0833333 | F8: 1.8028066 | G8: 77.8965 | H8: 1.4342 | I8: 1.101 | J8: 44.9 | K8: 0.45511028 | L8: 1984.2
B9: 2009Q2 | C9: 0.5 | D9: 4.366 | E9: 3.6 | F9: 1.5103333 | G9: 81.3212 | H9: 1.5533 | I9: 1.1389 | J9: 59.2 | K9: 0.27579152 | L9: 2172.1001
B10: 2009Q3 | C10: 0.5 | D10: 4.2522 | E10: 3.5766667 | F10: 1.406849 | G10: 82.9269 | H10: 1.6406 | I10: 1.1475 | J10: 68.4 | K10: 0.23301544 | L10: 2634.8
B11: 2009Q4 | C11: 0.5 | D11: 4.1971 | E11: 3.5733333 | F11: 1.3752951 | G11: 80.3886 | H11: 1.6343 | I11: 1.1058 | J11: 75 | K11: 0.27863333 | L11: 2760.8
B12: 2010Q1 | C12: 0.5 | D12: 4.5056 | E12: 3.6666667 | F12: 1.4102669 | G12: 79.6194 | H12: 1.5584 | I12: 1.1269 | J12: 76.7 | K12: 0.35896667 | L12: 2910.2
B13: 2010Q2 | C13: 0.5 | D13: 4.3618 | E13: 3.66 | F13: 1.4336856 | G13: 79.8981 | H13: 1.4909 | I13: 1.1747 | J13: 78.7 | K13: 0.38143333 | L13: 2543.5
B14: 2010Q3 | C14: 0.5 | D14: 4.0318 | E14: 3.57 | F14: 1.4292736 | G14: 81.7638 | H14: 1.551 | I14: 1.1995 | J14: 76.4 | K14: 0.43106667 | L14: 2867.6001
B15: 2010Q4 | C15: 0.5 | D15: 4.0978 | E15: 3.5066667 | F15: 1.4906262 | G15: 80.2965 | H15: 1.5811 | I15: 1.1639 | J15: 86.8 | K15: 0.5264 | L15: 3062.8999
... B100: 2032Q1 | C100: 4.5764 | D100: 6.1718 | E100: 4.969337 | F100: 3.0705735 | G100: 85.741 | H100: 1.3525 | I100: 1.1692 | J100: 73.9 | K100: 0.699 | L100: 6834.1897
B101: 2008 | C101: 4.68745 | D101: 4.6817 | E101: 5.7008333 | F101: 3.5861697 | G101: 91.1358 | H101: 1.8541 | I101: 1.25925 | J101: 97.6 | K101: =AVERAGE(OFFSET(K$4:K$7,4*ROWS(K$4:K4)-4,,4)) -> 0.61818213 | L101: 2618.925
B102: 2009 | C102: 0.64285 | D102: 4.25435 | E102: 3.7083333 | F102: 1.523821 | G102: 80.6333 | H102: 1.5656 | I102: 1.1233 | J102: 61.9 | K102: =AVERAGE(OFFSET(K$4:K$7,4*ROWS(K$4:K5)-4,,4)) -> 0.31063764 | L102: 2387.975
B103: 2010 | C103: 0.5 | D103: 4.24925 | E103: 3.6008333 | F103: 1.4409631 | G103: 80.39445 | H103: 1.54535 | I103: 1.16625 | J103: 79.6 | K103: =AVERAGE(OFFSET(K$4:K$7,4*ROWS(K$4:K6)-4,,4)) -> 0.42446667 | L103: 2846.05
B104: 2011 | C104: 0.5 | D104: 3.838075 | E104: 3.4333333 | F104: 1.6127511 | G104: 79.94395 | H104: 1.603275 | I104: 1.152525 | J104: 111.1 | K104: =AVERAGE(OFFSET(K$4:K$7,4*ROWS(K$4:K7)-4,,4)) -> 0.563025 | L104: 2919.17
B105: 2012 | C105: 0.5 | D105: 2.86545 | E105: 3.375 | F105: 1.7476551 | G105: 83.008775 | H105: 1.585075 | I105: 1.23365 | J105: 112 | K105: 0.597 | L105: 2996.625
B106: 2013 | C106: 0.5 | D106: 3.187225 | E106: 3.3266667 | F106: 1.5136602 | G106: 81.405925 | H106: 1.56415 | I106: 1.177625 | J106: 108.9 | K106: 0.681 | L106: 3405.9575
B107: 2014 | C107: 0.5 | D107: 3.102025 | E107: 3.2208333 | F107: 1.1190039 | G107: 86.9354 | H107: 1.648025 | I107: 1.240675 | J107: 98.9 | K107: 0.501 | L107: 3552.7325
B108: 2015 | C108: 0.5 | D108: 2.408075 | E108: 3.0816667 | F108: 0.9819606 | G108: 91.38135 | H108: 1.5285 | I108: 1.378125 | J108: 52.4 | K108: 0.427 | L108: 3503.585
B109: 2016 | C109: 0.398075 | D109: 1.911675 | E109: 2.84 | F109: 0.79001942 | G109: 81.9531 | H109: 1.354775 | I109: 1.224025 | J109: 44 | K109: 0.347 | L109: 3533.3647
B110: 2017 | C110: 0.289675 | D110: 1.8226 | E110: 2.5658333 | F110: 0.47750615 | G110: 77.306475 | H110: 1.2889 | I110: 1.141525 | J110: 54.4 | K110: 0.451 | L110: 4035.9708
B111: 2018 | C111: 0.60255 | D111: 1.83635 | E111: 2.4941667 | F111: 0.54098736 | G111: 78.422075 | H111: 1.335575 | I111: 1.130575 | J111: 71.1 | K111: 0.604 | L111: 4045.8626
B112: 2019 | C112: 0.75 | D112: 1.313075 | E112: 2.425 | F112: 0.57342337 | G112: 78.069625 | H112: 1.27695 | I112: 1.140525 | J112: 64 | K112: 0.347 | L112: 3994.2249
B113: 2020 | C113: 0.227925 | D113: 0.738175 | E113: 2.2008333 | F113: 0.3364627 | G113: 78.00115 | H113: 1.2832 | I113: 1.125075 | J113: 42.3 | K113: 0.248 | L113: 3495.0492
B114: 2021 | C114: 0.10585 | D114: 1.146075 | E114: 2.0591667 | F114: 0.14111882 | G114: 81.4098 | H114: 1.37595 | I114: 1.1632 | J114: 70.4 | K114: 1.159 | L114: 3996.5506
B115: 2022 | C115: 1.45935 | D115: 2.623975 | E115: 2.1733333 | F115: 0.38333925 | G115: 79.69175 | H115: 1.236675 | I115: 1.173275 | J115: 99.8 | K115: 2.115 | L115: 4068.6291
B116: 2023 | C116: 4.681 | D116: 4.20345 | E116: 2.9625 | F116: 1.8215773 | G116: 80.50995 | H116: 1.24355 | I116: 1.15005 | J116: 82.2 | K116: 0.992 | L116: 4152.3004
... B124: 2031 | C124: 4.482125 | D124: 6.11625 | E124: 4.8878586 | F124: 2.9711519 | G124: 85.741 | H124: 1.3525 | I124: 1.1692 | J124: 72.9 | K124: 0.689 | L124: 6694.4569
B125: 2008-09 | C125: 3.6166 | D125: 4.59795 | E125: 5.2575 | F125: 3.0885953 | G125: 86.641825 | H125: 1.71815 | I125: 1.2042 | J125: 84.6 | K125: =AVERAGE(OFFSET(K$5:K$8,4*ROWS(K$5:K5)-4,,4)) -> 0.60005234 | L125: 2383.2124
B126: 2009-10 | C126: 0.5 | D126: 4.330225 | E126: 3.6041667 | F126: 1.4256861 | G126: 81.064025 | H126: 1.59665 | I126: 1.129775 | J126: 69.8 | K126: =AVERAGE(OFFSET(K$5:K$8,4*ROWS(K$5:K6)-4,,4)) -> 0.28660174 | L126: 2619.475
B127: 2010-11 | C127: 0.5 | D127: 4.208875 | E127: 3.5583333 | F127: 1.4722675 | G127: 80.6944 | H127: 1.5566 | I127: 1.177275 | J127: 86.7 | K127: =AVERAGE(OFFSET(K$5:K$8,4*ROWS(K$5:K7)-4,,4)) -> 0.47648333 | L127: 2885.425
B128: 2011-12 | C128: 0.5 | D128: 3.516625 | E128: 3.4008333 | F128: 1.6593954 | G128: 80.032375 | H128: 1.59525 | I128: 1.1594 | J128: 114.5 | K128: =AVERAGE(OFFSET(K$5:K$8,4*ROWS(K$5:K8)-4,,4)) -> 0.56976667 | L128: 2902.94
B129: 2012-13 | C129: 0.5 | D129: 2.85705 | E129: 3.375 | F129: 1.742634 | G129: 82.796275 | H129: 1.580225 | I129: 1.2278 | J129: 110.5 | K129: 0.634 | L129: 3066.09
B130: 2013-14 | C130: 0.5 | D130: 3.2765 | E130: 3.2975 | F130: 1.3948989 | G130: 82.715775 | H130: 1.58995 | I130: 1.185825 | J130: 107.6 | K130: 0.646 | L130: 3474.695
B131: 2014-15 | C131: 0.5 | D131: 2.810625 | E131: 3.1966667 | F131: 1.0659645 | G131: 87.889525 | H131: 1.612725 | I131: 1.275275 | J131: 85.5 | K131: 0.47 | L131: 3579.73
B132: 2015-16 | C132: 0.5 | D132: 2.42065 | E132: 3.0308333 | F132: 0.95504009 | G132: 90.774875 | H132: 1.5077 | I132: 1.366075 | J132: 47.5 | K132: 0.383 | L132: 3410.4872
B133: 2016-17 | C133: 0.335575 | D133: 1.820325 | E133: 2.7591667 | F133: 0.68833245 | G133: 79.474775 | H133: 1.306925 | I133: 1.190175 | J133: 49 | K133: 0.392 | L133: 3698.4221
B134: 2017-18 | C134: 0.352175 | D134: 1.8175 | E134: 2.5391667 | F134: 0.48567108 | G134: 77.79985 | H134: 1.32705 | I134: 1.13395 | J134: 57.6 | K134: 0.474 | L134: 4059.3482
B135: 2018-19 | C135: 0.66505 | D135: 1.780225 | E135: 2.48 | F135: 0.55181826 | G135: 78.353825 | H135: 1.31325 | I135: 1.134275 | J135: 70.2 | K135: 0.579 | L135: 4003.8596
B136: 2019-20 | C136: 0.715425 | D136: 1.1261 | E136: 2.3983333 | F136: 0.56493902 | G136: 78.19135 | H136: 1.2711 | I136: 1.143975 | J136: 60.8 | K136: 0.289 | L136: 3978.5612
B137: 2020-21 | C137: 0.1 | D137: 0.7759 | E137: 2.1341667 | F137: 0.24336606 | G137: 78.307425 | H137: 1.308175 | I137: 1.121075 | J137: 44.8 | K137: 0.311 | L137: 3488.5682
B138: 2021-22 | C138: 0.194925 | D138: 1.26915 | E138: 2.0433333 | F138: 0.13415599 | G138: 81.88425 | H138: 1.366475 | I138: 1.1758 | J138: 80 | K138: 1.622 | L138: 4092.7482
B139: 2022-23 | C139: 2.30915 | D139: 3.176825 | E139: 2.3291667 | F139: 0.64716959 | G139: 78.648425 | H139: 1.205175 | I139: 1.15755 | J139: 95.4 | K139: 1.857 | L139: 4086.6585
B140: 2023-24 | C140: 5.029625 | D140: 4.32955 | E140: 3.1683333 | F140: 2.1477471 | G140: 81.609775 | H140: 1.25675 | I140: 1.158975 | J140: 82.4 | K140: 0.834 | L140: 4138.1849
... B148: 2031-32 | C148: 4.51875 | D148: 6.139025 | E148: 4.9205441 | F148: 3.0105778 | G148: 85.741 | H148: 1.3525 | I148: 1.1692 | J148: 73.3 | K148: 0.693 | L148: 6750.7318
B149: Definitions:
B150: Official Bank Rate (Bank of England, Bankstats, identifier: IUQABEDR)
B151: 20-year government gilt yields (Bank of England, Bankstats, identifier: IUQALNPY)
B152: Average mortgage rate (Bank of England, Bankstats, identifier: CFMHSDE)
B153: Sterling effective exchange rate (index) (Bank of England, Bankstats, identifier: XUQABK67)
B154: US$/£ exchange rate (Bank of England, Bankstats, identifier: XUQAUSS)
B155: Euro/£ exchange rate (Bank of England, Bankstats, identifier: XUQAERS)
B156: US dollar european crude dated brent spot is used as outturn, ICE brent crude futures are used for the economy forecast window (Bloomberg).
B157: UK natural gas 1M Fwd (Bloomberg) - Gas price expectations averaged over our economy forecast window, day-ahead future expectations for each month used as outturn (Ofgem and Bloomberg).
B158: FTSE All-Share Index (Bloomberg)

Sheet 1.10
A1: Back to contents
B2: 1.10 Financial balances by sector
C3: % GDP | H3: £ billion
C4: Household | D4: Corporate | E4: Public | F4: Rest of world | G4: Statistical discrepancy1 | H4: Household | I4: Corporate | J4: Public | K4: Rest of world | L4: Statistical discrepancy1
B5: 2008Q1 | C5: 0.68998989 | D5: -0.58416476 | E5: -3.5920504 | F5: 3.4862252 | G5: =0-SUM(C5:F5) -> 0 | H5: 2.758 | I5: -2.335 | J5: -14.358 | K5: 13.935 | L5: =0-SUM(H5:K5) -> 0
B6: 2008Q2 | C6: 1.8254873 | D6: -1.5508323 | E6: -4.4165816 | F6: 4.1419266 | G6: =0-SUM(C6:F6) -> 0 | H6: 7.351 | I6: -6.245 | J6: -17.785 | K6: 16.679 | L6: =0-SUM(H6:K6) -> 0
B7: 2008Q3 | C7: 1.4592042 | D7: 0.79699207 | E7: -5.8741175 | F7: 3.6179213 | G7: =0-SUM(C7:F7) -> 0 | H7: 5.868 | I7: 3.205 | J7: -23.622 | K7: 14.549 | L7: =0-SUM(H7:K7) -> 0
B8: 2008Q4 | C8: 4.0193423 | D8: -0.38020806 | E8: -7.7407041 | F8: 4.1015699 | G8: =0-SUM(C8:F8) -> 0 | H8: 15.984 | I8: -1.512 | J8: -30.783 | K8: 16.311 | L8: =0-SUM(H8:K8) -> 0
B9: 2009Q1 | C9: 3.821692 | D9: 3.1643897 | E9: -10.951446 | F9: 3.9653646 | G9: =0-SUM(C9:F9) -> 0 | H9: 14.896 | I9: 12.334 | J9: -42.686 | K9: 15.456 | L9: =0-SUM(H9:K9) -> 0
B10: 2009Q2 | C10: 5.3776041 | D10: 0.59976719 | E10: -9.8270337 | F10: 3.8496625 | G10: =0-SUM(C10:F10) -> 0 | H10: 20.927 | I10: 2.334 | J10: -38.242 | K10: 14.981 | L10: =0-SUM(H10:K10) -> 0
B11: 2009Q3 | C11: 5.1454705 | D11: 2.0458665 | E11: -9.4123151 | F11: 2.2209781 | G11: =0-SUM(C11:F11) -> 0 | H11: 20.128 | I11: 8.003 | J11: -36.819 | K11: 8.688 | L11: =0-SUM(H11:K11) -> 0
B12: 2009Q4 | C12: 5.7472386 | D12: 3.3768302 | E12: -11.289751 | F12: 2.165682 | G12: =0-SUM(C12:F12) -> 0 | H12: 22.374 | I12: 13.146 | J12: -43.951 | K12: 8.431 | L12: =0-SUM(H12:K12) -> 0
B13: 2010Q1 | C13: 7.0560576 | D13: 0.32401802 | E13: -9.7491749 | F13: 2.3690992 | G13: =0-SUM(C13:F13) -> 0 | H13: 28.092 | I13: 1.29 | J13: -38.814 | K13: 9.432 | L13: =0-SUM(H13:K13) -> 0
B14: 2010Q2 | C14: 5.4797648 | D14: 0.68918963 | E14: -8.4621169 | F14: 2.2934106 | G14: =0-SUM(C14:F14) -> -0.00024817775 | H14: 22.08 | I14: 2.777 | J14: -34.097 | K14: 9.241 | L14: =0-SUM(H14:K14) -> -0.001
B15: 2010Q3 | C15: 4.7486687 | D15: 1.5114101 | E15: -9.6866637 | F15: 3.426585 | G15: =0-SUM(C15:F15) -> 0 | H15: 19.288 | I15: 6.139 | J15: -39.345 | K15: 13.918 | L15: =0-SUM(H15:K15) -> 0
B16: 2010Q4 | C16: 4.7929633 | D16: 1.9987812 | E16: -9.9302739 | F16: 3.1382847 | G16: =0-SUM(C16:F16) -> 0.00024473873 | H16: 19.584 | I16: 8.167 | J16: -40.575 | K16: 12.823 | L16: =0-SUM(H16:K16) -> 0.001
... B101: 2032Q1 | C101: -1.5435976 | D101: 1.1636076 | E101: -1.7659663 | F101: 2.316141 | G101: =0-SUM(C101:F101) -> -0.17018476 | H101: -14.852489 | I101: 11.196227 | J101: -16.99212 | K101: 22.285898 | L101: =0-SUM(H101:K101) -> -1.637517
B102: 2008 | C102: 1.9947985 | D102: -0.4298419 | E102: -5.4017652 | F102: 3.8368086 | G102: =0-SUM(C102:F102) -> 0 | H102: 31.961 | I102: -6.887 | J102: -86.548 | K102: 61.474 | L102: =0-SUM(H102:K102) -> 0
B103: 2009 | C103: 5.0227491 | D103: 2.2968376 | E103: -10.369211 | F103: 3.0496247 | G103: =0-SUM(C103:F103) -> 0 | H103: 78.325 | I103: 35.817 | J103: -161.698 | K103: 47.556 | L103: =0-SUM(H103:K103) -> 0
B104: 2010 | C104: 5.5106975 | D104: 1.1370564 | E104: -9.4583062 | F104: 2.8105523 | G104: =0-SUM(C104:F104) -> 0 | H104: 89.044 | I104: 18.373 | J104: -152.831 | K104: 45.414 | L104: =0-SUM(H104:K104) -> 0
B105: 2011 | C105: 3.7062897 | D105: 2.1894733 | E105: -7.5854594 | F105: 1.6899359 | G105: =0-SUM(C105:F105) -> -0.00023952885 | H105: 61.893 | I105: 36.563 | J105: -126.673 | K105: 28.221 | L105: =0-SUM(H105:K105) -> -0.004
B106: 2012 | C106: 3.058823 | D106: 1.7813125 | E106: -8.0055968 | F106: 3.1654613 | G106: =0-SUM(C106:F106) -> 0 | H106: 52.664 | I106: 30.669 | J106: -137.833 | K106: 54.5 | L106: =0-SUM(H106:K106) -> 0
B107: 2013 | C107: 2.5110225 | D107: -1.8600146 | E107: -5.2454569 | F107: 4.594449 | G107: =0-SUM(C107:F107) -> 0 | H107: 44.924 | I107: -33.277 | J107: -93.845 | K107: 82.198 | L107: =0-SUM(H107:K107) -> 0
B108: 2014 | C108: 1.7163129 | D108: -1.0792687 | E108: -5.5649241 | F108: 4.9278799 | G108: =0-SUM(C108:F108) -> 0 | H108: 32.182 | I108: -20.237 | J108: -104.346 | K108: 92.401 | L108: =0-SUM(H108:K108) -> 0
B109: 2015 | C109: 3.418955 | D109: -3.7843047 | E109: -4.5132406 | F109: 4.8785902 | G109: =0-SUM(C109:F109) -> 0 | H109: 65.918 | I109: -72.962 | J109: -87.016 | K109: 94.06 | L109: =0-SUM(H109:K109) -> 0
B110: 2016 | C110: 0.88235221 | D110: -2.8296725 | E110: -3.3775199 | F110: 5.3248402 | G110: =0-SUM(C110:F110) -> 0 | H110: 17.689 | I110: -56.728 | J110: -67.711 | K110: 106.75 | L110: =0-SUM(H110:K110) -> 0
B111: 2017 | C111: -0.32624109 | D111: -0.92112328 | E111: -2.5977221 | F111: 3.8450865 | G111: =0-SUM(C111:F111) -> 0 | H111: -6.842 | I111: -19.318 | J111: -54.48 | K111: 80.64 | L111: =0-SUM(H111:K111) -> 0
B112: 2018 | C112: -0.52892876 | D112: -1.195869 | E112: -2.123037 | F112: 3.8478347 | G112: =0-SUM(C112:F112) -> 0 | H112: -11.486 | I112: -25.969 | J112: -46.103 | K112: 83.558 | L112: =0-SUM(H112:K112) -> 0
B113: 2019 | C113: -0.17408202 | D113: 0.022015472 | E113: -2.3861043 | F113: 2.5381709 | G113: =0-SUM(C113:F113) -> 0 | H113: -3.922 | I113: 0.496 | J113: -53.758 | K113: 57.184 | L113: =0-SUM(H113:K113) -> 0
... B125: 2031 | C125: -1.2006089 | D125: 0.84489351 | E125: -1.8486517 | F125: 2.3791337 | G125: =0-SUM(C125:F125) -> -0.17476664 | H125: -45.264218 | I125: 31.853373 | J125: -69.696112 | K125: 89.695842 | L125: =0-SUM(H125:K125) -> -6.5888858
B126: 2008-09 | C126: 2.7695575 | D126: 0.48873437 | E126: -7.2145784 | F126: 3.9562865 | G126: =0-SUM(C126:F126) -> 0 | H126: 44.099 | I126: 7.782 | J126: -114.876 | K126: 62.995 | L126: =0-SUM(H126:K126) -> 0
B127: 2009-10 | C127: 5.8377069 | D127: 1.5801566 | E127: -10.067 | F127: 2.6491367 | G127: =0-SUM(C127:F127) -> 0 | H127: 91.521 | I127: 24.773 | J127: -157.826 | K127: 41.532 | L127: =0-SUM(H127:K127) -> 0
B128: 2010-11 | C128: 4.6620619 | D128: 1.9326486 | E128: -9.0175581 | F128: 2.42297 | G128: =0-SUM(C128:F128) -> -0.00012238149 | H128: 76.189 | I128: 31.584 | J128: -147.368 | K128: 39.597 | L128: =0-SUM(H128:K128) -> -0.002
B129: 2011-12 | C129: 3.9066067 | D129: 1.8228926 | E129: -7.6500065 | F129: 1.9206263 | G129: =0-SUM(C129:F129) -> -0.00011904216 | H129: 65.634 | I129: 30.626 | J129: -128.526 | K129: 32.268 | L129: =0-SUM(H129:K129) -> -0.002
B130: 2012-13 | C130: 2.3232184 | D130: 1.1157903 | E130: -7.2681407 | F130: 3.8291319 | G130: =0-SUM(C130:F130) -> 0 | H130: 40.31 | I130: 19.36 | J130: -126.109 | K130: 66.439 | L130: =0-SUM(H130:K130) -> 0
B131: 2013-14 | C131: 2.8140327 | D131: -1.8231037 | E131: -5.4668799 | F131: 4.4759509 | G131: =0-SUM(C131:F131) -> 0 | H131: 50.926 | I131: -32.993 | J131: -98.935 | K131: 81.002 | L131: =0-SUM(H131:K131) -> 0
B132: 2014-15 | C132: 1.5795286 | D132: -1.7105263 | E132: -5.1430459 | F132: 5.2740435 | G132: =0-SUM(C132:F132) -> 0 | H132: 29.891 | I132: -32.37 | J132: -97.327 | K132: 99.806 | L132: =0-SUM(H132:K132) -> 0
B133: 2015-16 | C133: 3.4479812 | D133: -4.0538565 | E133: -4.3319311 | F133: 4.9378064 | G133: =0-SUM(C133:F133) -> 0 | H133: 66.982 | I133: -78.752 | J133: -84.154 | K133: 95.924 | L133: =0-SUM(H133:K133) -> 0
B134: 2016-17 | C134: 0.039370913 | D134: -1.7668128 | E134: -2.9381344 | F134: 4.6655764 | G134: =0-SUM(C134:F134) -> 0 | H134: 0.799 | I134: -35.856 | J134: -59.627 | K134: 94.684 | L134: =0-SUM(H134:K134) -> 0
B135: 2017-18 | C135: -0.043308075 | D135: -1.1392009 | E135: -2.8929889 | F135: 4.0754979 | G135: =0-SUM(C135:F135) -> 0 | H135: -0.916 | I135: -24.095 | J135: -61.189 | K135: 86.2 | L135: =0-SUM(H135:K135) -> 0
B136: 2018-19 | C136: -0.70275477 | D136: -1.8709082 | E136: -1.7837088 | F136: 4.3573718 | G136: =0-SUM(C136:F136) -> 0 | H136: -15.393 | I136: -40.98 | J136: -39.07 | K136: 95.443 | L136: =0-SUM(H136:K136) -> 0
B137: 2019-20 | C137: 0.23689946 | D137: 1.0424019 | E137: -2.9196198 | F137: 1.6400085 | G137: =0-SUM(C137:F137) -> 0.00030996191 | H137: 5.35 | I137: 23.541 | J137: -65.935 | K137: 37.037 | L137: =0-SUM(H137:K137) -> 0.007
... B149: 2031-32 | C149: -1.3398463 | D149: 0.97907246 | E149: -1.8168446 | F149: 2.3505171 | G149: =0-SUM(C149:F149) -> -0.1728987 | H149: -50.938242 | I149: 37.222351 | J149: -69.072749 | K149: 89.361898 | L149: =0-SUM(H149:K149) -> -6.5732581
B150: Notes:
B151: 1The sum of financial balances by sector is equal (but opposite sign) to the residual error between the expenditure and income based estimates of GDP.
B152: Definitions:
B153: Household net lending (ONS Economic Accounts, identifier: RPZT), includes non-profit institutions serving households
B154: Corporate net lending (ONS Economic Accounts, identifier: RPYN+RQBV)
B155: Public sector net lending (ONS Economic Accounts, identifiers: RQBN+RPZD)
B156: Rest of the world net lending (ONS Economic Accounts, identifier: RQCH)

Sheet 1.11
A1: Back to contents
B2: 1.11 Household balance sheet, PNFC balance sheet, and bank lending
C3: Households | P3: Private non-financial companies2 | W3: Lending
C4: Physical assets (£bn) | D4: Financial assets (£bn) | E4: Liabilities (£bn) | F4: Secured liabilities (£bn) | G4: Other liabilities (£bn) | H4: Total net worth (£bn) | I4: Disposable income (£bn) | J4: Assets to income ratio1 (per cent) | K4: Liabilities to income ratio1 (per cent) | L4: Secured liabilities to income ratio1 (per cent) | M4: Other liabilities to income ratio1 (per cent) | N4: Total net worth to income ratio1 (per cent) | P4: Financial assets (£bn) | Q4: UK sterling bank loans (£bn) | R4: Other financial liabilities (£bn) | S4: Profits (non-oil) (£bn) | T4: Financial asset to profits ratio1 (per cent) | U4: Financial liability to profits ratio1 (per cent) | W4: UK bank sterling-denominated lending to firms and households (£bn) | X4: UK bank sterling-denominated lending to firms and households to GDP ratio1 (per cent)
B5: 2012Q1 | C5: 3637.6377 | D5: 5110.205 | E5: 1663.079 | F5: 1233.352 | G5: 429.727 | H5: 7084.7637 | I5: 279.783 | J5: 796.23128 | K5: 151.37395 | L5: 112.26007 | M5: 39.113881 | N5: 644.85733 | P5: 1790.39 | Q5: 347.736 | R5: 4156.157 | S5: 65.069 | T5: 701.38758 | U5: 1764.4059 | W5: 2010.815 | X5: 119.68588
B6: 2012Q2 | C6: 3660.879 | D6: 5353.278 | E6: 1681.399 | F6: 1243.772 | G6: 437.627 | H6: 7332.758 | I6: 283.715 | J6: 811.57003 | K6: 151.3811 | L6: 111.98031 | M6: 39.400796 | N6: 660.18893 | P6: 1819.033 | Q6: 346.201 | R6: 4361.792 | S6: 64.194 | T6: 706.41784 | U6: 1828.3397 | W6: 2027.6 | X6: 119.78248
B7: 2012Q3 | C7: 3684.2688 | D7: 5282.963 | E7: 1685.112 | F7: 1251.342 | G7: 433.77 | H7: 7282.1198 | I7: 282.283 | J7: 801.03763 | K7: 150.53008 | L7: 111.78166 | M7: 38.748423 | N7: 650.50755 | P7: 1824.523 | Q7: 342.876 | R7: 4259.01 | S7: 69.121 | T7: 691.15956 | U7: 1743.2707 | W7: 2027.988 | X7: 118.7414
B8: 2012Q4 | C8: 3707.808 | D8: 5360.16 | E8: 1689.428 | F8: 1253.593 | G8: 435.835 | H8: 7378.54 | I8: 284.236 | J8: 802.46297 | K8: 149.50465 | L8: 110.93576 | M8: 38.568889 | N8: 652.95832 | P8: 1823.977 | Q8: 333.896 | R8: 4295.833 | S8: 70.134 | T8: 679.2755 | U8: 1724.1783 | W8: 2023.324 | X8: 117.51842
B9: 2013Q1 | C9: 3766.6444 | D9: 5382.12 | E9: 1701.24 | F9: 1261.101 | G9: 440.139 | H9: 7447.5244 | I9: 284.363 | J9: 806.34485 | K9: 149.94223 | L9: 111.14969 | M9: 38.79254 | N9: 656.40262 | P9: 1832.033 | Q9: 332.903 | R9: 4244.585 | S9: 73.265 | T9: 662.06733 | U9: 1654.2307 | W9: 2034.143 | X9: 117.23539
B10: 2013Q2 | C10: 3826.4145 | D10: 5158.947 | E10: 1696.857 | F10: 1263.445 | G10: 433.412 | H10: 7288.5045 | I10: 292.198 | J10: 786.06585 | K10: 148.44604 | L10: 110.52988 | M10: 37.916156 | N10: 637.61981 | P10: 1861.106 | Q10: 320.999 | R10: 4099.317 | S10: 66.706 | T10: 666.52317 | U10: 1583.0603 | W10: 2017.856 | X10: 115.17305
B11: 2013Q3 | C11: 3887.133 | D11: 5385.832 | E11: 1711.794 | F11: 1267.687 | G11: 444.107 | H11: 7561.171 | I11: 298.424 | J11: 799.93073 | K11: 147.66761 | L11: 109.3568 | M11: 38.310814 | N11: 652.26311 | P11: 1842.229 | Q11: 318.283 | R11: 4357.771 | S11: 70.143 | T11: 657.3567 | U11: 1668.5414 | W11: 2030.077 | X11: 114.72868
B12: 2013Q4 | C12: 3948.815 | D12: 5434.028 | E12: 1719.956 | F12: 1273.132 | G12: 446.824 | H12: 7662.887 | I12: 300.952 | J12: 797.90354 | K12: 146.2626 | L12: 108.26532 | M12: 37.997274 | N12: 651.64095 | P12: 1878.695 | Q12: 317.509 | R12: 4358.372 | S12: 71.442 | T12: 667.25447 | U12: 1660.7286 | W12: 2037.465 | X12: 113.8839
B13: 2014Q1 | C13: 4033.9369 | D13: 5545.382 | E13: 1724.408 | F13: 1277.313 | G13: 447.095 | H13: 7854.9109 | I13: 302 | J13: 802.57436 | K13: 144.47433 | L13: 107.01582 | M13: 37.458507 | N13: 658.10003 | P13: 1849.722 | Q13: 311.365 | R13: 4422.879 | S13: 73.047 | T13: 657.47322 | U13: 1682.7602 | W13: 2035.773 | X13: 112.4913
B14: 2014Q2 | C14: 4120.8936 | D14: 5714.661 | E14: 1735.118 | F14: 1283.536 | G14: 451.582 | H14: 8100.4366 | I14: 304.571 | J14: 815.58764 | K14: 143.88012 | L14: 106.43386 | M14: 37.446256 | N14: 671.70752 | P14: 1850.169 | Q14: 307.519 | R14: 4516.868 | S14: 77.272 | T14: 633.8279 | U14: 1652.7307 | W14: 2042.637 | X14: 111.57335
B15: 2014Q3 | C15: 4209.7249 | D15: 5921.651 | E15: 1752.255 | F15: 1289.826 | G15: 462.429 | H15: 8379.1209 | I15: 303.742 | J15: 836.42934 | K15: 144.66322 | L15: 106.48586 | M15: 38.17736 | N15: 691.76612 | P15: 1896.321 | Q15: 305.844 | R15: 4687.37 | S15: 84.222 | T15: 619.74718 | U15: 1631.8599 | W15: 2058.099 | X15: 110.99978
B16: 2014Q4 | C16: 4300.471 | D16: 6029.698 | E16: 1769.308 | F16: 1295.12 | G16: 474.188 | H16: 8560.861 | I16: 307.578 | J16: 848.20144 | K16: 145.27638 | L16: 106.34121 | M16: 38.935176 | N16: 702.92506 | P16: 1875.354 | Q16: 296.426 | R16: 4735.252 | S16: 80.559 | T16: 595.16154 | U16: 1596.8512 | W16: 2065.734 | X16: 110.1686
... B85: 2032Q1 | C85: 8058.1869 | D85: 7396.8639 | E85: 2764.7648 | F85: 2058.565 | G85: 706.19975 | H85: 12690.286 | I85: 588.19285 | J85: 663.72839 | K85: 118.73483 | L85: 88.406572 | M85: 30.328261 | N85: 544.99356 | P85: 3356.2682 | Q85: 463.14192 | R85: 6740.5028 | S85: 166.34066 | T85: 511.42372 | U85: 1097.6819 | W85: 3227.9067 | X85: 84.904754
B86: 2012 | C86: =OFFSET(C$8,4*(ROW()-ROW(C$86)),0) -> 3707.808 | D86: =OFFSET(D$8,4*(ROW()-ROW(D$86)),0) -> 5360.16 | E86: =OFFSET(E$8,4*(ROW()-ROW(E$86)),0) -> 1689.428 | F86: =OFFSET(F$8,4*(ROW()-ROW(F$86)),0) -> 1253.593 | G86: =OFFSET(G$8,4*(ROW()-ROW(G$86)),0) -> 435.835 | H86: =OFFSET(H$8,4*(ROW()-ROW(H$86)),0) -> 7378.54 | I86: ='1.12'!I85 -> 1130.017 | J86: =OFFSET(J$8,4*(ROW()-ROW(J$86)),0) -> 802.46297 | K86: =OFFSET(K$8,4*(ROW()-ROW(K$86)),0) -> 149.50465 | L86: =OFFSET(L$8,4*(ROW()-ROW(L$86)),0) -> 110.93576 | M86: =OFFSET(M$8,4*(ROW()-ROW(M$86)),0) -> 38.568889 | N86: =OFFSET(N$8,4*(ROW()-ROW(N$86)),0) -> 652.95832 | P86: =OFFSET(P$8,4*(ROW()-ROW(P$86)),0) -> 1823.977 | Q86: =OFFSET(Q$8,4*(ROW()-ROW(Q$86)),0) -> 333.896 | R86: =OFFSET(R$8,4*(ROW()-ROW(R$86)),0) -> 4295.833 | S86: ='1.3'!D105 -> 268.518 | T86: =OFFSET(T$8,4*(ROW()-ROW(T$86)),0) -> 679.2755 | U86: =OFFSET(U$8,4*(ROW()-ROW(U$86)),0) -> 1724.1783 | W86: =OFFSET(W$8,4*(ROW()-ROW(W$86)),0) -> 2023.324 | X86: =OFFSET(X$8,4*(ROW()-ROW(X$86)),0) -> 117.51842
B87: 2013 | C87: =OFFSET(C$8,4*(ROW()-ROW(C$86)),0) -> 3948.815 | D87: =OFFSET(D$8,4*(ROW()-ROW(D$86)),0) -> 5434.028 | E87: =OFFSET(E$8,4*(ROW()-ROW(E$86)),0) -> 1719.956 | F87: =OFFSET(F$8,4*(ROW()-ROW(F$86)),0) -> 1273.132 | G87: =OFFSET(G$8,4*(ROW()-ROW(G$86)),0) -> 446.824 | H87: =OFFSET(H$8,4*(ROW()-ROW(H$86)),0) -> 7662.887 | I87: ='1.12'!I86 -> 1175.937 | J87: =OFFSET(J$8,4*(ROW()-ROW(J$86)),0) -> 797.90354 | K87: =OFFSET(K$8,4*(ROW()-ROW(K$86)),0) -> 146.2626 | L87: =OFFSET(L$8,4*(ROW()-ROW(L$86)),0) -> 108.26532 | M87: =OFFSET(M$8,4*(ROW()-ROW(M$86)),0) -> 37.997274 | N87: =OFFSET(N$8,4*(ROW()-ROW(N$86)),0) -> 651.64095 | P87: =OFFSET(P$8,4*(ROW()-ROW(P$86)),0) -> 1878.695 | Q87: =OFFSET(Q$8,4*(ROW()-ROW(Q$86)),0) -> 317.509 | R87: =OFFSET(R$8,4*(ROW()-ROW(R$86)),0) -> 4358.372 | S87: ='1.3'!D106 -> 281.556 | T87: =OFFSET(T$8,4*(ROW()-ROW(T$86)),0) -> 667.25447 | U87: =OFFSET(U$8,4*(ROW()-ROW(U$86)),0) -> 1660.7286 | W87: =OFFSET(W$8,4*(ROW()-ROW(W$86)),0) -> 2037.465 | X87: =OFFSET(X$8,4*(ROW()-ROW(X$86)),0) -> 113.8839
B88: 2014 | C88: =OFFSET(C$8,4*(ROW()-ROW(C$86)),0) -> 4300.471 | D88: =OFFSET(D$8,4*(ROW()-ROW(D$86)),0) -> 6029.698 | E88: =OFFSET(E$8,4*(ROW()-ROW(E$86)),0) -> 1769.308 | F88: =OFFSET(F$8,4*(ROW()-ROW(F$86)),0) -> 1295.12 | G88: =OFFSET(G$8,4*(ROW()-ROW(G$86)),0) -> 474.188 | H88: =OFFSET(H$8,4*(ROW()-ROW(H$86)),0) -> 8560.861 | I88: ='1.12'!I87 -> 1217.891 | J88: =OFFSET(J$8,4*(ROW()-ROW(J$86)),0) -> 848.20144 | K88: =OFFSET(K$8,4*(ROW()-ROW(K$86)),0) -> 145.27638 | L88: =OFFSET(L$8,4*(ROW()-ROW(L$86)),0) -> 106.34121 | M88: =OFFSET(M$8,4*(ROW()-ROW(M$86)),0) -> 38.935176 | N88: =OFFSET(N$8,4*(ROW()-ROW(N$86)),0) -> 702.92506 | P88: =OFFSET(P$8,4*(ROW()-ROW(P$86)),0) -> 1875.354 | Q88: =OFFSET(Q$8,4*(ROW()-ROW(Q$86)),0) -> 296.426 | R88: =OFFSET(R$8,4*(ROW()-ROW(R$86)),0) -> 4735.252 | S88: ='1.3'!D107 -> 315.1 | T88: =OFFSET(T$8,4*(ROW()-ROW(T$86)),0) -> 595.16154 | U88: =OFFSET(U$8,4*(ROW()-ROW(U$86)),0) -> 1596.8512 | W88: =OFFSET(W$8,4*(ROW()-ROW(W$86)),0) -> 2065.734 | X88: =OFFSET(X$8,4*(ROW()-ROW(X$86)),0) -> 110.1686
B89: 2015 | C89: =OFFSET(C$8,4*(ROW()-ROW(C$86)),0) -> 4677.22 | D89: =OFFSET(D$8,4*(ROW()-ROW(D$86)),0) -> 6125.909 | E89: =OFFSET(E$8,4*(ROW()-ROW(E$86)),0) -> 1814.652 | F89: =OFFSET(F$8,4*(ROW()-ROW(F$86)),0) -> 1321.163 | G89: =OFFSET(G$8,4*(ROW()-ROW(G$86)),0) -> 493.489 | H89: =OFFSET(H$8,4*(ROW()-ROW(H$86)),0) -> 8988.477 | I89: ='1.12'!I88 -> 1287.116 | J89: =OFFSET(J$8,4*(ROW()-ROW(J$86)),0) -> 839.32831 | K89: =OFFSET(K$8,4*(ROW()-ROW(K$86)),0) -> 140.98589 | L89: =OFFSET(L$8,4*(ROW()-ROW(L$86)),0) -> 102.64522 | M89: =OFFSET(M$8,4*(ROW()-ROW(M$86)),0) -> 38.340678 | N89: =OFFSET(N$8,4*(ROW()-ROW(N$86)),0) -> 698.34242 | P89: =OFFSET(P$8,4*(ROW()-ROW(P$86)),0) -> 1943.953 | Q89: =OFFSET(Q$8,4*(ROW()-ROW(Q$86)),0) -> 290.508 | R89: =OFFSET(R$8,4*(ROW()-ROW(R$86)),0) -> 4705.154 | S89: ='1.3'!D108 -> 325.7 | T89: =OFFSET(T$8,4*(ROW()-ROW(T$86)),0) -> 596.85385 | U89: =OFFSET(U$8,4*(ROW()-ROW(U$86)),0) -> 1533.8232 | W89: =OFFSET(W$8,4*(ROW()-ROW(W$86)),0) -> 2105.16 | X89: =OFFSET(X$8,4*(ROW()-ROW(X$86)),0) -> 109.18789
B90: 2016 | C90: =OFFSET(C$8,4*(ROW()-ROW(C$86)),0) -> 4957.224 | D90: =OFFSET(D$8,4*(ROW()-ROW(D$86)),0) -> 6681.231 | E90: =OFFSET(E$8,4*(ROW()-ROW(E$86)),0) -> 1883.063 | F90: =OFFSET(F$8,4*(ROW()-ROW(F$86)),0) -> 1361.571 | G90: =OFFSET(G$8,4*(ROW()-ROW(G$86)),0) -> 521.492 | H90: =OFFSET(H$8,4*(ROW()-ROW(H$86)),0) -> 9755.392 | I90: ='1.12'!I89 -> 1312.733 | J90: =OFFSET(J$8,4*(ROW()-ROW(J$86)),0) -> 886.58204 | K90: =OFFSET(K$8,4*(ROW()-ROW(K$86)),0) -> 143.446 | L90: =OFFSET(L$8,4*(ROW()-ROW(L$86)),0) -> 103.72033 | M90: =OFFSET(M$8,4*(ROW()-ROW(M$86)),0) -> 39.725672 | N90: =OFFSET(N$8,4*(ROW()-ROW(N$86)),0) -> 743.13604 | P90: =OFFSET(P$8,4*(ROW()-ROW(P$86)),0) -> 2215.132 | Q90: =OFFSET(Q$8,4*(ROW()-ROW(Q$86)),0) -> 295.489 | R90: =OFFSET(R$8,4*(ROW()-ROW(R$86)),0) -> 5176.955 | S90: ='1.3'!D109 -> 337.323 | T90: =OFFSET(T$8,4*(ROW()-ROW(T$86)),0) -> 656.6798 | U90: =OFFSET(U$8,4*(ROW()-ROW(U$86)),0) -> 1622.3157 | W90: =OFFSET(W$8,4*(ROW()-ROW(W$86)),0) -> 2178.552 | X90: =OFFSET(X$8,4*(ROW()-ROW(X$86)),0) -> 108.66924
B91: 2017 | C91: =OFFSET(C$8,4*(ROW()-ROW(C$86)),0) -> 5205.669 | D91: =OFFSET(D$8,4*(ROW()-ROW(D$86)),0) -> 6901.023 | E91: =OFFSET(E$8,4*(ROW()-ROW(E$86)),0) -> 1937.05 | F91: =OFFSET(F$8,4*(ROW()-ROW(F$86)),0) -> 1397.217 | G91: =OFFSET(G$8,4*(ROW()-ROW(G$86)),0) -> 539.833 | H91: =OFFSET(H$8,4*(ROW()-ROW(H$86)),0) -> 10169.642 | I91: ='1.12'!I90 -> 1348.375 | J91: =OFFSET(J$8,4*(ROW()-ROW(J$86)),0) -> 897.87277 | K91: =OFFSET(K$8,4*(ROW()-ROW(K$86)),0) -> 143.65811 | L91: =OFFSET(L$8,4*(ROW()-ROW(L$86)),0) -> 103.62229 | M91: =OFFSET(M$8,4*(ROW()-ROW(M$86)),0) -> 40.035821 | N91: =OFFSET(N$8,4*(ROW()-ROW(N$86)),0) -> 754.21467 | P91: =OFFSET(P$8,4*(ROW()-ROW(P$86)),0) -> 2392.944 | Q91: =OFFSET(Q$8,4*(ROW()-ROW(Q$86)),0) -> 325.506 | R91: =OFFSET(R$8,4*(ROW()-ROW(R$86)),0) -> 5500.49 | S91: ='1.3'!D110 -> 354.319 | T91: =OFFSET(T$8,4*(ROW()-ROW(T$86)),0) -> 675.36429 | U91: =OFFSET(U$8,4*(ROW()-ROW(U$86)),0) -> 1644.2799 | W91: =OFFSET(W$8,4*(ROW()-ROW(W$86)),0) -> 2262.556 | X91: =OFFSET(X$8,4*(ROW()-ROW(X$86)),0) -> 107.88348
B92: 2018 | C92: =OFFSET(C$8,4*(ROW()-ROW(C$86)),0) -> 5335.372 | D92: =OFFSET(D$8,4*(ROW()-ROW(D$86)),0) -> 6668.942 | E92: =OFFSET(E$8,4*(ROW()-ROW(E$86)),0) -> 1974.772 | F92: =OFFSET(F$8,4*(ROW()-ROW(F$86)),0) -> 1425.835 | G92: =OFFSET(G$8,4*(ROW()-ROW(G$86)),0) -> 548.937 | H92: =OFFSET(H$8,4*(ROW()-ROW(H$86)),0) -> 10029.542 | I92: ='1.12'!I91 -> 1402.614 | J92: =OFFSET(J$8,4*(ROW()-ROW(J$86)),0) -> 855.853 | K92: =OFFSET(K$8,4*(ROW()-ROW(K$86)),0) -> 140.79226 | L92: =OFFSET(L$8,4*(ROW()-ROW(L$86)),0) -> 101.65555 | M92: =OFFSET(M$8,4*(ROW()-ROW(M$86)),0) -> 39.136712 | N92: =OFFSET(N$8,4*(ROW()-ROW(N$86)),0) -> 715.06074 | P92: =OFFSET(P$8,4*(ROW()-ROW(P$86)),0) -> 2412.254 | Q92: =OFFSET(Q$8,4*(ROW()-ROW(Q$86)),0) -> 341.716 | R92: =OFFSET(R$8,4*(ROW()-ROW(R$86)),0) -> 5047.431 | S92: ='1.3'!D111 -> 367.031 | T92: =OFFSET(T$8,4*(ROW()-ROW(T$86)),0) -> 657.2344 | U92: =OFFSET(U$8,4*(ROW()-ROW(U$86)),0) -> 1468.3084 | W92: =OFFSET(W$8,4*(ROW()-ROW(W$86)),0) -> 2316.488 | X92: =OFFSET(X$8,4*(ROW()-ROW(X$86)),0) -> 106.67396
B93: 2019 | C93: =OFFSET(C$8,4*(ROW()-ROW(C$86)),0) -> 5437.755 | D93: =OFFSET(D$8,4*(ROW()-ROW(D$86)),0) -> 7112.659 | E93: =OFFSET(E$8,4*(ROW()-ROW(E$86)),0) -> 2009.214 | F93: =OFFSET(F$8,4*(ROW()-ROW(F$86)),0) -> 1452.554 | G93: =OFFSET(G$8,4*(ROW()-ROW(G$86)),0) -> 556.66 | H93: =OFFSET(H$8,4*(ROW()-ROW(H$86)),0) -> 10541.2 | I93: ='1.12'!I92 -> 1456.54 | J93: =OFFSET(J$8,4*(ROW()-ROW(J$86)),0) -> 861.65941 | K93: =OFFSET(K$8,4*(ROW()-ROW(K$86)),0) -> 137.94431 | L93: =OFFSET(L$8,4*(ROW()-ROW(L$86)),0) -> 99.726338 | M93: =OFFSET(M$8,4*(ROW()-ROW(M$86)),0) -> 38.217969 | N93: =OFFSET(N$8,4*(ROW()-ROW(N$86)),0) -> 723.71511 | P93: =OFFSET(P$8,4*(ROW()-ROW(P$86)),0) -> 2572.968 | Q93: =OFFSET(Q$8,4*(ROW()-ROW(Q$86)),0) -> 352.136 | R93: =OFFSET(R$8,4*(ROW()-ROW(R$86)),0) -> 5297.292 | S93: ='1.3'!D112 -> 377.657 | T93: =OFFSET(T$8,4*(ROW()-ROW(T$86)),0) -> 681.29758 | U93: =OFFSET(U$8,4*(ROW()-ROW(U$86)),0) -> 1495.9151 | W93: =OFFSET(W$8,4*(ROW()-ROW(W$86)),0) -> 2361.35 | X93: =OFFSET(X$8,4*(ROW()-ROW(X$86)),0) -> 104.81096
B94: 2020 | C94: =OFFSET(C$8,4*(ROW()-ROW(C$86)),0) -> 5814.453 | D94: =OFFSET(D$8,4*(ROW()-ROW(D$86)),0) -> 7563.144 | E94: =OFFSET(E$8,4*(ROW()-ROW(E$86)),0) -> 2067.665 | F94: =OFFSET(F$8,4*(ROW()-ROW(F$86)),0) -> 1499.76 | G94: =OFFSET(G$8,4*(ROW()-ROW(G$86)),0) -> 567.905 | H94: =OFFSET(H$8,4*(ROW()-ROW(H$86)),0) -> 11309.932 | I94: ='1.12'!I93 -> 1454.341 | J94: =OFFSET(J$8,4*(ROW()-ROW(J$86)),0) -> 919.83909 | K94: =OFFSET(K$8,4*(ROW()-ROW(K$86)),0) -> 142.17195 | L94: =OFFSET(L$8,4*(ROW()-ROW(L$86)),0) -> 103.123 | M94: =OFFSET(M$8,4*(ROW()-ROW(M$86)),0) -> 39.048958 | N94: =OFFSET(N$8,4*(ROW()-ROW(N$86)),0) -> 777.66714 | P94: =OFFSET(P$8,4*(ROW()-ROW(P$86)),0) -> 2832.037 | Q94: =OFFSET(Q$8,4*(ROW()-ROW(Q$86)),0) -> 391.735 | R94: =OFFSET(R$8,4*(ROW()-ROW(R$86)),0) -> 5647.905 | S94: ='1.3'!D113 -> 381.545 | T94: =OFFSET(T$8,4*(ROW()-ROW(T$86)),0) -> 742.25504 | U94: =OFFSET(U$8,4*(ROW()-ROW(U$86)),0) -> 1582.943 | W94: =OFFSET(W$8,4*(ROW()-ROW(W$86)),0) -> 2459.4 | X94: =OFFSET(X$8,4*(ROW()-ROW(X$86)),0) -> 115.75172
B95: 2021 | C95: =OFFSET(C$8,4*(ROW()-ROW(C$86)),0) -> 6190.709 | D95: =OFFSET(D$8,4*(ROW()-ROW(D$86)),0) -> 7661.863 | E95: =OFFSET(E$8,4*(ROW()-ROW(E$86)),0) -> 2095.29 | F95: =OFFSET(F$8,4*(ROW()-ROW(F$86)),0) -> 1562.357 | G95: =OFFSET(G$8,4*(ROW()-ROW(G$86)),0) -> 532.933 | H95: =OFFSET(H$8,4*(ROW()-ROW(H$86)),0) -> 11757.282 | I95: ='1.12'!I94 -> 1519.777 | J95: =OFFSET(J$8,4*(ROW()-ROW(J$86)),0) -> 911.48715 | K95: =OFFSET(K$8,4*(ROW()-ROW(K$86)),0) -> 137.86825 | L95: =OFFSET(L$8,4*(ROW()-ROW(L$86)),0) -> 102.80173 | M95: =OFFSET(M$8,4*(ROW()-ROW(M$86)),0) -> 35.066526 | N95: =OFFSET(N$8,4*(ROW()-ROW(N$86)),0) -> 773.61889 | P95: =OFFSET(P$8,4*(ROW()-ROW(P$86)),0) -> 2879.937 | Q95: =OFFSET(Q$8,4*(ROW()-ROW(Q$86)),0) -> 392.041 | R95: =OFFSET(R$8,4*(ROW()-ROW(R$86)),0) -> 5971.069 | S95: ='1.3'!D114 -> 409.678 | T95: =OFFSET(T$8,4*(ROW()-ROW(T$86)),0) -> 702.97575 | U95: =OFFSET(U$8,4*(ROW()-ROW(U$86)),0) -> 1553.1979 | W95: =OFFSET(W$8,4*(ROW()-ROW(W$86)),0) -> 2487.331 | X95: =OFFSET(X$8,4*(ROW()-ROW(X$86)),0) -> 107.09013
B96: 2022 | C96: =OFFSET(C$8,4*(ROW()-ROW(C$86)),0) -> 6644.016 | D96: =OFFSET(D$8,4*(ROW()-ROW(D$86)),0) -> 6580.608 | E96: =OFFSET(E$8,4*(ROW()-ROW(E$86)),0) -> 2189.901 | F96: =OFFSET(F$8,4*(ROW()-ROW(F$86)),0) -> 1619.611 | G96: =OFFSET(G$8,4*(ROW()-ROW(G$86)),0) -> 570.29 | H96: =OFFSET(H$8,4*(ROW()-ROW(H$86)),0) -> 11034.723 | I96: ='1.12'!I95 -> 1613.529 | J96: =OFFSET(J$8,4*(ROW()-ROW(J$86)),0) -> 819.6087 | K96: =OFFSET(K$8,4*(ROW()-ROW(K$86)),0) -> 135.7212 | L96: =OFFSET(L$8,4*(ROW()-ROW(L$86)),0) -> 100.37694 | M96: =OFFSET(M$8,4*(ROW()-ROW(M$86)),0) -> 35.344267 | N96: =OFFSET(N$8,4*(ROW()-ROW(N$86)),0) -> 683.88749 | P96: =OFFSET(P$8,4*(ROW()-ROW(P$86)),0) -> 3096.159 | Q96: =OFFSET(Q$8,4*(ROW()-ROW(Q$86)),0) -> 395.537 | R96: =OFFSET(R$8,4*(ROW()-ROW(R$86)),0) -> 5570.069 | S96: ='1.3'!D115 -> 441.762 | T96: =OFFSET(T$8,4*(ROW()-ROW(T$86)),0) -> 700.86585 | U96: =OFFSET(U$8,4*(ROW()-ROW(U$86)),0) -> 1350.4118 | W96: =OFFSET(W$8,4*(ROW()-ROW(W$86)),0) -> 2585.438 | X96: =OFFSET(X$8,4*(ROW()-ROW(X$86)),0) -> 100.17393
B97: 2023 | C97: =OFFSET(C$8,4*(ROW()-ROW(C$86)),0) -> 6466.827 | D97: =OFFSET(D$8,4*(ROW()-ROW(D$86)),0) -> 6582.159 | E97: =OFFSET(E$8,4*(ROW()-ROW(E$86)),0) -> 2239.942 | F97: =OFFSET(F$8,4*(ROW()-ROW(F$86)),0) -> 1619.94 | G97: =OFFSET(G$8,4*(ROW()-ROW(G$86)),0) -> 620.002 | H97: =OFFSET(H$8,4*(ROW()-ROW(H$86)),0) -> 10809.044 | I97: ='1.12'!I96 -> 1740.15 | J97: =OFFSET(J$8,4*(ROW()-ROW(J$86)),0) -> 749.87708 | K97: =OFFSET(K$8,4*(ROW()-ROW(K$86)),0) -> 128.7212 | L97: =OFFSET(L$8,4*(ROW()-ROW(L$86)),0) -> 93.091975 | M97: =OFFSET(M$8,4*(ROW()-ROW(M$86)),0) -> 35.629227 | N97: =OFFSET(N$8,4*(ROW()-ROW(N$86)),0) -> 621.15588 | P97: =OFFSET(P$8,4*(ROW()-ROW(P$86)),0) -> 2980.66 | Q97: =OFFSET(Q$8,4*(ROW()-ROW(Q$86)),0) -> 391.155 | R97: =OFFSET(R$8,4*(ROW()-ROW(R$86)),0) -> 5489.296 | S97: ='1.3'!D116 -> 483.21 | T97: =OFFSET(T$8,4*(ROW()-ROW(T$86)),0) -> 616.84568 | U97: =OFFSET(U$8,4*(ROW()-ROW(U$86)),0) -> 1216.9556 | W97: =OFFSET(W$8,4*(ROW()-ROW(W$86)),0) -> 2631.097 | X97: =OFFSET(X$8,4*(ROW()-ROW(X$86)),0) -> 95.601025
... B105: 2031 | C105: =OFFSET(C$8,4*(ROW()-ROW(C$86)),0) -> 8001.2913 | D105: =OFFSET(D$8,4*(ROW()-ROW(D$86)),0) -> 7390.3139 | E105: =OFFSET(E$8,4*(ROW()-ROW(E$86)),0) -> 2739.4431 | F105: =OFFSET(F$8,4*(ROW()-ROW(F$86)),0) -> 2039.6187 | G105: =OFFSET(G$8,4*(ROW()-ROW(G$86)),0) -> 699.8244 | H105: =OFFSET(H$8,4*(ROW()-ROW(H$86)),0) -> 12652.162 | I105: ='1.12'!I104 -> 2312.5576 | J105: =OFFSET(J$8,4*(ROW()-ROW(J$86)),0) -> 665.56634 | K105: =OFFSET(K$8,4*(ROW()-ROW(K$86)),0) -> 118.45945 | L105: =OFFSET(L$8,4*(ROW()-ROW(L$86)),0) -> 88.197529 | M105: =OFFSET(M$8,4*(ROW()-ROW(M$86)),0) -> 30.261923 | N105: =OFFSET(N$8,4*(ROW()-ROW(N$86)),0) -> 547.10689 | P105: =OFFSET(P$8,4*(ROW()-ROW(P$86)),0) -> 3334.714 | Q105: =OFFSET(Q$8,4*(ROW()-ROW(Q$86)),0) -> 462.96824 | R105: =OFFSET(R$8,4*(ROW()-ROW(R$86)),0) -> 6698.637 | S105: ='1.3'!D124 -> 650.13631 | T105: =OFFSET(T$8,4*(ROW()-ROW(T$86)),0) -> 512.92536 | U105: =OFFSET(U$8,4*(ROW()-ROW(U$86)),0) -> 1101.5544 | W105: =OFFSET(W$8,4*(ROW()-ROW(W$86)),0) -> 3202.4113 | X105: =OFFSET(X$8,4*(ROW()-ROW(X$86)),0) -> 84.94223
B106: 2012-13 | C106: =OFFSET(C$9,4*(ROW()-ROW(C$106)),0) -> 3766.6444 | D106: =OFFSET(D$9,4*(ROW()-ROW(D$106)),0) -> 5382.12 | E106: =OFFSET(E$9,4*(ROW()-ROW(E$106)),0) -> 1701.24 | F106: =OFFSET(F$9,4*(ROW()-ROW(F$106)),0) -> 1261.101 | G106: =OFFSET(G$9,4*(ROW()-ROW(G$106)),0) -> 440.139 | H106: =OFFSET(H$9,4*(ROW()-ROW(H$106)),0) -> 7447.5244 | I106: ='1.12'!I105 -> 1134.597 | J106: =OFFSET(J$9,4*(ROW()-ROW(J$106)),0) -> 806.34485 | K106: =OFFSET(K$9,4*(ROW()-ROW(K$106)),0) -> 149.94223 | L106: =OFFSET(L$9,4*(ROW()-ROW(L$106)),0) -> 111.14969 | M106: =OFFSET(M$9,4*(ROW()-ROW(M$106)),0) -> 38.79254 | N106: =OFFSET(N$9,4*(ROW()-ROW(N$106)),0) -> 656.40262 | P106: =OFFSET(P$9,4*(ROW()-ROW(P$106)),0) -> 1832.033 | Q106: =OFFSET(Q$9,4*(ROW()-ROW(Q$106)),0) -> 332.903 | R106: =OFFSET(R$9,4*(ROW()-ROW(R$106)),0) -> 4244.585 | S106: ='1.3'!D129 -> 276.714 | T106: =OFFSET(T$9,4*(ROW()-ROW(T$106)),0) -> 662.06733 | U106: =OFFSET(U$9,4*(ROW()-ROW(U$106)),0) -> 1654.2307 | W106: =OFFSET(W$9,4*(ROW()-ROW(W$106)),0) -> 2034.143 | X106: =OFFSET(X$9,4*(ROW()-ROW(X$106)),0) -> 117.23539
B107: 2013-14 | C107: =OFFSET(C$9,4*(ROW()-ROW(C$106)),0) -> 4033.9369 | D107: =OFFSET(D$9,4*(ROW()-ROW(D$106)),0) -> 5545.382 | E107: =OFFSET(E$9,4*(ROW()-ROW(E$106)),0) -> 1724.408 | F107: =OFFSET(F$9,4*(ROW()-ROW(F$106)),0) -> 1277.313 | G107: =OFFSET(G$9,4*(ROW()-ROW(G$106)),0) -> 447.095 | H107: =OFFSET(H$9,4*(ROW()-ROW(H$106)),0) -> 7854.9109 | I107: ='1.12'!I106 -> 1193.574 | J107: =OFFSET(J$9,4*(ROW()-ROW(J$106)),0) -> 802.57436 | K107: =OFFSET(K$9,4*(ROW()-ROW(K$106)),0) -> 144.47433 | L107: =OFFSET(L$9,4*(ROW()-ROW(L$106)),0) -> 107.01582 | M107: =OFFSET(M$9,4*(ROW()-ROW(M$106)),0) -> 37.458507 | N107: =OFFSET(N$9,4*(ROW()-ROW(N$106)),0) -> 658.10003 | P107: =OFFSET(P$9,4*(ROW()-ROW(P$106)),0) -> 1849.722 | Q107: =OFFSET(Q$9,4*(ROW()-ROW(Q$106)),0) -> 311.365 | R107: =OFFSET(R$9,4*(ROW()-ROW(R$106)),0) -> 4422.879 | S107: ='1.3'!D130 -> 281.338 | T107: =OFFSET(T$9,4*(ROW()-ROW(T$106)),0) -> 657.47322 | U107: =OFFSET(U$9,4*(ROW()-ROW(U$106)),0) -> 1682.7602 | W107: =OFFSET(W$9,4*(ROW()-ROW(W$106)),0) -> 2035.773 | X107: =OFFSET(X$9,4*(ROW()-ROW(X$106)),0) -> 112.4913
B108: 2014-15 | C108: =OFFSET(C$9,4*(ROW()-ROW(C$106)),0) -> 4391.7132 | D108: =OFFSET(D$9,4*(ROW()-ROW(D$106)),0) -> 6049.202 | E108: =OFFSET(E$9,4*(ROW()-ROW(E$106)),0) -> 1774.037 | F108: =OFFSET(F$9,4*(ROW()-ROW(F$106)),0) -> 1299.824 | G108: =OFFSET(G$9,4*(ROW()-ROW(G$106)),0) -> 474.213 | H108: =OFFSET(H$9,4*(ROW()-ROW(H$106)),0) -> 8666.8782 | I108: ='1.12'!I107 -> 1228.019 | J108: =OFFSET(J$9,4*(ROW()-ROW(J$106)),0) -> 850.22424 | K108: =OFFSET(K$9,4*(ROW()-ROW(K$106)),0) -> 144.46332 | L108: =OFFSET(L$9,4*(ROW()-ROW(L$106)),0) -> 105.84722 | M108: =OFFSET(M$9,4*(ROW()-ROW(M$106)),0) -> 38.616096 | N108: =OFFSET(N$9,4*(ROW()-ROW(N$106)),0) -> 705.76092 | P108: =OFFSET(P$9,4*(ROW()-ROW(P$106)),0) -> 1990.391 | Q108: =OFFSET(Q$9,4*(ROW()-ROW(Q$106)),0) -> 299.593 | R108: =OFFSET(R$9,4*(ROW()-ROW(R$106)),0) -> 4721.546 | S108: ='1.3'!D131 -> 324.665 | T108: =OFFSET(T$9,4*(ROW()-ROW(T$106)),0) -> 613.05992 | U108: =OFFSET(U$9,4*(ROW()-ROW(U$106)),0) -> 1546.56 | W108: =OFFSET(W$9,4*(ROW()-ROW(W$106)),0) -> 2073.63 | X108: =OFFSET(X$9,4*(ROW()-ROW(X$106)),0) -> 109.57673
B109: 2015-16 | C109: =OFFSET(C$9,4*(ROW()-ROW(C$106)),0) -> 4745.7022 | D109: =OFFSET(D$9,4*(ROW()-ROW(D$106)),0) -> 6502.155 | E109: =OFFSET(E$9,4*(ROW()-ROW(E$106)),0) -> 1844.997 | F109: =OFFSET(F$9,4*(ROW()-ROW(F$106)),0) -> 1330.854 | G109: =OFFSET(G$9,4*(ROW()-ROW(G$106)),0) -> 514.143 | H109: =OFFSET(H$9,4*(ROW()-ROW(H$106)),0) -> 9402.8602 | I109: ='1.12'!I108 -> 1301.656 | J109: =OFFSET(J$9,4*(ROW()-ROW(J$106)),0) -> 864.11903 | K109: =OFFSET(K$9,4*(ROW()-ROW(K$106)),0) -> 141.74229 | L109: =OFFSET(L$9,4*(ROW()-ROW(L$106)),0) -> 102.24314 | M109: =OFFSET(M$9,4*(ROW()-ROW(M$106)),0) -> 39.499146 | N109: =OFFSET(N$9,4*(ROW()-ROW(N$106)),0) -> 722.37674 | P109: =OFFSET(P$9,4*(ROW()-ROW(P$106)),0) -> 1996.568 | Q109: =OFFSET(Q$9,4*(ROW()-ROW(Q$106)),0) -> 297.582 | R109: =OFFSET(R$9,4*(ROW()-ROW(R$106)),0) -> 4992.518 | S109: ='1.3'!D132 -> 325.931 | T109: =OFFSET(T$9,4*(ROW()-ROW(T$106)),0) -> 612.57383 | U109: =OFFSET(U$9,4*(ROW()-ROW(U$106)),0) -> 1623.0736 | W109: =OFFSET(W$9,4*(ROW()-ROW(W$106)),0) -> 2142.579 | X109: =OFFSET(X$9,4*(ROW()-ROW(X$106)),0) -> 110.2919
B110: 2016-17 | C110: =OFFSET(C$9,4*(ROW()-ROW(C$106)),0) -> 5018.2009 | D110: =OFFSET(D$9,4*(ROW()-ROW(D$106)),0) -> 6938.239 | E110: =OFFSET(E$9,4*(ROW()-ROW(E$106)),0) -> 1915.342 | F110: =OFFSET(F$9,4*(ROW()-ROW(F$106)),0) -> 1374.595 | G110: =OFFSET(G$9,4*(ROW()-ROW(G$106)),0) -> 540.747 | H110: =OFFSET(H$9,4*(ROW()-ROW(H$106)),0) -> 10041.098 | I110: ='1.12'!I109 -> 1314.003 | J110: =OFFSET(J$9,4*(ROW()-ROW(J$106)),0) -> 909.92486 | K110: =OFFSET(K$9,4*(ROW()-ROW(K$106)),0) -> 145.7639 | L110: =OFFSET(L$9,4*(ROW()-ROW(L$106)),0) -> 104.61125 | M110: =OFFSET(M$9,4*(ROW()-ROW(M$106)),0) -> 41.152646 | N110: =OFFSET(N$9,4*(ROW()-ROW(N$106)),0) -> 764.16096 | P110: =OFFSET(P$9,4*(ROW()-ROW(P$106)),0) -> 2281.071 | Q110: =OFFSET(Q$9,4*(ROW()-ROW(Q$106)),0) -> 302.462 | R110: =OFFSET(R$9,4*(ROW()-ROW(R$106)),0) -> 5429.312 | S110: ='1.3'!D133 -> 341.806 | T110: =OFFSET(T$9,4*(ROW()-ROW(T$106)),0) -> 667.35838 | U110: =OFFSET(U$9,4*(ROW()-ROW(U$106)),0) -> 1676.9085 | W110: =OFFSET(W$9,4*(ROW()-ROW(W$106)),0) -> 2217.804 | X110: =OFFSET(X$9,4*(ROW()-ROW(X$106)),0) -> 109.28281
B111: 2017-18 | C111: =OFFSET(C$9,4*(ROW()-ROW(C$106)),0) -> 5237.7961 | D111: =OFFSET(D$9,4*(ROW()-ROW(D$106)),0) -> 6705.828 | E111: =OFFSET(E$9,4*(ROW()-ROW(E$106)),0) -> 1939.564 | F111: =OFFSET(F$9,4*(ROW()-ROW(F$106)),0) -> 1400.165 | G111: =OFFSET(G$9,4*(ROW()-ROW(G$106)),0) -> 539.399 | H111: =OFFSET(H$9,4*(ROW()-ROW(H$106)),0) -> 10004.06 | I111: ='1.12'!I110 -> 1368.604 | J111: =OFFSET(J$9,4*(ROW()-ROW(J$106)),0) -> 872.68663 | K111: =OFFSET(K$9,4*(ROW()-ROW(K$106)),0) -> 141.71842 | L111: =OFFSET(L$9,4*(ROW()-ROW(L$106)),0) -> 102.30607 | M111: =OFFSET(M$9,4*(ROW()-ROW(M$106)),0) -> 39.41235 | N111: =OFFSET(N$9,4*(ROW()-ROW(N$106)),0) -> 730.96821 | P111: =OFFSET(P$9,4*(ROW()-ROW(P$106)),0) -> 2354.049 | Q111: =OFFSET(Q$9,4*(ROW()-ROW(Q$106)),0) -> 329.314 | R111: =OFFSET(R$9,4*(ROW()-ROW(R$106)),0) -> 5171.632 | S111: ='1.3'!D134 -> 356.425 | T111: =OFFSET(T$9,4*(ROW()-ROW(T$106)),0) -> 660.46125 | U111: =OFFSET(U$9,4*(ROW()-ROW(U$106)),0) -> 1543.367 | W111: =OFFSET(W$9,4*(ROW()-ROW(W$106)),0) -> 2268.878 | X111: =OFFSET(X$9,4*(ROW()-ROW(X$106)),0) -> 107.27155
B112: 2018-19 | C112: =OFFSET(C$9,4*(ROW()-ROW(C$106)),0) -> 5360.7856 | D112: =OFFSET(D$9,4*(ROW()-ROW(D$106)),0) -> 6954.014 | E112: =OFFSET(E$9,4*(ROW()-ROW(E$106)),0) -> 1968.304 | F112: =OFFSET(F$9,4*(ROW()-ROW(F$106)),0) -> 1406.8 | G112: =OFFSET(G$9,4*(ROW()-ROW(G$106)),0) -> 561.504 | H112: =OFFSET(H$9,4*(ROW()-ROW(H$106)),0) -> 10346.496 | I112: ='1.12'!I111 -> 1410.868 | J112: =OFFSET(J$9,4*(ROW()-ROW(J$106)),0) -> 872.85271 | K112: =OFFSET(K$9,4*(ROW()-ROW(K$106)),0) -> 139.51015 | L112: =OFFSET(L$9,4*(ROW()-ROW(L$106)),0) -> 99.711667 | M112: =OFFSET(M$9,4*(ROW()-ROW(M$106)),0) -> 39.798479 | N112: =OFFSET(N$9,4*(ROW()-ROW(N$106)),0) -> 733.34257 | P112: =OFFSET(P$9,4*(ROW()-ROW(P$106)),0) -> 2451.123 | Q112: =OFFSET(Q$9,4*(ROW()-ROW(Q$106)),0) -> 348.505 | R112: =OFFSET(R$9,4*(ROW()-ROW(R$106)),0) -> 5312.822 | S112: ='1.3'!D135 -> 367.389 | T112: =OFFSET(T$9,4*(ROW()-ROW(T$106)),0) -> 667.17376 | U112: =OFFSET(U$9,4*(ROW()-ROW(U$106)),0) -> 1540.9626 | W112: =OFFSET(W$9,4*(ROW()-ROW(W$106)),0) -> 2316.809 | X112: =OFFSET(X$9,4*(ROW()-ROW(X$106)),0) -> 105.77201
B113: 2019-20 | C113: =OFFSET(C$9,4*(ROW()-ROW(C$106)),0) -> 5529.5774 | D113: =OFFSET(D$9,4*(ROW()-ROW(D$106)),0) -> 7149.978 | E113: =OFFSET(E$9,4*(ROW()-ROW(E$106)),0) -> 2049.397 | F113: =OFFSET(F$9,4*(ROW()-ROW(F$106)),0) -> 1463.875 | G113: =OFFSET(G$9,4*(ROW()-ROW(G$106)),0) -> 585.522 | H113: =OFFSET(H$9,4*(ROW()-ROW(H$106)),0) -> 10630.158 | I113: ='1.12'!I112 -> 1461.695 | J113: =OFFSET(J$9,4*(ROW()-ROW(J$106)),0) -> 867.45562 | K113: =OFFSET(K$9,4*(ROW()-ROW(K$106)),0) -> 140.20688 | L113: =OFFSET(L$9,4*(ROW()-ROW(L$106)),0) -> 100.14914 | M113: =OFFSET(M$9,4*(ROW()-ROW(M$106)),0) -> 40.057741 | N113: =OFFSET(N$9,4*(ROW()-ROW(N$106)),0) -> 727.24874 | P113: =OFFSET(P$9,4*(ROW()-ROW(P$106)),0) -> 2710.823 | Q113: =OFFSET(Q$9,4*(ROW()-ROW(Q$106)),0) -> 380.473 | R113: =OFFSET(R$9,4*(ROW()-ROW(R$106)),0) -> 5147.197 | S113: ='1.3'!D136 -> 379.446 | T113: =OFFSET(T$9,4*(ROW()-ROW(T$106)),0) -> 714.41602 | U113: =OFFSET(U$9,4*(ROW()-ROW(U$106)),0) -> 1456.7738 | W113: =OFFSET(W$9,4*(ROW()-ROW(W$106)),0) -> 2429.87 | X113: =OFFSET(X$9,4*(ROW()-ROW(X$106)),0) -> 107.59531
B114: 2020-21 | C114: =OFFSET(C$9,4*(ROW()-ROW(C$106)),0) -> 5906.3169 | D114: =OFFSET(D$9,4*(ROW()-ROW(D$106)),0) -> 7397.901 | E114: =OFFSET(E$9,4*(ROW()-ROW(E$106)),0) -> 2075.582 | F114: =OFFSET(F$9,4*(ROW()-ROW(F$106)),0) -> 1517.283 | G114: =OFFSET(G$9,4*(ROW()-ROW(G$106)),0) -> 558.299 | H114: =OFFSET(H$9,4*(ROW()-ROW(H$106)),0) -> 11228.636 | I114: ='1.12'!I113 -> 1468.707 | J114: =OFFSET(J$9,4*(ROW()-ROW(J$106)),0) -> 905.84561 | K114: =OFFSET(K$9,4*(ROW()-ROW(K$106)),0) -> 141.32036 | L114: =OFFSET(L$9,4*(ROW()-ROW(L$106)),0) -> 103.3074 | M114: =OFFSET(M$9,4*(ROW()-ROW(M$106)),0) -> 38.01296 | N114: =OFFSET(N$9,4*(ROW()-ROW(N$106)),0) -> 764.52525 | P114: =OFFSET(P$9,4*(ROW()-ROW(P$106)),0) -> 2814.288 | Q114: =OFFSET(Q$9,4*(ROW()-ROW(Q$106)),0) -> 395.948 | R114: =OFFSET(R$9,4*(ROW()-ROW(R$106)),0) -> 5682.613 | S114: ='1.3'!D137 -> 385.85 | T114: =OFFSET(T$9,4*(ROW()-ROW(T$106)),0) -> 729.37359 | U114: =OFFSET(U$9,4*(ROW()-ROW(U$106)),0) -> 1575.3689 | W114: =OFFSET(W$9,4*(ROW()-ROW(W$106)),0) -> 2471.53 | X114: =OFFSET(X$9,4*(ROW()-ROW(X$106)),0) -> 117.10798
B115: 2021-22 | C115: =OFFSET(C$9,4*(ROW()-ROW(C$106)),0) -> 6301.0505 | D115: =OFFSET(D$9,4*(ROW()-ROW(D$106)),0) -> 7331.097 | E115: =OFFSET(E$9,4*(ROW()-ROW(E$106)),0) -> 2119.128 | F115: =OFFSET(F$9,4*(ROW()-ROW(F$106)),0) -> 1577.295 | G115: =OFFSET(G$9,4*(ROW()-ROW(G$106)),0) -> 541.833 | H115: =OFFSET(H$9,4*(ROW()-ROW(H$106)),0) -> 11513.02 | I115: ='1.12'!I114 -> 1535.526 | J115: =OFFSET(J$9,4*(ROW()-ROW(J$106)),0) -> 887.78357 | K115: =OFFSET(K$9,4*(ROW()-ROW(K$106)),0) -> 138.00665 | L115: =OFFSET(L$9,4*(ROW()-ROW(L$106)),0) -> 102.72018 | M115: =OFFSET(M$9,4*(ROW()-ROW(M$106)),0) -> 35.286475 | N115: =OFFSET(N$9,4*(ROW()-ROW(N$106)),0) -> 749.77692 | P115: =OFFSET(P$9,4*(ROW()-ROW(P$106)),0) -> 3019.233 | Q115: =OFFSET(Q$9,4*(ROW()-ROW(Q$106)),0) -> 396.878 | R115: =OFFSET(R$9,4*(ROW()-ROW(R$106)),0) -> 5707.566 | S115: ='1.3'!D138 -> 419.717 | T115: =OFFSET(T$9,4*(ROW()-ROW(T$106)),0) -> 719.3497 | U115: =OFFSET(U$9,4*(ROW()-ROW(U$106)),0) -> 1454.419 | W115: =OFFSET(W$9,4*(ROW()-ROW(W$106)),0) -> 2516.006 | X115: =OFFSET(X$9,4*(ROW()-ROW(X$106)),0) -> 104.80956
B116: 2022-23 | C116: =OFFSET(C$9,4*(ROW()-ROW(C$106)),0) -> 6599.2687 | D116: =OFFSET(D$9,4*(ROW()-ROW(D$106)),0) -> 6609.131 | E116: =OFFSET(E$9,4*(ROW()-ROW(E$106)),0) -> 2197.05 | F116: =OFFSET(F$9,4*(ROW()-ROW(F$106)),0) -> 1618.794 | G116: =OFFSET(G$9,4*(ROW()-ROW(G$106)),0) -> 578.256 | H116: =OFFSET(H$9,4*(ROW()-ROW(H$106)),0) -> 11011.35 | I116: ='1.12'!I115 -> 1647.953 | J116: =OFFSET(J$9,4*(ROW()-ROW(J$106)),0) -> 801.50342 | K116: =OFFSET(K$9,4*(ROW()-ROW(K$106)),0) -> 133.31994 | L116: =OFFSET(L$9,4*(ROW()-ROW(L$106)),0) -> 98.230593 | M116: =OFFSET(M$9,4*(ROW()-ROW(M$106)),0) -> 35.08935 | N116: =OFFSET(N$9,4*(ROW()-ROW(N$106)),0) -> 668.18348 | P116: =OFFSET(P$9,4*(ROW()-ROW(P$106)),0) -> 3040.566 | Q116: =OFFSET(Q$9,4*(ROW()-ROW(Q$106)),0) -> 394.759 | R116: =OFFSET(R$9,4*(ROW()-ROW(R$106)),0) -> 5573.777 | S116: ='1.3'!D139 -> 464.643 | T116: =OFFSET(T$9,4*(ROW()-ROW(T$106)),0) -> 654.38756 | U116: =OFFSET(U$9,4*(ROW()-ROW(U$106)),0) -> 1284.5423 | W116: =OFFSET(W$9,4*(ROW()-ROW(W$106)),0) -> 2591.809 | X116: =OFFSET(X$9,4*(ROW()-ROW(X$106)),0) -> 98.281464
B117: 2023-24 | C117: =OFFSET(C$9,4*(ROW()-ROW(C$106)),0) -> 6525.9483 | D117: =OFFSET(D$9,4*(ROW()-ROW(D$106)),0) -> 6619.756 | E117: =OFFSET(E$9,4*(ROW()-ROW(E$106)),0) -> 2252.288 | F117: =OFFSET(F$9,4*(ROW()-ROW(F$106)),0) -> 1620.57 | G117: =OFFSET(G$9,4*(ROW()-ROW(G$106)),0) -> 631.718 | H117: =OFFSET(H$9,4*(ROW()-ROW(H$106)),0) -> 10893.416 | I117: ='1.12'!I116 -> 1768.778 | J117: =OFFSET(J$9,4*(ROW()-ROW(J$106)),0) -> 743.20827 | K117: =OFFSET(K$9,4*(ROW()-ROW(K$106)),0) -> 127.33582 | L117: =OFFSET(L$9,4*(ROW()-ROW(L$106)),0) -> 91.620882 | M117: =OFFSET(M$9,4*(ROW()-ROW(M$106)),0) -> 35.71494 | N117: =OFFSET(N$9,4*(ROW()-ROW(N$106)),0) -> 615.87244 | P117: =OFFSET(P$9,4*(ROW()-ROW(P$106)),0) -> 2942.129 | Q117: =OFFSET(Q$9,4*(ROW()-ROW(Q$106)),0) -> 393.044 | R117: =OFFSET(R$9,4*(ROW()-ROW(R$106)),0) -> 5599.561 | S117: ='1.3'!D140 -> 468.058 | T117: =OFFSET(T$9,4*(ROW()-ROW(T$106)),0) -> 628.58214 | U117: =OFFSET(U$9,4*(ROW()-ROW(U$106)),0) -> 1280.3125 | W117: =OFFSET(W$9,4*(ROW()-ROW(W$106)),0) -> 2645.332 | X117: =OFFSET(X$9,4*(ROW()-ROW(X$106)),0) -> 95.223991
... B125: 2031-32 | C125: =OFFSET(C$9,4*(ROW()-ROW(C$106)),0) -> 8058.1869 | D125: =OFFSET(D$9,4*(ROW()-ROW(D$106)),0) -> 7396.8639 | E125: =OFFSET(E$9,4*(ROW()-ROW(E$106)),0) -> 2764.7648 | F125: =OFFSET(F$9,4*(ROW()-ROW(F$106)),0) -> 2058.565 | G125: =OFFSET(G$9,4*(ROW()-ROW(G$106)),0) -> 706.19975 | H125: =OFFSET(H$9,4*(ROW()-ROW(H$106)),0) -> 12690.286 | I125: ='1.12'!I124 -> 2328.5204 | J125: =OFFSET(J$9,4*(ROW()-ROW(J$106)),0) -> 663.72839 | K125: =OFFSET(K$9,4*(ROW()-ROW(K$106)),0) -> 118.73483 | L125: =OFFSET(L$9,4*(ROW()-ROW(L$106)),0) -> 88.406572 | M125: =OFFSET(M$9,4*(ROW()-ROW(M$106)),0) -> 30.328261 | N125: =OFFSET(N$9,4*(ROW()-ROW(N$106)),0) -> 544.99356 | P125: =OFFSET(P$9,4*(ROW()-ROW(P$106)),0) -> 3356.2682 | Q125: =OFFSET(Q$9,4*(ROW()-ROW(Q$106)),0) -> 463.14192 | R125: =OFFSET(R$9,4*(ROW()-ROW(R$106)),0) -> 6740.5028 | S125: ='1.3'!D148 -> 656.25978 | T125: =OFFSET(T$9,4*(ROW()-ROW(T$106)),0) -> 511.42372 | U125: =OFFSET(U$9,4*(ROW()-ROW(U$106)),0) -> 1097.6819 | W125: =OFFSET(W$9,4*(ROW()-ROW(W$106)),0) -> 3227.9067 | X125: =OFFSET(X$9,4*(ROW()-ROW(X$106)),0) -> 84.904754
B126: Definitions: | P126: Definitions: | W126: Definitions:
B127: Household financial assets (ONS Economic Accounts, identifier: NNML) | P127: Corporate financial assets (ONS Economic Accounts, identifier: NKWX) | W127: UK bank sterling-denominated lending to firms and households (ONS Economic Accounts, identifier: NLBE-NLBG+NNPP) 1 Ratios are calculated as stock relative to sum of flows over the preceding four quarters.
B128: Household physical assets (OBR interpolation of annual ONS data. Blue Book, identifiers: E42X+NG45-MU8A-MHT3+CGRO) | P128: Corporate financial liabilities (ONS Economic Accounts, identifier: NLBB)
B129: Household financial liabilities (ONS Economic Accounts, identifier: NNPP) | P129: Non-oil PNFC profits (ONS Economic Accounts identifier: CAED, adjusted in Q1, Q2 and Q3 2020 for the revised alignment adjustment DMUQ)
B130: Household secured liabilities (ONS Economic Accounts, identifier: NNRP)
B131: Household other liabilities (ONS Economic Accounts, identifier: NNPP-NNRP) | P131: 1 Ratios are calculated as stock relative to sum of flows over the preceding four quarters.
B132: Household total net worth (ONS Economic Accounts and Blue Book, identifier: NZEA+E42X+NG45-MU8A-MHT3+CGRO) | P132: 2 We do not produce a physical asset forecast so we cannot produce a forecast of PNFC net worth.
B133: Disposable income (ONS Economic Accounts, identifier: RPHQ)
B134: 1 Ratios are calculated as stock relative to sum of flows over the preceding four quarters.

Sheet 1.11b
A1: Back to contents
B2: 1.11b Household balance sheet - unsecured household debt
C3: Households
C4: Student debt (£bn) | D4: Other unsecured liabilities (£bn) | E4: Total unsecured liabilities (£bn) | F4: Student debt to income ratio1 (per cent) | G4: Other unsecured liabilities to income ratio1 (per cent) | H4: Total unsecured liabilities to income ratio1 (per cent)
B5: 2012Q1 | C5: 40.877 | D5: 388.85 | E5: 429.727 | F5: 3.7206369 | G5: 35.393244 | H5: 39.113881
B6: 2012Q2 | C6: 43.024 | D6: 394.603 | E6: 437.627 | F6: 3.8735723 | G6: 35.527223 | H6: 39.400796
B7: 2012Q3 | C7: 44.452 | D7: 389.318 | E7: 433.77 | F7: 3.9708715 | G7: 34.777552 | H7: 38.748423
B8: 2012Q4 | C8: 44.195 | D8: 391.64 | E8: 435.835 | F8: 3.9110031 | G8: 34.657886 | H8: 38.568889
B9: 2013Q1 | C9: 45.657 | D9: 394.482 | E9: 440.139 | F9: 4.024072 | G9: 34.768468 | H9: 38.79254
B10: 2013Q2 | C10: 48.034 | D10: 385.378 | E10: 433.412 | F10: 4.2021556 | G10: 33.714001 | H10: 37.916156
B11: 2013Q3 | C11: 49.54 | D11: 394.567 | E11: 444.107 | F11: 4.2735596 | G11: 34.037254 | H11: 38.310814
B12: 2013Q4 | C12: 49.14 | D12: 397.684 | E12: 446.824 | F12: 4.1787953 | G12: 33.818478 | H12: 37.997274
B13: 2014Q1 | C13: 50.883 | D13: 396.212 | E13: 447.095 | F13: 4.2630788 | G13: 33.195428 | H13: 37.458507
B14: 2014Q2 | C14: 53.448 | D14: 398.134 | E14: 451.582 | F14: 4.4320356 | G14: 33.01422 | H14: 37.446256
B15: 2014Q3 | C15: 55.021 | D15: 407.408 | E15: 462.429 | F15: 4.5424412 | G15: 33.634919 | H15: 38.17736
B16: 2014Q4 | C16: 54.799 | D16: 419.389 | E16: 474.188 | F16: 4.4994995 | G16: 34.435676 | H16: 38.935176
... B85: 2032Q1 | C85: 270.922 | D85: 435.27774 | E85: 706.19975 | F85: 11.634942 | G85: 18.693319 | H85: 30.328261
B86: 2012 | C86: =OFFSET(C$8,4*(ROW()-ROW(C$86)),0) -> 44.195 | D86: =OFFSET(D$8,4*(ROW()-ROW(D$86)),0) -> 391.64 | E86: =OFFSET(E$8,4*(ROW()-ROW(E$86)),0) -> 435.835 | F86: =OFFSET(F$8,4*(ROW()-ROW(F$86)),0) -> 3.9110031 | G86: =OFFSET(G$8,4*(ROW()-ROW(G$86)),0) -> 34.657886 | H86: =OFFSET(H$8,4*(ROW()-ROW(H$86)),0) -> 38.568889
B87: 2013 | C87: =OFFSET(C$8,4*(ROW()-ROW(C$86)),0) -> 49.14 | D87: =OFFSET(D$8,4*(ROW()-ROW(D$86)),0) -> 397.684 | E87: =OFFSET(E$8,4*(ROW()-ROW(E$86)),0) -> 446.824 | F87: =OFFSET(F$8,4*(ROW()-ROW(F$86)),0) -> 4.1787953 | G87: =OFFSET(G$8,4*(ROW()-ROW(G$86)),0) -> 33.818478 | H87: =OFFSET(H$8,4*(ROW()-ROW(H$86)),0) -> 37.997274
B88: 2014 | C88: =OFFSET(C$8,4*(ROW()-ROW(C$86)),0) -> 54.799 | D88: =OFFSET(D$8,4*(ROW()-ROW(D$86)),0) -> 419.389 | E88: =OFFSET(E$8,4*(ROW()-ROW(E$86)),0) -> 474.188 | F88: =OFFSET(F$8,4*(ROW()-ROW(F$86)),0) -> 4.4994995 | G88: =OFFSET(G$8,4*(ROW()-ROW(G$86)),0) -> 34.435676 | H88: =OFFSET(H$8,4*(ROW()-ROW(H$86)),0) -> 38.935176
B89: 2015 | C89: =OFFSET(C$8,4*(ROW()-ROW(C$86)),0) -> 60.63 | D89: =OFFSET(D$8,4*(ROW()-ROW(D$86)),0) -> 432.859 | E89: =OFFSET(E$8,4*(ROW()-ROW(E$86)),0) -> 493.489 | F89: =OFFSET(F$8,4*(ROW()-ROW(F$86)),0) -> 4.7105311 | G89: =OFFSET(G$8,4*(ROW()-ROW(G$86)),0) -> 33.630147 | H89: =OFFSET(H$8,4*(ROW()-ROW(H$86)),0) -> 38.340678
B90: 2016 | C90: =OFFSET(C$8,4*(ROW()-ROW(C$86)),0) -> 66.702 | D90: =OFFSET(D$8,4*(ROW()-ROW(D$86)),0) -> 454.79 | E90: =OFFSET(E$8,4*(ROW()-ROW(E$86)),0) -> 521.492 | F90: =OFFSET(F$8,4*(ROW()-ROW(F$86)),0) -> 5.0811551 | G90: =OFFSET(G$8,4*(ROW()-ROW(G$86)),0) -> 34.644516 | H90: =OFFSET(H$8,4*(ROW()-ROW(H$86)),0) -> 39.725672
B91: 2017 | C91: =OFFSET(C$8,4*(ROW()-ROW(C$86)),0) -> 71.323 | D91: =OFFSET(D$8,4*(ROW()-ROW(D$86)),0) -> 468.51 | E91: =OFFSET(E$8,4*(ROW()-ROW(E$86)),0) -> 539.833 | F91: =OFFSET(F$8,4*(ROW()-ROW(F$86)),0) -> 5.2895522 | G91: =OFFSET(G$8,4*(ROW()-ROW(G$86)),0) -> 34.746269 | H91: =OFFSET(H$8,4*(ROW()-ROW(H$86)),0) -> 40.035821
B92: 2018 | C92: =OFFSET(C$8,4*(ROW()-ROW(C$86)),0) -> 74.033 | D92: =OFFSET(D$8,4*(ROW()-ROW(D$86)),0) -> 474.904 | E92: =OFFSET(E$8,4*(ROW()-ROW(E$86)),0) -> 548.937 | F92: =OFFSET(F$8,4*(ROW()-ROW(F$86)),0) -> 5.2782162 | G92: =OFFSET(G$8,4*(ROW()-ROW(G$86)),0) -> 33.858496 | H92: =OFFSET(H$8,4*(ROW()-ROW(H$86)),0) -> 39.136712
B93: 2019 | C93: =OFFSET(C$8,4*(ROW()-ROW(C$86)),0) -> 86.139 | D93: =OFFSET(D$8,4*(ROW()-ROW(D$86)),0) -> 470.521 | E93: =OFFSET(E$8,4*(ROW()-ROW(E$86)),0) -> 556.66 | F93: =OFFSET(F$8,4*(ROW()-ROW(F$86)),0) -> 5.9139468 | G93: =OFFSET(G$8,4*(ROW()-ROW(G$86)),0) -> 32.304022 | H93: =OFFSET(H$8,4*(ROW()-ROW(H$86)),0) -> 38.217969
B94: 2020 | C94: =OFFSET(C$8,4*(ROW()-ROW(C$86)),0) -> 89.427 | D94: =OFFSET(D$8,4*(ROW()-ROW(D$86)),0) -> 478.478 | E94: =OFFSET(E$8,4*(ROW()-ROW(E$86)),0) -> 567.905 | F94: =OFFSET(F$8,4*(ROW()-ROW(F$86)),0) -> 6.1489706 | G94: =OFFSET(G$8,4*(ROW()-ROW(G$86)),0) -> 32.899987 | H94: =OFFSET(H$8,4*(ROW()-ROW(H$86)),0) -> 39.048958
B95: 2021 | C95: =OFFSET(C$8,4*(ROW()-ROW(C$86)),0) -> 84.247 | D95: =OFFSET(D$8,4*(ROW()-ROW(D$86)),0) -> 448.686 | E95: =OFFSET(E$8,4*(ROW()-ROW(E$86)),0) -> 532.933 | F95: =OFFSET(F$8,4*(ROW()-ROW(F$86)),0) -> 5.5433791 | G95: =OFFSET(G$8,4*(ROW()-ROW(G$86)),0) -> 29.523147 | H95: =OFFSET(H$8,4*(ROW()-ROW(H$86)),0) -> 35.066526
B96: 2022 | C96: =OFFSET(C$8,4*(ROW()-ROW(C$86)),0) -> 97.118 | D96: =OFFSET(D$8,4*(ROW()-ROW(D$86)),0) -> 473.172 | E96: =OFFSET(E$8,4*(ROW()-ROW(E$86)),0) -> 570.29 | F96: =OFFSET(F$8,4*(ROW()-ROW(F$86)),0) -> 6.0189808 | G96: =OFFSET(G$8,4*(ROW()-ROW(G$86)),0) -> 29.325286 | H96: =OFFSET(H$8,4*(ROW()-ROW(H$86)),0) -> 35.344267
B97: 2023 | C97: =OFFSET(C$8,4*(ROW()-ROW(C$86)),0) -> 121.598 | D97: =OFFSET(D$8,4*(ROW()-ROW(D$86)),0) -> 498.404 | E97: =OFFSET(E$8,4*(ROW()-ROW(E$86)),0) -> 620.002 | F97: =OFFSET(F$8,4*(ROW()-ROW(F$86)),0) -> 6.9877884 | G97: =OFFSET(G$8,4*(ROW()-ROW(G$86)),0) -> 28.641439 | H97: =OFFSET(H$8,4*(ROW()-ROW(H$86)),0) -> 35.629227
... B105: 2031 | C105: =OFFSET(C$8,4*(ROW()-ROW(C$86)),0) -> 265.89568 | D105: =OFFSET(D$8,4*(ROW()-ROW(D$86)),0) -> 433.92872 | E105: =OFFSET(E$8,4*(ROW()-ROW(E$86)),0) -> 699.8244 | F105: =OFFSET(F$8,4*(ROW()-ROW(F$86)),0) -> 11.497905 | G105: =OFFSET(G$8,4*(ROW()-ROW(G$86)),0) -> 18.764018 | H105: =OFFSET(H$8,4*(ROW()-ROW(H$86)),0) -> 30.261923
B106: 2012-13 | C106: =OFFSET(C$9,4*(ROW()-ROW(C$106)),0) -> 45.657 | D106: =OFFSET(D$9,4*(ROW()-ROW(D$106)),0) -> 394.482 | E106: =OFFSET(E$9,4*(ROW()-ROW(E$106)),0) -> 440.139 | F106: =OFFSET(F$9,4*(ROW()-ROW(F$106)),0) -> 4.024072 | G106: =OFFSET(G$9,4*(ROW()-ROW(G$106)),0) -> 34.768468 | H106: =OFFSET(H$9,4*(ROW()-ROW(H$106)),0) -> 38.79254
B107: 2013-14 | C107: =OFFSET(C$9,4*(ROW()-ROW(C$106)),0) -> 50.883 | D107: =OFFSET(D$9,4*(ROW()-ROW(D$106)),0) -> 396.212 | E107: =OFFSET(E$9,4*(ROW()-ROW(E$106)),0) -> 447.095 | F107: =OFFSET(F$9,4*(ROW()-ROW(F$106)),0) -> 4.2630788 | G107: =OFFSET(G$9,4*(ROW()-ROW(G$106)),0) -> 33.195428 | H107: =OFFSET(H$9,4*(ROW()-ROW(H$106)),0) -> 37.458507
B108: 2014-15 | C108: =OFFSET(C$9,4*(ROW()-ROW(C$106)),0) -> 56.549 | D108: =OFFSET(D$9,4*(ROW()-ROW(D$106)),0) -> 417.664 | E108: =OFFSET(E$9,4*(ROW()-ROW(E$106)),0) -> 474.213 | F108: =OFFSET(F$9,4*(ROW()-ROW(F$106)),0) -> 4.6048962 | G108: =OFFSET(G$9,4*(ROW()-ROW(G$106)),0) -> 34.0112 | H108: =OFFSET(H$9,4*(ROW()-ROW(H$106)),0) -> 38.616096
B109: 2015-16 | C109: =OFFSET(C$9,4*(ROW()-ROW(C$106)),0) -> 62.418 | D109: =OFFSET(D$9,4*(ROW()-ROW(D$106)),0) -> 451.725 | E109: =OFFSET(E$9,4*(ROW()-ROW(E$106)),0) -> 514.143 | F109: =OFFSET(F$9,4*(ROW()-ROW(F$106)),0) -> 4.7952762 | G109: =OFFSET(G$9,4*(ROW()-ROW(G$106)),0) -> 34.70387 | H109: =OFFSET(H$9,4*(ROW()-ROW(H$106)),0) -> 39.499146
B110: 2016-17 | C110: =OFFSET(C$9,4*(ROW()-ROW(C$106)),0) -> 69.032 | D110: =OFFSET(D$9,4*(ROW()-ROW(D$106)),0) -> 471.715 | E110: =OFFSET(E$9,4*(ROW()-ROW(E$106)),0) -> 540.747 | F110: =OFFSET(F$9,4*(ROW()-ROW(F$106)),0) -> 5.2535649 | G110: =OFFSET(G$9,4*(ROW()-ROW(G$106)),0) -> 35.899081 | H110: =OFFSET(H$9,4*(ROW()-ROW(H$106)),0) -> 41.152646
B111: 2017-18 | C111: =OFFSET(C$9,4*(ROW()-ROW(C$106)),0) -> 70.809 | D111: =OFFSET(D$9,4*(ROW()-ROW(D$106)),0) -> 468.59 | E111: =OFFSET(E$9,4*(ROW()-ROW(E$106)),0) -> 539.399 | F111: =OFFSET(F$9,4*(ROW()-ROW(F$106)),0) -> 5.1738121 | G111: =OFFSET(G$9,4*(ROW()-ROW(G$106)),0) -> 34.238538 | H111: =OFFSET(H$9,4*(ROW()-ROW(H$106)),0) -> 39.41235
B112: 2018-19 | C112: =OFFSET(C$9,4*(ROW()-ROW(C$106)),0) -> 79.778 | D112: =OFFSET(D$9,4*(ROW()-ROW(D$106)),0) -> 481.726 | E112: =OFFSET(E$9,4*(ROW()-ROW(E$106)),0) -> 561.504 | F112: =OFFSET(F$9,4*(ROW()-ROW(F$106)),0) -> 5.6545332 | G112: =OFFSET(G$9,4*(ROW()-ROW(G$106)),0) -> 34.143945 | H112: =OFFSET(H$9,4*(ROW()-ROW(H$106)),0) -> 39.798479
B113: 2019-20 | C113: =OFFSET(C$9,4*(ROW()-ROW(C$106)),0) -> 83.092 | D113: =OFFSET(D$9,4*(ROW()-ROW(D$106)),0) -> 502.43 | E113: =OFFSET(E$9,4*(ROW()-ROW(E$106)),0) -> 585.522 | F113: =OFFSET(F$9,4*(ROW()-ROW(F$106)),0) -> 5.6846333 | G113: =OFFSET(G$9,4*(ROW()-ROW(G$106)),0) -> 34.373108 | H113: =OFFSET(H$9,4*(ROW()-ROW(H$106)),0) -> 40.057741
B114: 2020-21 | C114: =OFFSET(C$9,4*(ROW()-ROW(C$106)),0) -> 90.268 | D114: =OFFSET(D$9,4*(ROW()-ROW(D$106)),0) -> 468.031 | E114: =OFFSET(E$9,4*(ROW()-ROW(E$106)),0) -> 558.299 | F114: =OFFSET(F$9,4*(ROW()-ROW(F$106)),0) -> 6.1460863 | G114: =OFFSET(G$9,4*(ROW()-ROW(G$106)),0) -> 31.866873 | H114: =OFFSET(H$9,4*(ROW()-ROW(H$106)),0) -> 38.01296
B115: 2021-22 | C115: =OFFSET(C$9,4*(ROW()-ROW(C$106)),0) -> 86.509 | D115: =OFFSET(D$9,4*(ROW()-ROW(D$106)),0) -> 455.324 | E115: =OFFSET(E$9,4*(ROW()-ROW(E$106)),0) -> 541.833 | F115: =OFFSET(F$9,4*(ROW()-ROW(F$106)),0) -> 5.6338349 | G115: =OFFSET(G$9,4*(ROW()-ROW(G$106)),0) -> 29.65264 | H115: =OFFSET(H$9,4*(ROW()-ROW(H$106)),0) -> 35.286475
B116: 2022-23 | C116: =OFFSET(C$9,4*(ROW()-ROW(C$106)),0) -> 97.49 | D116: =OFFSET(D$9,4*(ROW()-ROW(D$106)),0) -> 480.766 | E116: =OFFSET(E$9,4*(ROW()-ROW(E$106)),0) -> 578.256 | F116: =OFFSET(F$9,4*(ROW()-ROW(F$106)),0) -> 5.9158241 | G116: =OFFSET(G$9,4*(ROW()-ROW(G$106)),0) -> 29.173526 | H116: =OFFSET(H$9,4*(ROW()-ROW(H$106)),0) -> 35.08935
B117: 2023-24 | C117: =OFFSET(C$9,4*(ROW()-ROW(C$106)),0) -> 130.203 | D117: =OFFSET(D$9,4*(ROW()-ROW(D$106)),0) -> 501.515 | E117: =OFFSET(E$9,4*(ROW()-ROW(E$106)),0) -> 631.718 | F117: =OFFSET(F$9,4*(ROW()-ROW(F$106)),0) -> 7.3611838 | G117: =OFFSET(G$9,4*(ROW()-ROW(G$106)),0) -> 28.353756 | H117: =OFFSET(H$9,4*(ROW()-ROW(H$106)),0) -> 35.71494
... B125: 2031-32 | C125: =OFFSET(C$9,4*(ROW()-ROW(C$106)),0) -> 270.922 | D125: =OFFSET(D$9,4*(ROW()-ROW(D$106)),0) -> 435.27774 | E125: =OFFSET(E$9,4*(ROW()-ROW(E$106)),0) -> 706.19975 | F125: =OFFSET(F$9,4*(ROW()-ROW(F$106)),0) -> 11.634942 | G125: =OFFSET(G$9,4*(ROW()-ROW(G$106)),0) -> 18.693319 | H125: =OFFSET(H$9,4*(ROW()-ROW(H$106)),0) -> 30.328261
B126: Definitions:
B127: Student debt (ONS Economic Accounts, identifier: CT9E)
B128: Household other unsecured liabilities (ONS Economic Accounts, identifier: NNPP-NNRP-CT9E)
B129: Household total unsecured liabilities (ONS Economic Accounts, identifier: NNPP-NNRP)
B130: 1 Ratios are calculated as stock relative to sum of flows over the preceding four quarters.

Sheet 1.12
A1: Back to contents
B2: 1.12 Household disposable income (£ billion current prices, seasonally adjusted)
C3: Labour Income (a + b - c) | D3: Employee compensation (a) | E3: Mixed Income (b) | F3: Employer social contributions (c) | G3: Non-labour income | H3: Net benefits and taxes | I3: Household disposable income
B4: 2012Q1 | C4: 196.099 | D4: 208.951 | E4: 25.457 | F4: 38.309 | G4: 65.487877 | H4: 18.196123 | I4: 279.783
B5: 2012Q2 | C5: 197.592 | D5: 210.298 | E5: 26.079 | F5: 38.785 | G5: 66.446123 | H5: 19.676877 | I5: 283.715
B6: 2012Q3 | C6: 197.233 | D6: 210.566 | E6: 25.771 | F6: 39.104 | G6: 65.926373 | H6: 19.123627 | I6: 282.283
B7: 2012Q4 | C7: 198.761 | D7: 211.729 | E7: 25.844 | F7: 38.812 | G7: 64.853628 | H7: 20.621372 | I7: 284.236
B8: 2013Q1 | C8: 199.543 | D8: 212.36 | E8: 25.873 | F8: 38.69 | G8: 64.421887 | H8: 20.398113 | I8: 284.363
B9: 2013Q2 | C9: 206.352 | D9: 219.378 | E9: 26.508 | F9: 39.534 | G9: 68.021136 | H9: 17.824864 | I9: 292.198
B10: 2013Q3 | C10: 208.181 | D10: 219.989 | E10: 27.198 | F10: 39.006 | G10: 69.308374 | H10: 20.934626 | I10: 298.424
B11: 2013Q4 | C11: 212.304 | D11: 221.903 | E11: 28.929 | F11: 38.528 | G11: 68.455602 | H11: 20.192398 | I11: 300.952
B12: 2014Q1 | C12: 215.281 | D12: 224.249 | E12: 29.35 | F12: 38.318 | G12: 67.543818 | H12: 19.175182 | I12: 302
B13: 2014Q2 | C13: 214.996 | D13: 223.446 | E13: 29.144 | F13: 37.594 | G13: 70.515078 | H13: 19.059922 | I13: 304.571
B14: 2014Q3 | C14: 213.969 | D14: 222.887 | E14: 28.445 | F14: 37.363 | G14: 71.12638 | H14: 18.64662 | I14: 303.742
B15: 2014Q4 | C15: 216.415 | D15: 225.552 | E15: 28.693 | F15: 37.83 | G15: 72.319725 | H15: 18.843275 | I15: 307.578
... B84: 2032Q1 | C84: 434.16357 | D84: 467.97648 | E84: 56.99786 | F84: 90.810777 | G84: 152.73116 | H84: 1.2981218 | I84: 588.19285
B85: 2012 | C85: 789.685 | D85: 841.544 | E85: 103.151 | F85: 155.01 | G85: 262.714 | H85: 77.618 | I85: 1130.017
B86: 2013 | C86: 826.38 | D86: 873.63 | E86: 108.508 | F86: 155.758 | G86: 270.207 | H86: 79.35 | I86: 1175.937
B87: 2014 | C87: 860.661 | D87: 896.134 | E87: 115.632 | F87: 151.105 | G87: 281.505 | H87: 75.725 | I87: 1217.891
B88: 2015 | C88: 892.399 | D88: 926.218 | E88: 122.582 | F88: 156.401 | G88: 321.469 | H88: 73.248 | I88: 1287.116
B89: 2016 | C89: 923.303 | D89: 963.419 | E89: 126.455 | F89: 166.571 | G89: 321.457 | H89: 67.973 | I89: 1312.733
B90: 2017 | C90: 966.72 | D90: 1001.099 | E90: 138.119 | F90: 172.498 | G90: 325.317 | H90: 56.338 | I90: 1348.375
B91: 2018 | C91: 1005.435 | D91: 1042.025 | E91: 143.106 | F91: 179.696 | G91: 342.469 | H91: 54.71 | I91: 1402.614
B92: 2019 | C92: 1046.154 | D92: 1090.664 | E92: 150.766 | F92: 195.276 | G92: 357.593 | H92: 52.793 | I92: 1456.54
B93: 2020 | C93: 1045.306 | D93: 1094.07 | E93: 152.109 | F93: 200.873 | G93: 330.879 | H93: 78.156 | I93: 1454.341
B94: 2021 | C94: 1111.849 | D94: 1155.891 | E94: 162.369 | F94: 206.411 | G94: 359.65 | H94: 48.278 | I94: 1519.777
B95: 2022 | C95: 1189.846 | D95: 1245.947 | E95: 168.687 | F95: 224.788 | G95: 395.161 | H95: 28.522 | I95: 1613.529
B96: 2023 | C96: 1264.439 | D96: 1329.125 | E96: 169.885 | F96: 234.571 | G96: 443.187 | H96: 32.524 | I96: 1740.15
... B104: 2031 | C104: 1704.3591 | D104: 1838.4137 | E104: 222.38105 | F104: 356.43563 | G104: 599.53065 | H104: 8.6678408 | I104: 2312.5576
B105: 2012-13 | C105: 793.129 | D105: 844.953 | E105: 103.567 | F105: 155.391 | G105: 261.64801 | H105: 79.81999 | I105: 1134.597
B106: 2013-14 | C106: 842.118 | D106: 885.519 | E106: 111.985 | F106: 155.386 | G106: 273.32893 | H106: 78.127069 | I106: 1193.574
B107: 2014-15 | C107: 864.617 | D107: 900.438 | E107: 115.382 | F107: 151.203 | G107: 289.59529 | H107: 73.806706 | I107: 1228.019
B108: 2015-16 | C108: 901.42 | D108: 934.245 | E108: 124.747 | F108: 157.572 | G108: 326.24978 | H108: 73.986224 | I108: 1301.656
B109: 2016-17 | C109: 931.509 | D109: 973.416 | E109: 128.019 | F109: 169.926 | G109: 320.15809 | H109: 62.335907 | I109: 1314.003
B110: 2017-18 | C110: 979.275 | D110: 1012.849 | E110: 140.573 | F110: 174.147 | G110: 330.49742 | H110: 58.831584 | I110: 1368.604
B111: 2018-19 | C111: 1013.754 | D111: 1051.436 | E111: 144.849 | F111: 182.531 | G111: 346.17648 | H111: 50.937522 | I111: 1410.868
B112: 2019-20 | C112: 1050.808 | D112: 1096.314 | E112: 151.696 | F112: 197.202 | G112: 354.50448 | H112: 56.382519 | I112: 1461.695
B113: 2020-21 | C113: 1052.526 | D113: 1101.679 | E113: 153.543 | F113: 202.696 | G113: 335.0372 | H113: 81.143796 | I113: 1468.707
B114: 2021-22 | C114: 1133.42 | D114: 1177.865 | E114: 164.776 | F114: 209.221 | G114: 364.78562 | H114: 37.320379 | I114: 1535.526
B115: 2022-23 | C115: 1210.389 | D115: 1269.72 | E115: 169.204 | F115: 228.535 | G115: 414.71126 | H115: 22.852738 | I115: 1647.953
B116: 2023-24 | C116: 1279.037 | D116: 1346.092 | E116: 171.245 | F116: 238.3 | G116: 443.24503 | H116: 46.495974 | I116: 1768.778
... B124: 2031-32 | C124: 1717.323 | D124: 1851.8486 | E124: 224.62634 | F124: 359.1519 | G124: 604.12644 | H124: 7.0709402 | I124: 2328.5204
B125: Definitions:
B126: Labour income = Employee compensation (including net compensation from abroad) + mixed income (largely self-employment income) - employer social contributions. (ONS Economic Accounts, identifier: DTWM+ROYH-ROYK+IJAH-IJAI)
B127: Non-labour income = Operating surplus of households + net property income + imputed social contributions - social benefits (use) + net miscellaneous transfers. (ONS Economic Accounts identifier: CAEN+ROYL-ROYT+L8RF-QWMZ+RPHO-RPID - (L8PE+L8Q2+L8LQ) - (CX3X+FJBH)).
B128: Net benefits and taxes = Social benefits (resource) - taxation on income and wealth - employees' social contributions (excluding employee contributions to funded pension schemes). (ONS Economic Accounts, identifier: RPHL-RPHS-RPHT-L8PS-L8Q8-L8LU + (L8PE+L8Q2+L8LQ) + (CX3X+FJBH)).
B129: Household disposable income (ONS Economic Accounts, identifier: RPHQ)

Sheet 1.13
A1: Back to contents
B2: 1.13 National Living Wage
C3: £ per hour
C4: 2020 | D4: 2021 | E4: 2022 | F4: 2023 | G4: 2024 | H4: 2025 | I4: 2026 | J4: 2027 | K4: 2028 | L4: 2029 | M4: 2030 | N4: 2031
B5: National Living Wage (NLW) | C5: 8.72 | D5: 8.91 | E5: 9.5 | F5: 10.42 | G5: 11.44 | H5: 12.21 | I5: 12.71 | J5: 13.21 | K5: 13.513623 | L5: 13.854853 | M5: 14.232939 | N5: 14.617023
B6: Note: The NLW has been set by the Government up until 2027 following recommendations from the Low Pay Commission (LPC) in accordance with its remit, and the state of the labour market and economy. Figures beyond 2027 are OBR estimates consistent with the rest of our economy forecast.

Sheet 1.14
A1: Back to contents
B2: 1.14 OBR central estimate of the output gap
B3: 1972Q1 | C3: -0.31754134
B4: 1972Q2 | C4: -0.12507214
B5: 1972Q3 | C5: 1.2172976
B6: 1972Q4 | C6: 3.0940251
B7: 1973Q1 | C7: 5.9924949
B8: 1973Q2 | C8: 8.3384672
B9: 1973Q3 | C9: 7.0809655
B10: 1973Q4 | C10: 6.1121425
B11: 1974Q1 | C11: 4.6261511
B12: 1974Q2 | C12: 5.5649824
B13: 1974Q3 | C13: 4.119837
B14: 1974Q4 | C14: 2.361365
... B220: 2026Q2 | C220: -1.1056935
B221: 1972 | C221: =AVERAGE(OFFSET(C$3,4*(ROW()-ROW($C$221)),0,4)) -> 0.9671773
B222: 1973 | C222: =AVERAGE(OFFSET(C$3,4*(ROW()-ROW($C$221)),0,4)) -> 6.8810175
B223: 1974 | C223: =AVERAGE(OFFSET(C$3,4*(ROW()-ROW($C$221)),0,4)) -> 4.1680839
B224: 1975 | C224: =AVERAGE(OFFSET(C$3,4*(ROW()-ROW($C$221)),0,4)) -> -1.1675653
B225: 1976 | C225: =AVERAGE(OFFSET(C$3,4*(ROW()-ROW($C$221)),0,4)) -> -1.0247315
B226: 1977 | C226: =AVERAGE(OFFSET(C$3,4*(ROW()-ROW($C$221)),0,4)) -> -0.59622047
B227: 1978 | C227: =AVERAGE(OFFSET(C$3,4*(ROW()-ROW($C$221)),0,4)) -> 1.1573002
B228: 1979 | C228: =AVERAGE(OFFSET(C$3,4*(ROW()-ROW($C$221)),0,4)) -> 0.76529255
B229: 1980 | C229: =AVERAGE(OFFSET(C$3,4*(ROW()-ROW($C$221)),0,4)) -> -2.4583244
B230: 1981 | C230: =AVERAGE(OFFSET(C$3,4*(ROW()-ROW($C$221)),0,4)) -> -3.1739715
B231: 1982 | C231: =AVERAGE(OFFSET(C$3,4*(ROW()-ROW($C$221)),0,4)) -> -2.9254717
B232: 1983 | C232: =AVERAGE(OFFSET(C$3,4*(ROW()-ROW($C$221)),0,4)) -> -1.7607649
... B255: 2006 | C255: =AVERAGE(OFFSET(C$3,4*(ROW()-ROW($C$221)),0,4)) -> -0.017825624
B256: 2007 | C256: 0.51710559
B257: 2008 | C257: -0.0093468768
B258: 2009 | C258: -3.0775729
B259: 2010 | C259: -2.5518392
B260: 2011 | C260: -2.5409051
B261: 2012 | C261: -2.11446
B262: 2013 | C262: -1.9024187
B263: 2014 | C263: -0.79087038
B264: 2015 | C264: -0.18446459
B265: 2016 | C265: -0.20525992
B266: 2017 | C266: 0.05838926
B267: 2018 | C267: 0.21795894
... B274: 2025 | C274: -0.74240334
B275: 1972-73 | C275: =AVERAGE(OFFSET(C$4,4*(ROW()-ROW($C$275)),0,4)) -> 2.5446864
B276: 1973-74 | C276: =AVERAGE(OFFSET(C$4,4*(ROW()-ROW($C$275)),0,4)) -> 6.5394316
B277: 1974-75 | C277: =AVERAGE(OFFSET(C$4,4*(ROW()-ROW($C$275)),0,4)) -> 3.1047807
B278: 1975-76 | C278: =AVERAGE(OFFSET(C$4,4*(ROW()-ROW($C$275)),0,4)) -> -1.7370637
B279: 1976-77 | C279: =AVERAGE(OFFSET(C$4,4*(ROW()-ROW($C$275)),0,4)) -> -0.63964205
B280: 1977-78 | C280: =AVERAGE(OFFSET(C$4,4*(ROW()-ROW($C$275)),0,4)) -> -0.46907117
B281: 1978-79 | C281: =AVERAGE(OFFSET(C$4,4*(ROW()-ROW($C$275)),0,4)) -> 1.5613273
B282: 1979-80 | C282: =AVERAGE(OFFSET(C$4,4*(ROW()-ROW($C$275)),0,4)) -> -0.097964602
B283: 1980-81 | C283: =AVERAGE(OFFSET(C$4,4*(ROW()-ROW($C$275)),0,4)) -> -2.8166062
B284: 1981-82 | C284: =AVERAGE(OFFSET(C$4,4*(ROW()-ROW($C$275)),0,4)) -> -3.1630102
B285: 1982-83 | C285: =AVERAGE(OFFSET(C$4,4*(ROW()-ROW($C$275)),0,4)) -> -2.7122309
B286: 1983-84 | C286: =AVERAGE(OFFSET(C$4,4*(ROW()-ROW($C$275)),0,4)) -> -1.4882459
... B310: 2007-08 | C310: =AVERAGE(OFFSET(C$4,4*(ROW()-ROW($C$275)),0,4)) -> 0.6839156
B311: 2008-09 | C311: -0.95357533
B312: 2009-10 | C312: -3.1122303
B313: 2010-11 | C313: -2.3859045
B314: 2011-12 | C314: -2.4997143
B315: 2012-13 | C315: -2.1562726
B316: 2013-14 | C316: -1.5679072
B317: 2014-15 | C317: -0.64477542
B318: 2015-16 | C318: -0.095691442
B319: 2016-17 | C319: -0.17883743
B320: 2017-18 | C320: 0.076808462
B321: 2018-19 | C321: 0.37926667
B322: 2019-20 | C322: 0.55457139
... B328: 2025-26 | C328: -0.84877376
B329: Note: Estimates of the output gap between 1994 and 2025 are based on our suite of output gap models. Estimates prior to 1994 are based on our 'principle component analysis'. These estimates should be treated with extra caution prior to 1994 as only a limited number of the data sources used in this method are available for this period. For more details, see Pybus (2011): OBR Working Paper No.1: Estimating the UK’s historical output gap.

Sheet 1.15
A1: Back to contents
B2: 1.15 Potential output forecast
C3: Levels | L3: Growth rates
D4: Potential output1 (£m) | F4: Population (16+) | G4: Potential employment rate2 (16+) | H4: Potential participation rate | I4: Equilibrium unemployment rate | J4: Potential average hours | K4: Potential productivity per hour | M4: Potential output3 | O4: Population (16+) | P4: Potential employment rate | Q4: Potential participation rate | R4: Equilibrium unemployment rate | S4: Potential average hours | T4: Potential productivity per hour
B5: 2019Q1 | D5: 660703.2 | F5: 53301 | G5: 61.243246 | H5: 63.774381 | I5: 3.9688889 | J5: 31.777531 | K5: 636.93145 | M5: 0.52524372 | O5: 0.57361737 | P5: 0.46377684 | Q5: 0.091576861 | R5: 0.37185946 | S5: -0.71858088 | T5: 0.21058247
B6: 2019Q2 | D6: 661753.04 | F6: 53381 | G6: 61.240665 | H6: 63.776858 | I6: 3.9766667 | J6: 31.727531 | K6: 638.01819 | M6: 0.51372999 | O6: 0.59549609 | P6: 0.23416929 | Q6: 0.069588636 | R6: 0.16446625 | S6: -0.62641861 | T6: 0.31366906
B7: 2019Q3 | D7: 664170.11 | F7: 53435 | G7: 61.23021 | H7: 63.771136 | I7: 3.9844444 | J7: 31.677531 | K7: 640.82055 | M7: 0.78069578 | O7: 0.55324514 | P7: 0.05076133 | Q7: 0.034552109 | R7: 0.016203704 | S7: -0.62740115 | T7: 0.80781819
B8: 2019Q4 | D8: 667414.56 | F8: 53475 | G8: 61.215992 | H8: 63.761492 | I8: 3.9922222 | J8: 31.627531 | K8: 644.63621 | M8: 1.137853 | O8: 0.47725522 | P8: -0.038760296 | Q8: -0.00636812 | R8: -0.032394285 | S8: -0.62838678 | T8: 1.3332551
B9: 2020Q1 | D9: 652180 | F9: 53515 | G9: 61.195265 | H9: 63.745068 | I9: 4 | J9: 31.30912 | K9: 636.0676 | M9: -1.2900193 | O9: 0.40149341 | P9: -0.078345781 | Q9: -0.0459637 | R9: -0.032396908 | S9: -1.4740349 | T9: -0.13562666
B10: 2020Q2 | D10: 522347.25 | F10: 53555 | G10: 60.85331 | H10: 63.720743 | I10: 4.5 | J10: 26.205522 | K10: 611.62084 | M10: -21.066135 | O10: 0.32595867 | P10: -0.63251419 | Q10: -0.087987404 | R10: -0.54500642 | S10: -17.404473 | T10: -4.1373967
B11: 2020Q3 | D11: 616029.42 | F11: 53618 | G11: 60.83121 | H11: 63.697602 | I11: 4.5 | J11: 30.60767 | K11: 617.06955 | M11: -7.2482472 | O11: 0.34247216 | P11: -0.65163928 | Q11: -0.11530842 | R11: -0.53695003 | S11: -3.3773511 | T11: -3.7063421
B12: 2020Q4 | D12: 624312.06 | F12: 53692 | G12: 60.809885 | H12: 63.675272 | I12: 4.5 | J12: 31.123036 | K12: 614.3785 | M12: -6.45813 | O12: 0.4057971 | P12: -0.66340051 | Q12: -0.1352234 | R12: -0.52889234 | S12: -1.5951152 | T12: -4.6937651
B13: 2021Q1 | D13: 609814.64 | F13: 53767 | G13: 60.78923 | H13: 63.653644 | I13: 4.5 | J13: 30.45 | K13: 612.72853 | M13: -6.4959614 | O13: 0.47089601 | P13: -0.66350722 | Q13: -0.14342089 | R13: -0.52083333 | S13: -2.7439915 | T13: -3.6692748
B14: 2021Q2 | D14: 645942.3 | F14: 53842 | G14: 60.899 | H14: 63.635319 | I14: 4.3 | J14: 31.3 | K14: 629.3874 | M14: 23.661472 | O14: 0.53589768 | P14: 0.07508318 | Q14: -0.13406014 | R14: 0.20942408 | S14: 19.440475 | T14: 2.9048321
B15: 2021Q3 | D15: 655412.17 | F15: 53949 | G15: 61.010675 | H15: 63.619056 | I15: 4.1 | J15: 31.39 | K15: 634.35732 | M15: 6.3929979 | O15: 0.61733 | P15: 0.29502142 | Q15: -0.12331022 | R15: 0.41884817 | S15: 2.5559933 | T15: 2.8015912
B16: 2021Q4 | D16: 662998.81 | F16: 54073 | G16: 61.036931 | H16: 63.601541 | I16: 4.0323077 | J16: 31.51 | K16: 637.51615 | M16: 6.1967003 | O16: 0.70960292 | P16: 0.37337121 | Q16: -0.11579182 | R16: 0.48973017 | S16: 1.2433365 | T16: 3.7660246
... B57: 2032Q1 | D57: 777400.28 | F57: 58574.635 | G57: 60.601175 | H57: 63.218417 | I57: 4.14 | J57: 31.674836 | K57: 691.41642 | M57: 1.4787509 | O57: 0.55591985 | P57: -0.073369624 | Q57: -0.073369585 | R57: 0 | S57: -0.1051406 | T57: 1.0981216
B58: 2019 | D58: 2654040.9 | F58: 53398 | G58: 61.232528 | H58: 63.770967 | I58: 3.9805556 | J58: 31.702531 | K58: 640.1016 | M58: 0.73971407 | O58: 0.54984371 | P58: 0.17714795 | Q58: 0.04732672 | R58: 0.12980057 | S58: -0.65026573 | T58: 0.66642398
B59: 2020 | D59: 2414868.7 | F59: 53595 | G59: 60.922417 | H59: 63.709671 | I59: 4.375 | J59: 29.811337 | K59: 619.78412 | M59: -9.0116237 | O59: 0.36892768 | P59: -0.50644842 | Q59: -0.096118432 | R59: -0.41079642 | S59: -5.9654372 | T59: -3.1741018
B60: 2021 | D60: 2574167.9 | F60: 53907.75 | G60: 60.933959 | H60: 63.62739 | I60: 4.2330769 | J60: 31.1625 | K60: 628.49735 | M60: 6.596598 | O60: 0.58354324 | P60: 0.01894512 | Q60: -0.12915004 | R60: 0.14841629 | S60: 4.5323802 | T60: 1.4058485
B61: 2022 | D61: 2707503.6 | F61: 54407 | G61: 60.990597 | H61: 63.571093 | I61: 4.0592308 | J61: 31.7248 | K61: 642.95913 | M61: 5.1797571 | O61: 0.92611916 | P61: 0.092949524 | Q61: -0.088479102 | R61: 0.18153048 | S61: 1.8044135 | T61: 2.3010095
B62: 2023 | D62: 2746003.2 | F62: 55044.5 | G62: 60.935345 | H62: 63.542034 | I62: 4.1023077 | J62: 31.8874 | K62: 641.86358 | M62: 1.4219617 | O62: 1.1717242 | P62: -0.090590317 | Q62: -0.04571059 | R62: -0.044899497 | S62: 0.51253012 | T62: -0.17039206
B63: 2024 | D63: 2789982.5 | F63: 55690 | G63: 60.901095 | H63: 63.529506 | I63: 4.1373077 | J63: 31.942845 | K63: 643.81698 | M63: 1.6015759 | O63: 1.1726876 | P63: -0.056207649 | Q63: -0.019716612 | R63: -0.036497229 | S63: 0.1738802 | T63: 0.30433244
B64: 2025 | D64: 2838487 | F64: 56278.5 | G64: 60.885074 | H64: 63.514578 | I64: 4.14 | J64: 31.952712 | K64: 648.13641 | M64: 1.7385224 | O64: 1.0567427 | P64: -0.026305808 | Q64: -0.023497818 | R64: -0.0028085042 | S64: 0.030888548 | T64: 0.67090949
B65: 2026 | D65: 2883721.7 | F65: 56772.567 | G65: 60.826533 | H65: 63.453509 | I65: 4.14 | J65: 31.936205 | K65: 653.69855 | M65: 1.5936185 | O65: 0.87789595 | P65: -0.096150207 | Q65: -0.096150172 | R65: 0 | S65: -0.051661747 | T65: 0.85817397
B66: 2027 | D66: 2911848.8 | F66: 57081.701 | G66: 60.764147 | H66: 63.388428 | I66: 4.14 | J66: 31.89628 | K66: 657.99745 | M66: 0.97537618 | O66: 0.5445144 | P66: -0.10256478 | Q66: -0.10256483 | R66: 0 | S66: -0.12501499 | T66: 0.65762723
B67: 2028 | D67: 2949679.8 | F67: 57397.534 | G67: 60.71549 | H67: 63.337669 | I67: 4.14 | J67: 31.840388 | K67: 664.57351 | M67: 1.2992091 | O67: 0.55329964 | P67: -0.080075057 | Q67: -0.080075057 | R67: 0 | S67: -0.17522796 | T67: 0.99940588
B68: 2029 | D68: 2992484.1 | F68: 57720.356 | G68: 60.686796 | H68: 63.307736 | I68: 4.14 | J68: 31.786241 | K68: 671.90598 | M68: 1.4511488 | O68: 0.56243091 | P68: -0.047260016 | Q68: -0.047259992 | R68: 0 | S68: -0.17005809 | T68: 1.103334
B69: 2030 | D69: 3036522.4 | F69: 58047.952 | G69: 60.6685 | H69: 63.28865 | I69: 4.14 | J69: 31.734761 | K69: 679.2507 | M69: 1.4716314 | O69: 0.56755796 | P69: -0.030147332 | Q69: -0.030147336 | R69: 0 | S69: -0.16195925 | T69: 1.0931176
B70: 2031 | D70: 3081197.8 | F70: 58372.274 | G70: 60.629226 | H70: 63.24768 | I70: 4.14 | J70: 31.695053 | K70: 686.71793 | M70: 1.4712678 | O70: 0.55871394 | P70: -0.064736436 | Q70: -0.064736437 | R70: 0 | S70: -0.12512283 | T70: 1.099334
B71: 2019-20 | D71: 2645517.7 | F71: 53451.5 | G71: 61.220533 | H71: 63.763639 | I71: 3.9883333 | J71: 31.585428 | K71: 639.88564 | M71: 0.28479056 | O71: 0.5067504 | P71: 0.041841335 | Q71: 0.01294146 | R71: 0.028911094 | S71: -0.83856121 | T71: 0.57953225
B72: 2020-21 | D72: 2372503.4 | F72: 53658 | G72: 60.820909 | H72: 63.686815 | I72: 4.5 | J72: 29.596557 | K72: 613.94936 | M72: -10.319883 | O72: 0.38633153 | P72: -0.65276228 | Q72: -0.1204814 | R72: -0.53292135 | S72: -6.2968008 | T72: -4.0532682
B73: 2021-22 | D73: 2633165 | F73: 54015.5 | G73: 60.990323 | H73: 63.610353 | I73: 4.1188462 | J73: 31.454625 | K73: 635.22865 | M73: 10.986774 | O73: 0.66625666 | P73: 0.27854615 | Q73: -0.12005983 | R73: 0.39911398 | S73: 6.2779871 | T73: 3.4659698
B74: 2022-23 | D74: 2723437.5 | F74: 54557.25 | G74: 60.975749 | H74: 63.562752 | I74: 4.07 | J74: 31.782943 | K74: 643.94759 | M74: 3.4282889 | O74: 1.0029529 | P74: -0.023895594 | Q74: -0.07483225 | R74: 0.050944479 | S74: 1.0437827 | T74: 1.3725664
B75: 2023-24 | D75: 2753328.2 | F75: 55208.25 | G75: 60.92402 | H75: 63.53736 | I75: 4.1130769 | J75: 31.907253 | K75: 641.38353 | M75: 1.0975384 | O75: 1.193242 | P75: -0.084835121 | Q75: -0.039947562 | R75: -0.044904538 | S75: 0.39112043 | T75: -0.3981783
B76: 2024-25 | D76: 2805192.2 | F76: 55842.75 | G76: 60.896875 | H76: 63.526888 | I76: 4.14 | J76: 31.949099 | K76: 645.47383 | M76: 1.883682 | O76: 1.1492848 | P76: -0.04455562 | Q76: -0.016481692 | R76: -0.028077944 | S76: 0.13115165 | T76: 0.63773112
B77: 2025-26 | D77: 2848007.1 | F77: 56416.75 | G77: 60.875668 | H77: 63.504766 | I77: 4.14 | J77: 31.950064 | K77: 648.86819 | M77: 1.5262752 | O77: 1.0278863 | P77: -0.034823585 | Q77: -0.03482357 | R77: 0 | S77: 0.0030176413 | T77: 0.52587073
B78: 2026-27 | D78: 2892362.1 | F78: 56860.133 | G78: 60.808681 | H78: 63.434885 | I78: 4.14 | J78: 31.928803 | K78: 654.99248 | M78: 1.5574041 | O78: 0.78590729 | P78: -0.11003953 | Q78: -0.11003953 | R78: 0 | S78: -0.066544267 | T78: 0.94384216
B79: 2027-28 | D79: 2919815.6 | F79: 57159.092 | G79: 60.75113 | H79: 63.374849 | I79: 4.14 | J79: 31.883018 | K79: 659.31941 | M79: 0.94917023 | O79: 0.52577871 | P79: -0.094642285 | Q79: -0.094642316 | R79: 0 | S79: -0.1433973 | T79: 0.660607
B80: 2028-29 | D80: 2960323.9 | F80: 57477.662 | G80: 60.705963 | H80: 63.327731 | I80: 4.14 | J80: 31.826371 | K80: 666.43966 | M80: 1.3873595 | O80: 0.55733911 | P80: -0.07434837 | Q80: -0.074348348 | R80: 0 | S80: -0.17766889 | T80: 1.0799403
B81: 2029-30 | D81: 3003413.2 | F81: 57802.148 | G81: 60.683184 | H81: 63.303969 | I81: 4.14 | J81: 31.772729 | K81: 673.73209 | M81: 1.4555607 | O81: 0.56454349 | P81: -0.037522961 | Q81: -0.037522952 | R81: 0 | S81: -0.16854571 | T81: 1.0942359
B82: 2030-31 | D82: 3047613.6 | F82: 58129.277 | G82: 60.660053 | H82: 63.279839 | I82: 4.14 | J82: 31.723771 | K82: 681.10863 | M82: 1.4716728 | O82: 0.56594609 | P82: -0.038117644 | Q82: -0.038117681 | R82: 0 | S82: -0.15408786 | T82: 1.0948783
B83: 2031-32 | D83: 3092526.1 | F83: 58453.231 | G83: 60.618102 | H83: 63.236075 | I83: 4.14 | J83: 31.686719 | K83: 688.59546 | M83: 1.4736922 | O83: 0.55729925 | P83: -0.069158363 | Q83: -0.069158329 | R83: 0 | S83: -0.1167983 | T83: 1.0992125
B84: Definitions:
B85: OBR estimate of potential population, based on LFS household population, all aged 16 and over (ONS identifier: MGSL)
B86: OBR estimate of the potential participation rate, on the same basis as the LFS participation rate, all aged 16 and over (ONS identifier: MGWG)
B87: OBR estimate of the equilibirum unemployment rate, on the same basis as the ILO unemployment rate, all aged 16 and over (ONS identifier: MGSX)
B88: OBR estimate of the potential employment rate, on the same basis as the LFS employment rate, all aged 16 and over (ONS identifier: MGSR)
B89: OBR estimate of potential average hours, on the same basis as LFS average (mean) actual weekly hours worked, all workers (ONS identifier: YBUV)
B90: OBR estimate of potential output per hour, on the same basis as GDP (ONS identifier: ABMI) divided by total weekly hours worked (ONS identifier: YBUS)
B91: Notes:
B92: 1 Potential output can be calculated by multiplying potential population, productivity, average hours and the employment rate divided by 100.
B93: 2 The potential employment rate is determined by multiplying the potential participation rate by 1 minus the equilibrium unemployment rate divided by 100.
B94: 3 Potential output growth is approximately equal to the sum of the growth rates of potential population, the employment rate, average hours and productivity.

Sheet 1.16
A1: Back to contents
B2: 1.16 Housing market
C3: House price index (Jan 2023 = 100) | D3: House price index (per cent change on a year earlier) | E3: Residential property transactions (000s, seasonally adjusted) | F3: Private enterprise housing starts, UK (seasonally adjusted) | G3: Private enterprise housing completions, UK (seasonally adjusted) | H3: Housing stock, UK (000s) | I3: Net additions to the housing stock, UK (000s) | J3: Turnover rate
B4: 2008Q1 | C4: 65.7 | D4: 3.7914692 | E4: 294.88 | F4: 37646.062 | G4: 43816.48 | H4: 27047.075 | I4: 68.735 | J4: =(E4/H4)*100 -> 1.0902473
B5: 2008Q2 | C5: 64.2 | D5: -0.61919505 | E5: 259.33 | F5: 32515.886 | G5: 40202.701 | H5: 27101.587 | I5: 54.511625 | J5: =(E5/H5)*100 -> 0.95688123
B6: 2008Q3 | C6: 61 | D6: -7.1537291 | E6: 187.81 | F6: 20509.624 | G6: 38358.193 | H6: 27156.099 | I6: 54.511625 | J6: =(E6/H6)*100 -> 0.69159418
B7: 2008Q4 | C7: 57.6 | D7: -13.383459 | E7: 174.9 | F7: 18415.762 | G7: 33689.068 | H7: 27210.61 | I7: 54.511625 | J7: =(E7/H7)*100 -> 0.64276397
B8: 2009Q1 | C8: 55.4 | D8: -15.677321 | E8: 170.84 | F8: 16897.559 | G8: 32836.227 | H8: 27265.122 | I8: 54.511625 | J8: =(E8/H8)*100 -> 0.62658806
B9: 2009Q2 | C9: 55.4 | D9: -13.707165 | E9: 193.27 | F9: 19070.503 | G9: 30586.398 | H9: 27310.891 | I9: 45.769125 | J9: =(E9/H9)*100 -> 0.7076664
B10: 2009Q3 | C10: 56.8 | D10: -6.8852459 | E10: 223.68 | F10: 24742.769 | G10: 28973.124 | H10: 27356.66 | I10: 45.769125 | J10: =(E10/H10)*100 -> 0.81764367
B11: 2009Q4 | C11: 58.7 | D11: 1.9097222 | E11: 259.75 | F11: 25176.527 | G11: 29457.13 | H11: 27402.429 | I11: 45.769125 | J11: =(E11/H11)*100 -> 0.94790866
B12: 2010Q1 | C12: 59.7 | D12: 7.7617329 | E12: 216.23 | F12: 26952.172 | G12: 27180.543 | H12: 27448.198 | I12: 45.769125 | J12: =(E12/H12)*100 -> 0.78777483
B13: 2010Q2 | C13: 60 | D13: 8.3032491 | E13: 229.88 | F13: 28636.523 | G13: 26610.126 | H13: 27489.534 | I13: 41.335 | J13: =(E13/H13)*100 -> 0.83624555
B14: 2010Q3 | C14: 60 | D14: 5.6338028 | E14: 227.02 | F14: 26514 | G14: 27180.728 | H14: 27530.869 | I14: 41.335 | J14: =(E14/H14)*100 -> 0.82460166
B15: 2010Q4 | C15: 59.5 | D15: 1.362862 | E15: 210.92 | F15: 23507.069 | G15: 24621.632 | H15: 27572.203 | I15: 41.335 | J15: =(E15/H15)*100 -> 0.76497332
... B100: 2032Q1 | C100: 121.04569 | D100: 2.7477919 | E100: 334.04921 | F100: 39454.241 | G100: 38650.57 | H100: 32576.151 | I100: 67.88433 | J100: =(E100/H100)*100 -> 1.025441
B101: 2008 | C101: 62.125 | D101: -4.4598231 | E101: =SUM(E4:E7) -> 916.92 | F101: 109087.33 | G101: 156066.44 | H101: 27210.61 | I101: 232.26988 | J101: =(E101/H101)*100 -> 3.3697149
B102: 2009 | C102: 56.575 | D102: -8.9336016 | E102: =SUM(E8:E11) -> 847.54 | F102: 85887.358 | G102: 121852.88 | H102: 27402.429 | I102: 191.819 | J102: =(E102/H102)*100 -> 3.0929374
B103: 2010 | C103: 59.8 | D103: 5.7003977 | E103: =SUM(E12:E15) -> 884.05 | F103: 105609.76 | G103: 105593.03 | H103: 27572.203 | I103: 169.77413 | J103: =(E103/H103)*100 -> 3.2063088
B104: 2011 | C104: 58.925 | D104: -1.4632107 | E104: =SUM(E16:E19) -> 882.67 | F104: 107643.83 | G104: 105403.35 | H104: 27734.932 | I104: 162.7285 | J104: =(E104/H104)*100 -> 3.1825209
B105: 2012 | C105: 59.2 | D105: 0.46669495 | E105: =SUM(E20:E23) -> 931.28 | F105: 99580.543 | G105: 107988.25 | H105: 27892.038 | I105: 157.10563 | J105: =(E105/H105)*100 -> 3.338874
B106: 2013 | C106: 60.7 | D106: 2.5337838 | E106: =SUM(E24:E27) -> 1066.97 | F106: 118616.58 | G106: 106530.36 | H106: 28056.433 | I106: 164.3955 | J106: =(E106/H106)*100 -> 3.8029424
B107: 2014 | C107: 65.55 | D107: 7.9901153 | E107: =SUM(E28:E31) -> 1222.9 | F107: 135006.99 | G107: 114868.13 | H107: 28251.625 | I107: 195.19162 | J107: =(E107/H107)*100 -> 4.3286006
B108: 2015 | C108: 69.475 | D108: 5.9877956 | E108: =SUM(E32:E35) -> 1226.14 | F108: 146064.24 | G108: 134073.16 | H108: 28473.502 | I108: 221.87775 | J108: =(E108/H108)*100 -> 4.3062493
B109: 2016 | C109: 74.35 | D109: 7.0169126 | E109: =SUM(E36:E39) -> 1232.49 | F109: 153428.43 | G109: 139344.68 | H109: 28723.927 | I109: 250.42413 | J109: =(E109/H109)*100 -> 4.2908131
B110: 2017 | C110: 77.725 | D110: 4.539341 | E110: =SUM(E40:E43) -> 1223.43 | F110: 160771.54 | G110: 158102.64 | H110: 28986.417 | I110: 262.49013 | J110: =(E110/H110)*100 -> 4.2207011
B111: 2018 | C111: 80.225 | D111: 3.2164683 | E111: =SUM(E44:E47) -> 1189.36 | F111: 166237.44 | G111: 160946.46 | H111: 29266.56 | I111: 280.143 | J111: =(E111/H111)*100 -> 4.0638873
B112: 2019 | C112: 81.025 | D112: 0.99719539 | E112: =SUM(E48:E51) -> 1176.6 | F112: 152347.42 | G112: 172140.12 | H112: 29551.843 | I112: 285.28375 | J112: =(E112/H112)*100 -> 3.9814775
B113: 2020 | C113: 83.325 | D113: 2.8386301 | E113: =SUM(E52:E55) -> 1037.39 | F113: 126537.01 | G113: 141329.18 | H113: 29810.804 | I113: 258.96025 | J113: =(E113/H113)*100 -> 3.4799129
B114: 2021 | C114: 90.125 | D114: 8.1608161 | E114: =SUM(E56:E59) -> 1482.4 | F114: 169748.75 | G114: 169061.14 | H114: 30076.128 | I114: 265.32475 | J114: =(E114/H114)*100 -> 4.9288259
B115: 2022 | C115: 98.475 | D115: 9.2649098 | E115: =SUM(E60:E63) -> 1264.81 | F115: 167629.33 | G115: 172386.73 | H115: 30346.035 | I115: 269.906 | J115: =(E115/H115)*100 -> 4.1679581
B116: 2023 | C116: 98.825 | D116: 0.35542016 | E116: =SUM(E64:E67) -> 1023.16 | F116: 132112.56 | G116: 149211.01 | H116: 30603.947 | I116: 257.91225 | J116: =(E116/H116)*100 -> 3.3432289
B117: 2024 | C117: 99.525 | D117: 0.70832279 | E117: =SUM(E68:E71) -> 1094.78 | F117: 96980.07 | G117: 139211.72 | H117: 30846.545 | I117: 242.598 | J117: =(E117/H117)*100 -> 3.5491171
B118: 2025 | C118: 102.15 | D118: 2.6375283 | E118: =SUM(E72:E75) -> 1215.04 | F118: 115014.15 | G118: 127250.29 | H118: 31076.572 | I118: 230.02755 | J118: =(E118/H118)*100 -> 3.9098263
B119: 2026 | C119: 104.28381 | D119: 2.0888973 | E119: =SUM(E76:E79) -> 1185.679 | F119: 124572.92 | G119: 121013.63 | H119: 31300.717 | I119: 224.14456 | J119: =(E119/H119)*100 -> 3.7880252
B120: 2027 | C120: 106.82338 | D120: 2.4352542 | E120: =SUM(E80:E83) -> 1196.6641 | F120: 124525.67 | G120: 121752.96 | H120: 31520.418 | I120: 219.70077 | J120: =(E120/H120)*100 -> 3.7964729
B121: 2028 | C121: 109.79131 | D121: 2.7783457 | E121: =SUM(E84:E87) -> 1225.9737 | F121: 136792.83 | G121: 125338.37 | H121: 31744.483 | I121: 224.06571 | J121: =(E121/H121)*100 -> 3.8620054
B122: 2029 | C122: 112.81091 | D122: 2.7503135 | E122: =SUM(E88:E91) -> 1261.2465 | F122: 151461.71 | G122: 135888.82 | H122: 31984.773 | I122: 240.28985 | J122: =(E122/H122)*100 -> 3.9432716
B123: 2030 | C123: 115.91072 | D123: 2.7477919 | E123: =SUM(E92:E95) -> 1295.0056 | F123: 155408.32 | G123: 146264.84 | H123: 32241.324 | I123: 256.55068 | J123: =(E123/H123)*100 -> 4.0166019
B124: 2031 | C124: 119.09571 | D124: 2.7477919 | E124: =SUM(E96:E99) -> 1327.2619 | F124: 157243.42 | G124: 152238.89 | H124: 32508.267 | I124: 266.94267 | J124: =(E124/H124)*100 -> 4.0828442
B125: 2008-09 | C125: 59.55 | D125: -9.2571429 | E125: =SUM(E5:E8) -> 792.88 | F125: 88338.832 | G125: 145086.19 | H125: 27265.122 | I125: 218.0465 | J125: =(E125/H125)*100 -> 2.9080376
B126: 2009-10 | C126: 57.65 | D126: -3.1905961 | E126: =SUM(E9:E12) -> 892.93 | F126: 95941.971 | G126: 116197.2 | H126: 27448.198 | I126: 183.0765 | J126: =(E126/H126)*100 -> 3.2531461
B127: 2010-11 | C127: 59.675 | D127: 3.5125759 | E127: =SUM(E13:E16) -> 876.23 | F127: 104630.79 | G127: 104075.97 | H127: 27613.538 | I127: 165.34 | J127: =(E127/H127)*100 -> 3.1731898
B128: 2011-12 | C128: 58.875 | D128: -1.3405949 | E128: =SUM(E17:E20) -> 915.94 | F128: 107000.1 | G128: 109073.48 | H128: 27775.396 | I128: 161.858 | J128: =(E128/H128)*100 -> 3.2976667
B129: 2012-13 | C129: 59.375 | D129: 0.8492569 | E129: =SUM(E21:E24) -> 929.27 | F129: 100998.96 | G129: 103153.22 | H129: 27930.918 | I129: 155.5215 | J129: =(E129/H129)*100 -> 3.3270299
B130: 2013-14 | C130: 61.65 | D130: 3.8315789 | E130: =SUM(E25:E28) -> 1138.39 | F130: 128050.22 | G130: 110206.99 | H130: 28098.271 | I130: 167.3535 | J130: =(E130/H130)*100 -> 4.0514592
B131: 2014-15 | C131: 66.625 | D131: 8.0697486 | E131: =SUM(E29:E32) -> 1199.47 | F131: 137795.02 | G131: 118892.46 | H131: 28302.743 | I131: 204.471 | J131: =(E131/H131)*100 -> 4.2379992
B132: 2015-16 | C132: 70.825 | D132: 6.30394 | E132: =SUM(E33:E36) -> 1325.54 | F132: 142496.55 | G132: 135511.01 | H132: 28530.423 | I132: 227.68 | J132: =(E132/H132)*100 -> 4.6460581
B133: 2016-17 | C133: 75.15 | D133: 6.1066008 | E133: =SUM(E37:E40) -> 1152.15 | F133: 158353.09 | G133: 145848.29 | H133: 28788.428 | I133: 258.0055 | J133: =(E133/H133)*100 -> 4.0021289
B134: 2017-18 | C134: 78.525 | D134: 4.491018 | E134: =SUM(E41:E44) -> 1207.5 | F134: 161118 | G134: 155817.78 | H134: 29052.413 | I134: 263.985 | J134: =(E134/H134)*100 -> 4.1562813
B135: 2018-19 | C135: 80.525 | D135: 2.5469596 | E135: =SUM(E45:E48) -> 1190.43 | F135: 164142.03 | G135: 165308.72 | H135: 29337.942 | I135: 285.529 | J135: =(E135/H135)*100 -> 4.0576466
B136: 2019-20 | C136: 81.375 | D136: 1.0555728 | E136: =SUM(E49:E52) -> 1169.9 | F136: 147465.29 | G136: 168805.28 | H136: 29623.144 | I136: 285.202 | J136: =(E136/H136)*100 -> 3.949277
B137: 2020-21 | C137: 84.9 | D137: 4.3317972 | E137: =SUM(E53:E56) -> 1189.32 | F137: 136433.75 | G137: 149703.95 | H137: 29873.357 | I137: 250.213 | J137: =(E137/H137)*100 -> 3.9812064
B138: 2021-22 | C138: 91.925 | D138: 8.2744405 | E138: =SUM(E57:E60) -> 1375.48 | F138: 167010.14 | G138: 165672.74 | H138: 30143.719 | I138: 270.362 | J138: =(E138/H138)*100 -> 4.5630733
B139: 2022-23 | C139: 99.45 | D139: 8.1860212 | E139: =SUM(E61:E64) -> 1208.09 | F139: 158996.17 | G139: 166227.61 | H139: 30413.473 | I139: 269.754 | J139: =(E139/H139)*100 -> 3.9722198
B140: 2023-24 | C140: 98.5 | D140: -0.9552539 | E140: =SUM(E65:E68) -> 1000.63 | F140: 121020.85 | G140: 145495.59 | H140: 30667.438 | I140: 253.965 | J140: =(E140/H140)*100 -> 3.2628418
B141: 2024-25 | C141: 100.525 | D141: 2.0558376 | E141: =SUM(E69:E72) -> 1221.02 | F141: 102266.91 | G141: 137570.4 | H141: 30906.247 | I141: 238.809 | J141: =(E141/H141)*100 -> 3.9507223
B142: 2025-26 | C142: 102.425 | D142: 1.8900771 | E142: =SUM(E73:E76) -> 1139.76 | F142: 119601.45 | G142: 126960.78 | H142: 31135.389 | I142: 229.14162 | J142: =(E142/H142)*100 -> 3.6606577
B143: 2026-27 | C143: 104.83597 | D143: 2.3538911 | E143: =SUM(E77:E80) -> 1180.0409 | F143: 124590.8 | G143: 119170.04 | H143: 31356.58 | I143: 221.19114 | J143: =(E143/H143)*100 -> 3.7632959
B144: 2027-28 | C144: 107.57037 | D144: 2.6082637 | E144: =SUM(E81:E84) -> 1203.9533 | F144: 125663.87 | G144: 122314.98 | H144: 31575.518 | I144: 218.93868 | J144: =(E144/H144)*100 -> 3.8129327
B145: 2028-29 | C145: 110.54008 | D145: 2.7607103 | E145: =SUM(E85:E88) -> 1234.6565 | F145: 141684.78 | G145: 127361.1 | H145: 31802.76 | I145: 227.24167 | J145: =(E145/H145)*100 -> 3.8822308
B146: 2029-30 | C146: 113.57749 | D146: 2.7477919 | E146: =SUM(E89:E92) -> 1269.5718 | F146: 153070.05 | G146: 138864.86 | H146: 32047.618 | I146: 244.85814 | J146: =(E146/H146)*100 -> 3.9615169
B147: 2030-31 | C147: 116.69836 | D147: 2.7477919 | E147: =SUM(E93:E96) -> 1303.6307 | F147: 155908.9 | G147: 148115.42 | H147: 32307.243 | I147: 259.62442 | J147: =(E147/H147)*100 -> 4.0351037
B148: 2031-32 | C148: 119.90499 | D148: 2.7477919 | E148: =SUM(E97:E100) -> 1332.1467 | F148: 157537.86 | G148: 153257.13 | H148: 32576.151 | I148: 268.90821 | J148: =(E148/H148)*100 -> 4.0893313
B149: Notes:
B150: Seasonally adjusted ONS House Price Index (House Price Index Statistical Bulletin)
B151: Number of residential property transaction completions with value £40,000 or above, seasonally adjusted (HMRC UK Property Transaction Statistics)
B152: Number of private enterprise housing starts and completions, seasonally adjusted OBR estimates based on ONS, House building, UK: permanent dwellings started and completed by country.
B153: Net additions are changes in the UK housing stock which are OBR estimates based on housing stock data from DLUHC, StatsWales, Scottish Government and Northern Ireland Department for communities. Annual net additions are calculated as the change in the average size of the stock between adjacent years.
B154: Turnover rate is calculated as the number of residential property transactions divided by the stock of dwellings.

Sheet 1.17
A1: Back to contents
B2: 1.17 Household debt servicing costs
C3: Household debt servicing costs (rolling four quarter sum, £bn) | D3: Household disposable income (rolling four quarter sum, £bn) | E3: Household debt servicing costs (per cent of household disposable income, rolling four quarter sum)
B4: 2008Q1 | C4: 96.854 | D4: 996.082 | E4: =100*(C4/D4) -> 9.7234967
B5: 2008Q2 | C5: 98.089 | D5: 1007.976 | E5: =100*(C5/D5) -> 9.7312833
B6: 2008Q3 | C6: 98.813 | D6: 1014.776 | E6: =100*(C6/D6) -> 9.7374199
B7: 2008Q4 | C7: 98.277 | D7: 1024.014 | E7: =100*(C7/D7) -> 9.5972321
B8: 2009Q1 | C8: 92.716 | D8: 1030.885 | E8: =100*(C8/D8) -> 8.9938257
B9: 2009Q2 | C9: 85.935 | D9: 1038.39 | E9: =100*(C9/D9) -> 8.2757923
B10: 2009Q3 | C10: 78.572 | D10: 1045.223 | E10: =100*(C10/D10) -> 7.5172475
B11: 2009Q4 | C11: 71.739 | D11: 1050.092 | E11: =100*(C11/D11) -> 6.8316871
B12: 2010Q1 | C12: 68.903 | D12: 1057.303 | E12: =100*(C12/D12) -> 6.5168641
B13: 2010Q2 | C13: 67.543 | D13: 1060.716 | E13: =100*(C13/D13) -> 6.3676799
B14: 2010Q3 | C14: 66.02 | D14: 1065.915 | E14: =100*(C14/D14) -> 6.1937397
B15: 2010Q4 | C15: 64.618 | D15: 1070.069 | E15: =100*(C15/D15) -> 6.038676
... B100: 2032Q1 | C100: 125.52785 | D100: 2328.5204 | E100: =100*(C100/D100) -> 5.3908849
B101: 2008 | C101: =OFFSET(C$7,4*(ROW()-ROW(C$101)),0) -> 98.277 | D101: =OFFSET(D$7,4*(ROW()-ROW(D$101)),0) -> 1024.014 | E101: =100*(C101/D101) -> 9.5972321
B102: 2009 | C102: =OFFSET(C$7,4*(ROW()-ROW(C$101)),0) -> 71.739 | D102: =OFFSET(D$7,4*(ROW()-ROW(D$101)),0) -> 1050.092 | E102: =100*(C102/D102) -> 6.8316871
B103: 2010 | C103: =OFFSET(C$7,4*(ROW()-ROW(C$101)),0) -> 64.618 | D103: =OFFSET(D$7,4*(ROW()-ROW(D$101)),0) -> 1070.069 | E103: =100*(C103/D103) -> 6.038676
B104: 2011 | C104: =OFFSET(C$7,4*(ROW()-ROW(C$101)),0) -> 61.992 | D104: =OFFSET(D$7,4*(ROW()-ROW(D$101)),0) -> 1084.99 | E104: =100*(C104/D104) -> 5.713601
B105: 2012 | C105: =OFFSET(C$7,4*(ROW()-ROW(C$101)),0) -> 61.506 | D105: =OFFSET(D$7,4*(ROW()-ROW(D$101)),0) -> 1130.017 | E105: =100*(C105/D105) -> 5.442927
B106: 2013 | C106: =OFFSET(C$7,4*(ROW()-ROW(C$101)),0) -> 61.118 | D106: =OFFSET(D$7,4*(ROW()-ROW(D$101)),0) -> 1175.937 | E106: =100*(C106/D106) -> 5.1973873
B107: 2014 | C107: =OFFSET(C$7,4*(ROW()-ROW(C$101)),0) -> 59.843 | D107: =OFFSET(D$7,4*(ROW()-ROW(D$101)),0) -> 1217.891 | E107: =100*(C107/D107) -> 4.9136581
B108: 2015 | C108: =OFFSET(C$7,4*(ROW()-ROW(C$101)),0) -> 57.613 | D108: =OFFSET(D$7,4*(ROW()-ROW(D$101)),0) -> 1287.116 | E108: =100*(C108/D108) -> 4.4761311
B109: 2016 | C109: =OFFSET(C$7,4*(ROW()-ROW(C$101)),0) -> 57.529 | D109: =OFFSET(D$7,4*(ROW()-ROW(D$101)),0) -> 1312.733 | E109: =100*(C109/D109) -> 4.3823839
B110: 2017 | C110: =OFFSET(C$7,4*(ROW()-ROW(C$101)),0) -> 55.664 | D110: =OFFSET(D$7,4*(ROW()-ROW(D$101)),0) -> 1348.375 | E110: =100*(C110/D110) -> 4.1282284
B111: 2018 | C111: =OFFSET(C$7,4*(ROW()-ROW(C$101)),0) -> 56.661 | D111: =OFFSET(D$7,4*(ROW()-ROW(D$101)),0) -> 1402.614 | E111: =100*(C111/D111) -> 4.0396716
B112: 2019 | C112: =OFFSET(C$7,4*(ROW()-ROW(C$101)),0) -> 57.231 | D112: =OFFSET(D$7,4*(ROW()-ROW(D$101)),0) -> 1456.54 | E112: =100*(C112/D112) -> 3.9292433
... B124: 2031 | C124: =OFFSET(C$7,4*(ROW()-ROW(C$101)),0) -> 123.57823 | D124: =OFFSET(D$7,4*(ROW()-ROW(D$101)),0) -> 2312.5576 | E124: =100*(C124/D124) -> 5.3437904
B125: 2008-09 | C125: =OFFSET(C$8,4*(ROW()-ROW(C$125)),0) -> 92.716 | D125: =OFFSET(D$8,4*(ROW()-ROW(D$125)),0) -> 1030.885 | E125: =100*(C125/D125) -> 8.9938257
B126: 2009-10 | C126: =OFFSET(C$8,4*(ROW()-ROW(C$125)),0) -> 68.903 | D126: =OFFSET(D$8,4*(ROW()-ROW(D$125)),0) -> 1057.303 | E126: =100*(C126/D126) -> 6.5168641
B127: 2010-11 | C127: =OFFSET(C$8,4*(ROW()-ROW(C$125)),0) -> 63.977 | D127: =OFFSET(D$8,4*(ROW()-ROW(D$125)),0) -> 1071.456 | E127: =100*(C127/D127) -> 5.9710338
B128: 2011-12 | C128: =OFFSET(C$8,4*(ROW()-ROW(C$125)),0) -> 61.638 | D128: =OFFSET(D$8,4*(ROW()-ROW(D$125)),0) -> 1098.656 | E128: =100*(C128/D128) -> 5.6103093
B129: 2012-13 | C129: =OFFSET(C$8,4*(ROW()-ROW(C$125)),0) -> 61.301 | D129: =OFFSET(D$8,4*(ROW()-ROW(D$125)),0) -> 1134.597 | E129: =100*(C129/D129) -> 5.4028875
B130: 2013-14 | C130: =OFFSET(C$8,4*(ROW()-ROW(C$125)),0) -> 60.98 | D130: =OFFSET(D$8,4*(ROW()-ROW(D$125)),0) -> 1193.574 | E130: =100*(C130/D130) -> 5.1090255
B131: 2014-15 | C131: =OFFSET(C$8,4*(ROW()-ROW(C$125)),0) -> 59.192 | D131: =OFFSET(D$8,4*(ROW()-ROW(D$125)),0) -> 1228.019 | E131: =100*(C131/D131) -> 4.8201209
B132: 2015-16 | C132: =OFFSET(C$8,4*(ROW()-ROW(C$125)),0) -> 57.71 | D132: =OFFSET(D$8,4*(ROW()-ROW(D$125)),0) -> 1301.656 | E132: =100*(C132/D132) -> 4.4335831
B133: 2016-17 | C133: =OFFSET(C$8,4*(ROW()-ROW(C$125)),0) -> 56.865 | D133: =OFFSET(D$8,4*(ROW()-ROW(D$125)),0) -> 1314.003 | E133: =100*(C133/D133) -> 4.3276157
B134: 2017-18 | C134: =OFFSET(C$8,4*(ROW()-ROW(C$125)),0) -> 55.807 | D134: =OFFSET(D$8,4*(ROW()-ROW(D$125)),0) -> 1368.604 | E134: =100*(C134/D134) -> 4.0776587
B135: 2018-19 | C135: =OFFSET(C$8,4*(ROW()-ROW(C$125)),0) -> 56.903 | D135: =OFFSET(D$8,4*(ROW()-ROW(D$125)),0) -> 1410.868 | E135: =100*(C135/D135) -> 4.0331909
B136: 2019-20 | C136: =OFFSET(C$8,4*(ROW()-ROW(C$125)),0) -> 57.405 | D136: =OFFSET(D$8,4*(ROW()-ROW(D$125)),0) -> 1461.695 | E136: =100*(C136/D136) -> 3.9272899
... B148: 2031-32 | C148: =OFFSET(C$8,4*(ROW()-ROW(C$125)),0) -> 125.52785 | D148: =OFFSET(D$8,4*(ROW()-ROW(D$125)),0) -> 2328.5204 | E148: =100*(C148/D148) -> 5.3908849
B149: Definitions:
B150: Rolling four-quarter sum of total household interest payments excluding FISIM (ONS Economic Accounts, identifier: J4X3).
B151: Rolling four-quarter sum of household disposable income (ONS Economic Accounts, identifier: RPHQ).

Sheet 1.18
A1: Back to contents
B2: 1.18 Eligible rent growth assumptions
D3: 2025-26 | E3: 2026-27 | F3: 2027-28 | G3: 2028-29 | H3: 2023-30 | I3: 2030-31 | J3: 2031-32
B4: Private sector
B5: Local Housing Allowance | D5: 4.2 | E5: 3.2 | F5: 3.3 | G5: 3 | H5: 2.8 | I5: 2.7 | J5: 2.5
B6: Non-LHA Regulated | D6: 4 | E6: 4 | F6: 4 | G6: 4 | H6: 4 | I6: 4 | J6: 4
B7: Non-LHA Deregulated | D7: 4 | E7: 4 | F7: 4 | G7: 4 | H7: 4 | I7: 4 | J7: 4
B8: Social sector
B9: Local Authorities | D9: 7.5 | E9: 4.6 | F9: 4.9 | G9: 5.5 | H9: 3.9 | I9: 3.9 | J9: 3.7
B10: Registered Social Landlords | D10: 15.7 | E10: 7.5 | F10: 7.6 | G10: 7.9 | H10: 6.5 | I10: 6.6 | J10: 6.5
B11: Notes:
B12: The assumptions provided in this table cover only growth in the element of rent eligible for Housing Benefit and not overall market rents. The eligible rent is based on the amount paid by the tenant to occupy the property not including bills and some service charges. In many cases (mainly Private Rented Sector tenants), the amount of eligible rent is also influenced by the amount of maximum rent determined by LHA regulations, or by the Rent Officer.
B13: These figures now include compositional shifts, including the Move to UC, the increase in use of affordable tenancies and increases to Supported Housing caseloads.
B14: The assumptions provided in this table include the impact of social rent convergence. We assume that all cases in scope of convergence are below national formula rents for modelling purposes. Some cases may also converge earlier than is modelled, and therefore require smaller rent increases each financial year, decreasing the average rental growth.

Sheet 1.19
A1: Back to contents
B2: 1.19 CPI category inflation
C3: Year-on-year growth
C4: Food, beverages and tobacco | D4: Utilities | E4: Fuels | F4: Other tradables | G4: Other non-tradables
B5: 2019Q1 | C5: 2.0214771 | D5: 1.4659201 | E5: 1.4393743 | F5: 1.2593333 | G5: 2.4178554
B6: 2019Q2 | C6: 1.7955231 | D6: 10.208316 | E6: 2.6550462 | F6: 0.84902124 | G6: 2.6282253
B7: 2019Q3 | C7: 2.1017071 | D7: 6.3748501 | E7: -0.6403562 | F7: 1.1251883 | G7: 2.2752049
B8: 2019Q4 | C8: 1.8531285 | D8: -1.7742005 | E8: -1.7482827 | F8: 0.97742261 | G8: 2.1234754
B9: 2020Q1 | C9: 1.2639956 | D9: 4.846834 | E9: 1.4649606 | F9: 1.0504336 | G9: 2.163575
B10: 2020Q2 | C10: 1.688854 | D10: -6.1895401 | E10: -15.303965 | F10: 0.99744959 | G10: 1.674461
B11: 2020Q3 | C11: 0.86752929 | D11: -6.2414054 | E11: -11.537859 | F11: 1.5035672 | G11: 1.0338966
B12: 2020Q4 | C12: 0.34913717 | D12: -8.3639481 | E12: -9.8797258 | F12: 1.1508458 | G12: 1.5019713
B13: 2021Q1 | C13: 0.11016879 | D13: -8.3643673 | E13: -2.7039404 | F13: 0.46357518 | G13: 1.8839603
B14: 2021Q2 | C14: 0.018700858 | D14: 1.5022501 | E14: 17.418165 | F14: 1.7446102 | G14: 2.0224943
B15: 2021Q3 | C15: 0.71832198 | D15: 1.6504219 | E15: 17.888735 | F15: 2.4749144 | G15: 2.8687183
B16: 2021Q4 | C16: 2.8759178 | D16: 22.385759 | E16: 26.090298 | F16: 4.0110615 | G16: 3.8126264
... B57: 2032Q1 | C57: 2.1460174 | D57: 1.9263426 | E57: 1.9697181 | F57: 0.62218509 | G57: 3.0749153
B58: 2019 | C58: =AVERAGE(OFFSET(C$5,4*(ROW()-ROW(C$58)),0, 4, 1)) -> 1.942959 | D58: =AVERAGE(OFFSET(D$5,4*(ROW()-ROW(D$58)),0, 4, 1)) -> 4.0687215 | E58: =AVERAGE(OFFSET(E$5,4*(ROW()-ROW(E$58)),0, 4, 1)) -> 0.42644538 | F58: =AVERAGE(OFFSET(F$5,4*(ROW()-ROW(F$58)),0, 4, 1)) -> 1.0527414 | G58: =AVERAGE(OFFSET(G$5,4*(ROW()-ROW(G$58)),0, 4, 1)) -> 2.3611902
B59: 2020 | C59: =AVERAGE(OFFSET(C$5,4*(ROW()-ROW(C$58)),0, 4, 1)) -> 1.042379 | D59: =AVERAGE(OFFSET(D$5,4*(ROW()-ROW(D$58)),0, 4, 1)) -> -3.9870149 | E59: =AVERAGE(OFFSET(E$5,4*(ROW()-ROW(E$58)),0, 4, 1)) -> -8.8141474 | F59: =AVERAGE(OFFSET(F$5,4*(ROW()-ROW(F$58)),0, 4, 1)) -> 1.175574 | G59: =AVERAGE(OFFSET(G$5,4*(ROW()-ROW(G$58)),0, 4, 1)) -> 1.593476
B60: =B59+1 -> 2021 | C60: =AVERAGE(OFFSET(C$5,4*(ROW()-ROW(C$58)),0, 4, 1)) -> 0.93077736 | D60: =AVERAGE(OFFSET(D$5,4*(ROW()-ROW(D$58)),0, 4, 1)) -> 4.2935159 | E60: =AVERAGE(OFFSET(E$5,4*(ROW()-ROW(E$58)),0, 4, 1)) -> 14.673314 | F60: =AVERAGE(OFFSET(F$5,4*(ROW()-ROW(F$58)),0, 4, 1)) -> 2.1735403 | G60: =AVERAGE(OFFSET(G$5,4*(ROW()-ROW(G$58)),0, 4, 1)) -> 2.6469498
B61: =B60+1 -> 2022 | C61: =AVERAGE(OFFSET(C$5,4*(ROW()-ROW(C$58)),0, 4, 1)) -> 8.9202898 | D61: =AVERAGE(OFFSET(D$5,4*(ROW()-ROW(D$58)),0, 4, 1)) -> 63.38239 | E61: =AVERAGE(OFFSET(E$5,4*(ROW()-ROW(E$58)),0, 4, 1)) -> 29.537505 | F61: =AVERAGE(OFFSET(F$5,4*(ROW()-ROW(F$58)),0, 4, 1)) -> 6.5940991 | G61: =AVERAGE(OFFSET(G$5,4*(ROW()-ROW(G$58)),0, 4, 1)) -> 5.5466969
B62: =B61+1 -> 2023 | C62: =AVERAGE(OFFSET(C$5,4*(ROW()-ROW(C$58)),0, 4, 1)) -> 12.952135 | D62: =AVERAGE(OFFSET(D$5,4*(ROW()-ROW(D$58)),0, 4, 1)) -> 24.882015 | E62: =AVERAGE(OFFSET(E$5,4*(ROW()-ROW(E$58)),0, 4, 1)) -> -9.7436239 | F62: =AVERAGE(OFFSET(F$5,4*(ROW()-ROW(F$58)),0, 4, 1)) -> 6.2284153 | G62: =AVERAGE(OFFSET(G$5,4*(ROW()-ROW(G$58)),0, 4, 1)) -> 6.7987233
B63: 2024 | C63: =AVERAGE(OFFSET(C$5,4*(ROW()-ROW(C$58)),0, 4, 1)) -> 3.9877901 | D63: =AVERAGE(OFFSET(D$5,4*(ROW()-ROW(D$58)),0, 4, 1)) -> -18.543771 | E63: =AVERAGE(OFFSET(E$5,4*(ROW()-ROW(E$58)),0, 4, 1)) -> -4.9195893 | F63: =AVERAGE(OFFSET(F$5,4*(ROW()-ROW(F$58)),0, 4, 1)) -> 1.9475292 | G63: =AVERAGE(OFFSET(G$5,4*(ROW()-ROW(G$58)),0, 4, 1)) -> 5.5733578
B64: 2025 | C64: =AVERAGE(OFFSET(C$5,4*(ROW()-ROW(C$58)),0, 4, 1)) -> 4.5397139 | D64: =AVERAGE(OFFSET(D$5,4*(ROW()-ROW(D$58)),0, 4, 1)) -> 3.1209751 | E64: =AVERAGE(OFFSET(E$5,4*(ROW()-ROW(E$58)),0, 4, 1)) -> -4.1542922 | F64: =AVERAGE(OFFSET(F$5,4*(ROW()-ROW(F$58)),0, 4, 1)) -> 1.5786892 | G64: =AVERAGE(OFFSET(G$5,4*(ROW()-ROW(G$58)),0, 4, 1)) -> 5.1248604
B65: 2026 | C65: =AVERAGE(OFFSET(C$5,4*(ROW()-ROW(C$58)),0, 4, 1)) -> 2.8293805 | D65: =AVERAGE(OFFSET(D$5,4*(ROW()-ROW(D$58)),0, 4, 1)) -> -0.034465465 | E65: =AVERAGE(OFFSET(E$5,4*(ROW()-ROW(E$58)),0, 4, 1)) -> 21.39224 | F65: =AVERAGE(OFFSET(F$5,4*(ROW()-ROW(F$58)),0, 4, 1)) -> 1.07942 | G65: =AVERAGE(OFFSET(G$5,4*(ROW()-ROW(G$58)),0, 4, 1)) -> 3.9786845
B66: 2027 | C66: =AVERAGE(OFFSET(C$5,4*(ROW()-ROW(C$58)),0, 4, 1)) -> 4.6923588 | D66: =AVERAGE(OFFSET(D$5,4*(ROW()-ROW(D$58)),0, 4, 1)) -> 8.2450142 | E66: =AVERAGE(OFFSET(E$5,4*(ROW()-ROW(E$58)),0, 4, 1)) -> 6.1172018 | F66: =AVERAGE(OFFSET(F$5,4*(ROW()-ROW(F$58)),0, 4, 1)) -> 1.888084 | G66: =AVERAGE(OFFSET(G$5,4*(ROW()-ROW(G$58)),0, 4, 1)) -> 3.7097922
B67: 2028 | C67: =AVERAGE(OFFSET(C$5,4*(ROW()-ROW(C$58)),0, 4, 1)) -> 2.7379445 | D67: =AVERAGE(OFFSET(D$5,4*(ROW()-ROW(D$58)),0, 4, 1)) -> -8.5799117 | E67: =AVERAGE(OFFSET(E$5,4*(ROW()-ROW(E$58)),0, 4, 1)) -> -0.2948161 | F67: =AVERAGE(OFFSET(F$5,4*(ROW()-ROW(F$58)),0, 4, 1)) -> 1.2176667 | G67: =AVERAGE(OFFSET(G$5,4*(ROW()-ROW(G$58)),0, 4, 1)) -> 3.5390144
B68: 2029 | C68: =AVERAGE(OFFSET(C$5,4*(ROW()-ROW(C$58)),0, 4, 1)) -> 2.1021382 | D68: =AVERAGE(OFFSET(D$5,4*(ROW()-ROW(D$58)),0, 4, 1)) -> 2.0684552 | E68: =AVERAGE(OFFSET(E$5,4*(ROW()-ROW(E$58)),0, 4, 1)) -> 0.084345468 | F68: =AVERAGE(OFFSET(F$5,4*(ROW()-ROW(F$58)),0, 4, 1)) -> 0.75364527 | G68: =AVERAGE(OFFSET(G$5,4*(ROW()-ROW(G$58)),0, 4, 1)) -> 3.3330386
B69: 2030 | C69: =AVERAGE(OFFSET(C$5,4*(ROW()-ROW(C$58)),0, 4, 1)) -> 2.0945973 | D69: =AVERAGE(OFFSET(D$5,4*(ROW()-ROW(D$58)),0, 4, 1)) -> 2.4265007 | E69: =AVERAGE(OFFSET(E$5,4*(ROW()-ROW(E$58)),0, 4, 1)) -> 0.96903325 | F69: =AVERAGE(OFFSET(F$5,4*(ROW()-ROW(F$58)),0, 4, 1)) -> 0.69689734 | G69: =AVERAGE(OFFSET(G$5,4*(ROW()-ROW(G$58)),0, 4, 1)) -> 3.0829332
B70: 2031 | C70: =AVERAGE(OFFSET(C$5,4*(ROW()-ROW(C$58)),0, 4, 1)) -> 2.1847745 | D70: =AVERAGE(OFFSET(D$5,4*(ROW()-ROW(D$58)),0, 4, 1)) -> 1.8745738 | E70: =AVERAGE(OFFSET(E$5,4*(ROW()-ROW(E$58)),0, 4, 1)) -> 1.9871858 | F70: =AVERAGE(OFFSET(F$5,4*(ROW()-ROW(F$58)),0, 4, 1)) -> 0.61730447 | G70: =AVERAGE(OFFSET(G$5,4*(ROW()-ROW(G$58)),0, 4, 1)) -> 3.0685034
B71: 2019-20 | C71: =AVERAGE(OFFSET(C$6,4*(ROW()-ROW(C$71)),0, 4, 1)) -> 1.7535886 | D71: =AVERAGE(OFFSET(D$6,4*(ROW()-ROW(D$71)),0, 4, 1)) -> 4.91395 | E71: =AVERAGE(OFFSET(E$6,4*(ROW()-ROW(E$71)),0, 4, 1)) -> 0.43284196 | F71: =AVERAGE(OFFSET(F$6,4*(ROW()-ROW(F$71)),0, 4, 1)) -> 1.0005165 | G71: =AVERAGE(OFFSET(G$6,4*(ROW()-ROW(G$71)),0, 4, 1)) -> 2.2976201
B72: 2020-21 | C72: =AVERAGE(OFFSET(C$6,4*(ROW()-ROW(C$71)),0, 4, 1)) -> 0.75392232 | D72: =AVERAGE(OFFSET(D$6,4*(ROW()-ROW(D$71)),0, 4, 1)) -> -7.2898152 | E72: =AVERAGE(OFFSET(E$6,4*(ROW()-ROW(E$71)),0, 4, 1)) -> -9.8563726 | F72: =AVERAGE(OFFSET(F$6,4*(ROW()-ROW(F$71)),0, 4, 1)) -> 1.0288594 | G72: =AVERAGE(OFFSET(G$6,4*(ROW()-ROW(G$71)),0, 4, 1)) -> 1.5235723
B73: 2021-22 | C73: =AVERAGE(OFFSET(C$6,4*(ROW()-ROW(C$71)),0, 4, 1)) -> 2.0797639 | D73: =AVERAGE(OFFSET(D$6,4*(ROW()-ROW(D$71)),0, 4, 1)) -> 12.064223 | E73: =AVERAGE(OFFSET(E$6,4*(ROW()-ROW(E$71)),0, 4, 1)) -> 21.9515 | F73: =AVERAGE(OFFSET(F$6,4*(ROW()-ROW(F$71)),0, 4, 1)) -> 3.6606671 | G73: =AVERAGE(OFFSET(G$6,4*(ROW()-ROW(G$71)),0, 4, 1)) -> 3.131991
B74: 2022-23 | C74: =AVERAGE(OFFSET(C$6,4*(ROW()-ROW(C$71)),0, 4, 1)) -> 11.271907 | D74: =AVERAGE(OFFSET(D$6,4*(ROW()-ROW(D$71)),0, 4, 1)) -> 80.54358 | E74: =AVERAGE(OFFSET(E$6,4*(ROW()-ROW(E$71)),0, 4, 1)) -> 23.628569 | F74: =AVERAGE(OFFSET(F$6,4*(ROW()-ROW(F$71)),0, 4, 1)) -> 6.534636 | G74: =AVERAGE(OFFSET(G$6,4*(ROW()-ROW(G$71)),0, 4, 1)) -> 6.2873383
B75: 2023-24 | C75: =AVERAGE(OFFSET(C$6,4*(ROW()-ROW(C$71)),0, 4, 1)) -> 11.169458 | D75: =AVERAGE(OFFSET(D$6,4*(ROW()-ROW(D$71)),0, 4, 1)) -> -2.6253932 | E75: =AVERAGE(OFFSET(E$6,4*(ROW()-ROW(E$71)),0, 4, 1)) -> -12.075913 | F75: =AVERAGE(OFFSET(F$6,4*(ROW()-ROW(F$71)),0, 4, 1)) -> 5.5430295 | G75: =AVERAGE(OFFSET(G$6,4*(ROW()-ROW(G$71)),0, 4, 1)) -> 6.5994133
B76: 2024-25 | C76: =AVERAGE(OFFSET(C$6,4*(ROW()-ROW(C$71)),0, 4, 1)) -> 3.1788239 | D76: =AVERAGE(OFFSET(D$6,4*(ROW()-ROW(D$71)),0, 4, 1)) -> -16.33373 | E76: =AVERAGE(OFFSET(E$6,4*(ROW()-ROW(E$71)),0, 4, 1)) -> -4.1129092 | F76: =AVERAGE(OFFSET(F$6,4*(ROW()-ROW(F$71)),0, 4, 1)) -> 1.5154887 | G76: =AVERAGE(OFFSET(G$6,4*(ROW()-ROW(G$71)),0, 4, 1)) -> 5.3506695
B77: 2025-26 | C77: =AVERAGE(OFFSET(C$6,4*(ROW()-ROW(C$71)),0, 4, 1)) -> 4.5170569 | D77: =AVERAGE(OFFSET(D$6,4*(ROW()-ROW(D$71)),0, 4, 1)) -> 6.1980054 | E77: =AVERAGE(OFFSET(E$6,4*(ROW()-ROW(E$71)),0, 4, 1)) -> -3.2114445 | F77: =AVERAGE(OFFSET(F$6,4*(ROW()-ROW(F$71)),0, 4, 1)) -> 1.4412883 | G77: =AVERAGE(OFFSET(G$6,4*(ROW()-ROW(G$71)),0, 4, 1)) -> 5.0615216
B78: 2026-27 | C78: =AVERAGE(OFFSET(C$6,4*(ROW()-ROW(C$71)),0, 4, 1)) -> 3.0196257 | D78: =AVERAGE(OFFSET(D$6,4*(ROW()-ROW(D$71)),0, 4, 1)) -> 2.1760836 | E78: =AVERAGE(OFFSET(E$6,4*(ROW()-ROW(E$71)),0, 4, 1)) -> 27.26901 | F78: =AVERAGE(OFFSET(F$6,4*(ROW()-ROW(F$71)),0, 4, 1)) -> 1.1795006 | G78: =AVERAGE(OFFSET(G$6,4*(ROW()-ROW(G$71)),0, 4, 1)) -> 3.6482275
